Workbook

Sheet 客户基础数据
A1: 序号 | B1: 客户编号 | C1: 中文名称 | D1: 越南名称 | E1: 英文名称 | F1: 简称 | G1: 税号 | H1: 公司地址(VN) | I1: 公司电话 | J1: Người đại diện theo pháp luật: | K1: 公司法人代表（中文） | L1: Chức vụ: | M1: 代表职位（中文） | N1: 仓库地址 | O1: 仓库联系人 | P1: 联系方式 | Q1: 港口/关口 | R1: 送货时间 | S1: 运输问题 | T1: 财务联系人 | U1: 财务联系方式 | V1: 邮箱 | W1: 客户编号 | X1: 银行 | Y1: 银行 | Z1: 银行账号 | AA1: 海天销售 | AB1: 其他 | AC1: 快递 | AD1: 中文翻译地址 | AE1: 备注 | AF1: 经销商协议付款条款
A2: 1 | B2: 2141010050 | C2: 越南俊芳进出口销售贸易公司 | D2: CÔNG TY TNHH THƯƠNG MẠI XUẤT NHẬP KHẨU TUẤN PHƯƠNG | E2: CONG TY TNHH THUONG MAI XUAT NHAP KHAU TUAN PHUONG | F2: 俊芳 | G2: 0108272471 | H2: Số 77 Phố Hàm Tử Quan, Phường Phúc Tân, Quận Hoàn Kiếm, Thành phố Hà Nội, Việt Nam | I2: 984968999 | J2: Bùi Tuyết Chinh | K2: Bui Tuyet Chinh | L2: GIÁM ĐỐC | M2: 经理 | N2: Khu khả lễ.phường võ cường. Thành phố bắc ninh | O2: Anh Thành Tuấn Phương | P2: 098 4968999 | Q2: CHI MA, LANG SON，VIETNAM/HAIPHONG ,VIETNAM | R2: 每天晚上10点 | W2: =B2 -> 2141010050 | X2: Ngân hàng TMCP Kỹ thương Việt Nam（Techcombank ) | Y2: 越南科技商业股份银行（Techcombank ) | Z2: 1903720864017 | AA2: 郑明黄 | AC2: 098 4968999， a Thành ，1138 nguyễn khoái. Lĩnh nam. Hoàng mai. | AD2: 越南河内市还剑郡福新坊咸子关街77号 | AF2: 不作为一级经销商合作。Không hợp tác với tư cách nhà phân phối cấp 1. | AG2: =VLOOKUP(B2,'[1]Danh sách khách hàng'!$B:$G,6,FALSE) -> Số 77 Phố Hàm Tử Quan, Phường Phúc Tân, Quận Hoàn Kiếm, Thành phố Hà Nội, Việt Nam
A3: 2 | B3: 2141050030 | C3: 越南平明果蔬有限公司 | D3: CÔNG TY TNHH RAU QUẢ BÌNH MINH VIỆT NAM | E3: CONG TY TNHH RAU QUA BINH MINH VIET NAM | F3: 黎明水果 | G3: 0201640232 | H3: Tờ bản đồ số 15, Tổ dân phố Hạ, Phường An Hưng, Quận Hồng Bàng, Thành phố Hải Phòng, Việt Nam | I3: 0225.3528323 | J3: Ông NGUYỄN THÀNH TRUNG | K3: NGUYEN THANH TRUNG | L3: GIÁM ĐỐC | M3: 经理 | N3: Tờ bản đồ số 15, Thôn Hạ, Xã An Hưng, Huyện An Dương, Thành phố Hải Phòng, Việt Nam | O3: Anh Trung | P3: 090 4288089 | Q3: HAIPHONG ,VIETNAM | R3: 经常 | V3: rauquabinhminhvietnam@gmail.com | W3: =B3 -> 2141050030 | X3: Vietcombank - chi nhánh Nam Hải Phòng | Y3: 越南商业银行 - 南海防分行 | Z3: 1031 000 000 456 | AA3: 郑明黄 | AC3: 090 4288089 ，a Trung ， tờ bản đồ số 15, thôn Hạ, xã An Hưng, huyện An Dương, thành phố Hải Phòng. | AD3: 越南海防市鸿庞郡安兴坊下居民组第15号地图块 | AF3: 不作为一级经销商合作。Không hợp tác với tư cách nhà phân phối cấp 1. | AG3: =VLOOKUP(B3,'[1]Danh sách khách hàng'!$B:$G,6,FALSE) -> Tờ bản đồ số 15, Tổ dân phố Hạ, Phường An Hưng, Quận Hồng Bàng, Thành phố Hải Phòng, Việt Nam
A4: 3 | B4: 2141020110 | C4: 越南黄天发贸易有限公司 | D4: CÔNG TY TNHH THƯƠNG MẠI HOÀNG THIÊN PHÁT | E4: CONG TY TNHH THUONG MAI HOANG THIEN PHAT | F4: 黄天发 | G4: 0316353410 | H4: 387 Phan Văn Trị, Phường Bình Lợi Trung, TP Hồ Chí Minh, Việt Nam. | I4: 0939368123 | J4: TRAN MINH HOANG | K4: 陈明黄 | L4: TỔNG GIÁM ĐỐC | M4: 总经理 | N4: 189 nguyễn oanh p10 gò vấp， hcmc | O4: Hoàng | P4: 937778293 | Q4: CAT LAI PORT ,HO CHI MINH,VIETNAM | R4: 军区附近，每天晚上10点 | S4: 仓库与卸货点较远 | T4: Chị Liễu | U4: 906887847 | V4: Hoangthienphat368@gmail.com | W4: =B4 -> 2141020110 | X4: Ngân hàng TMCP Á Châu (ACB) | Y4: 亚洲贸易股份银行（ACB) | Z4: 1363638888 | AA4: 朱建君 | AD4: 越南胡志明市平盛郡潘文治路387号 | AF4: 订单生效之日起3个工作日内，乙方应支付订单金额的【50】%作为预付款；自产品到达越南目的港/站后3个工作日内，乙方应支付订单金额剩余的全部款项。甲方将在收到订单100%款项后送货到乙方指定的收货地点。 Trong vòng 03 ngày làm việc kể từ ngày đơn hàng có hiệu lực, Bên Mua phải thanh toán 【50】% giá trị đơn hàng dưới hình thức tiền tạm ứng; trong vòng 03 ngày làm việc kể từ ngày sản phẩm đến cảng/ga đích tại Việt Nam, Bên Mua phải thanh toán toàn bộ số tiền còn lại của đơn hàng. Bên Bán sẽ giao hàng đến địa điểm nhận hàng do Bên Mua chỉ định sau khi nhận được 100% giá trị thanh toán của đơn hàng. | AG4: =VLOOKUP(B4,'[1]Danh sách khách hàng'!$B:$G,6,FALSE) -> 387 Phan Văn Trị, Phường Bình Lợi Trung, TP Hồ Chí Minh, Việt Nam.
A5: 4 | B5: 2141030020 | C5: 越南谅山龙霞一成员有限公司 | D5: CÔNG TY TNHH MTV XUẤT NHẬP KHẨU HƯƠNG THỊNH LS | E5: CONG TY TNHH MTV XUAT NHAP KHAU HUONG THINH LS | F5: 龙霞 | G5: 4900905841 | H5: Số 132 đường Trần Phú, Phường Kỳ Lừa, Tỉnh Lạng Sơn, Việt Nam. | I5: 0357584099 | J5: Đỗ Thị Kim Anh | K5: Do Thi Kim Anh | L5: TỔNG GIÁM ĐỐC | M5: 总经理 | N5: 132 đường Trần Phú thành phố Lạng Sơn | O5: Anh Long | P5: 942854827 | Q5: HUU NGHI, LANG SON ,VIETNAM | R5: 经常 | V5: dothikimanh2801@gmail.com | W5: =B5 -> 2141030020 | X5: Ngân hàng Sài Gòn Thương Tín (STB) | Y5: 越南西贡商业银行 | Z5: 30093866491 | AA5: 阮文忠 | AD5: 越南谅山省谅山市奇劳坊陈富路132号 | AF5: 订单生效之日起3个工作日内，乙方应支付订单金额的【50】%作为预付款；自产品到达越南目的港/站后3个工作日内，乙方应支付订单金额剩余的全部款项。甲方将在收到订单100%款项后送货到乙方指定的收货地点。 Trong vòng 03 ngày làm việc kể từ ngày đơn hàng có hiệu lực, Bên Mua phải thanh toán 【50】% giá trị đơn hàng dưới hình thức tiền tạm ứng; trong vòng 03 ngày làm việc kể từ ngày sản phẩm đến cảng/ga đích tại Việt Nam, Bên Mua phải thanh toán toàn bộ số tiền còn lại của đơn hàng. Bên Bán sẽ giao hàng đến địa điểm nhận hàng do Bên Mua chỉ định sau khi nhận được 100% giá trị thanh toán của đơn hàng. | AG5: =VLOOKUP(B5,'[1]Danh sách khách hàng'!$B:$G,6,FALSE) -> Số 132 đường Trần Phú, Phường Kỳ Lừa, Tỉnh Lạng Sơn, Việt Nam.
A6: 5 | B6: 2141010070 | C6: 越南食品进出口服务贸易有限公司 | D6: CÔNG TY TNHH THƯƠNG MẠI DỊCH VỤ XUẤT NHẬP KHẨU VIỆT FOODS | E6: CONG TY TNHH THUONG MAI DICH VU XUAT NHAP KHAU VIET FOODS | F6: 新俊芳 | G6: 0110615246 | H6: Thôn Đông Trạch, Xã Nam Phù, TP Hà Nội, Việt Nam. | I6: 0966506434 | J6: Nguyễn Đức Thành | K6: Nguyen Duc Thanh | L6: GIÁM ĐỐC | M6: 经理 | N6: Khu khả lễ.phường võ cường. Thành phố bắc ninh | O6: Anh Thành Tuấn Phương | P6: 098 4968999 | Q6: CHI MA, LANG SON，VIETNAM/HAIPHONG ,VIETNAM | R6: 每天晚上10点 0363333888-Binh - Kho hàng | V6: congtyvietfood68@gmail.com | W6: =B6 -> 2141010070 | X6: Ngân hàng TMCP Đầu tư và Phát triển Việt Nam (BIDV) | Y6: 越南投资和发展股份制商业银行（BIDV） | Z6: 8600022041 | AA6: 郑明黄 | AD6: 越南河内市南扶乡东泽村 | AF6: 不作为一级经销商合作。Không hợp tác với tư cách nhà phân phối cấp 1. | AG6: =VLOOKUP(B6,'[1]Danh sách khách hàng'!$B:$G,6,FALSE) -> Thôn Đông Trạch, Xã Nam Phù, TP Hà Nội, Việt Nam.
A7: 6 | B7: 2141110010 | C7: 越南阮氏娇庄 | D7: NGUYỄN THỊ KIỀU TRANG | E7: NGUYEN THI KIEU TRANG | F7: 阮氏娇庄 | G7: 8712031066-001 | H7: Số 77, Nguyễn Tất Thành, Phường Khai Quang, Thành phố Vĩnh Yên, Tỉnh Vĩnh Phúc, Việt Nam | I7: 0365634443 | J7: Nguyễn Thị Kiều Trang | K7: Nguyen Thi Kieu Trang | L7: GIÁM ĐỐC | M7: 经理 | N7: 77 Nguyễn Tất Thành, P. Khai Quang, TP Vĩnh Yên, tỉnh Vĩnh Phúc | Q7: HAIPHONG ,VIETNAM | R7: 经常 | W7: =B7 -> 2141110010 | X7: Ngân hàng Teckcombank -NGUYEN THI KIEU TRANG | Y7: 越南科技商业股份银行（Techcombank ) | Z7: 9036821692011 | AA7: 阮文忠 | AC7: 永福 | AD7: 越南永福省永安市开光坊阮必成路77号 | AF7: 不作为一级经销商合作。Không hợp tác với tư cách nhà phân phối cấp 1. | AG7: =VLOOKUP(B7,'[1]Danh sách khách hàng'!$B:$G,6,FALSE) -> Số 77, Nguyễn Tất Thành, Phường Khai Quang, Thành phố Vĩnh Yên, Tỉnh Vĩnh Phúc, Việt Nam
A8: 7 | B8: 2141090020 | C8: 越南武德贵 | D8: VŨ ĐỨC QUÝ | E8: VU DUC QUY | F8: 武德贵 | H8: Ngõ 276, khối 1 , Vĩnh Tân , thành phố Vinh, Nghệ An | I8: 0968416361 | J8: VŨ ĐỨC QUÝ | K8: VU DUC QUY | N8: Khối 1 (nhà ông Nguyễn Văn Hưng, thửa đất số 668, tờ bản đồ số 06) phường Vinh Tân, thành phố Vinh, tỉnh Nghệ An | Q8: HAIPHONG ,VIETNAM | R8: 经常 | W8: =B8 -> 2141090020 | X8: Vietcombank trự sở CN Nghệ An | Y8: 越南商业银行 - 乂安分行 | Z8: 0101001169857 / Nguyễn Thị Nguyệt | AA8: 郑明黄 | AC8: 义安 | AD8: 越南乂安省荣市永新坊第1街区276号巷 | AF8: 不作为一级经销商合作。Không hợp tác với tư cách nhà phân phối cấp 1. | AG8: =VLOOKUP(B8,'[1]Danh sách khách hàng'!$B:$G,6,FALSE) -> Ngõ 276, khối 1 , Vĩnh Tân , thành phố Vinh, Nghệ An
A9: 8 | B9: 2141100020 | C9: 越南天龙发有限公司 | D9: CÔNG TY TNHH THIÊN LONG PHÁT VN | E9: CONG TY TNHH THIEN LONG PHAT VN | F9: 天龙发 | G9: 3703171766 | H9: Số 170A, Đường Số 1, Khu 2, Phường Hoà Phú, Thành phố Thủ Dầu Một, Tỉnh Bình Dương, Việt Nam | I9: 0373098579 | J9: Lê Mộng Kha | K9: 黎梦珂 | L9: GIÁM ĐỐC | M9: 总经理 | N9: VSIP2 Đường D4, Tổ 1, KP1, Vĩnh Tân, Tân Uyên, Bình Dương | P9: 866471453 | Q9: CAT LAI PORT ,HO CHI MINH,VIETNAM | R9: 经常 | W9: =B9 -> 2141100020 | X9: Ngân hàng TMCP công thương Việt Nam,Chi nhánh KCN Bình Dương | Y9: 越南工商银行平阳工业区分行 | Z9: 111002958480 | AA9: 朱建君 | AD9: 越南平阳省土龙木市和富坊第2区1号路170A号 | AF9: 不作为一级经销商合作。Không hợp tác với tư cách nhà phân phối cấp 1. | AG9: =VLOOKUP(B9,'[1]Danh sách khách hàng'!$B:$G,6,FALSE) -> Số 170A, Đường Số 1, Khu 2, Phường Hoà Phú, Thành phố Thủ Dầu Một, Tỉnh Bình Dương, Việt Nam
A10: 9 | B10: 2141030030 | C10: 越南青青有限责任公司 | D10: CÔNG TY TNHH KINH DOANH THƯƠNG MẠI THANH THANH | E10: CONG TY TNHH KINH DOANH THUONG MAI THANH THANH | F10: 青青 | G10: 4900891726 | H10: Số 164, đường Hoàng Văn Thụ, khu Lò Rèn, Thị trấn Đồng Đăng, Huyện Cao Lộc, Tỉnh Lạng Sơn, Việt Nam | J10: Hà Thị Thanh | K10: Ha Thi Thanh | L10: GIÁM ĐỐC | M10: 经理 | N10: Số 164, đường Hoàng Văn Thụ, khu Lò Rèn, Thị trấn Đồng Đăng, Huyện Cao Lộc, Tỉnh Lạng Sơn, Việt Nam | P10: ‘0352139888 | Q10: HUU NGHI, LANG SON ,VIETNAM | R10: 经常 | W10: =B10 -> 2141030030 | X10: Ngân Hàng TMCP Công Thương Việt Nam (Vietinbank) | Y10: 越南工商银行 | Z10: 115604323999 | AA10: 阮文忠 | AD10: 越南谅山省高禄县同登市镇炉炼区黄文树路164号 | AF10: 不作为一级经销商合作。Không hợp tác với tư cách nhà phân phối cấp 1. | AG10: =VLOOKUP(B10,'[1]Danh sách khách hàng'!$B:$G,6,FALSE) -> Số 164, đường Hoàng Văn Thụ, khu Lò Rèn, Thị trấn Đồng Đăng, Huyện Cao Lộc, Tỉnh Lạng Sơn, Việt Nam
A11: 10 | B11: 2141020030 | C11: 越南味丹股份有限公司（总部-总仓） | D11: CÔNG TY CỔ PHẦN HỮU HẠN VEDAN VIỆT NAM | E11: CONG TY CO PHAN HUU HAN VEDAN VIET NAM | F11: 味丹 | G11: 3600239719 | H11: Quốc lộ 51, Ấp 1A, Xã Phước Thái, Đồng Nai, Việt Nam. | J11: TANG DAW SEN | K11: TANG DAW SEN | L11: GIÁM ĐỐC | M11: 总经理 | N11: Quốc lộ 51, Ấp 1A, Xã Phước Thái, Huyện Long Thành, Tỉnh Đồng Nai, Việt Nam. | Q11: CAT LAI PORT ,HO CHI MINH,VIETNAM | R11: 经常 | V11: huyen-tt@vedaninternational.com | W11: =B11 -> 2141020030 | AA11: 朱建君 | AD11: 越南同奈省福泰乡1A邑51号国道 | AF11: 订单生效之日起14个工作日内，乙方应支付订单金额的【100】%作为预付款；自产品到达越南目的港/站后3个工作日内，乙方应支付订单金额剩余的全部款项。甲方将在收到订单100%款项后送货到乙方指定的收货地点。 Trong vòng 14 ngày làm việc kể từ ngày đơn hàng có hiệu lực, Bên Mua phải thanh toán 【100】% giá trị đơn hàng dưới hình thức tiền tạm ứng; trong vòng 03 ngày làm việc kể từ ngày sản phẩm đến cảng/ga đích tại Việt Nam, Bên Mua phải thanh toán toàn bộ số tiền còn lại của đơn hàng. Bên Bán sẽ giao hàng đến địa điểm nhận hàng do Bên Mua chỉ định sau khi nhận được 100% giá trị thanh toán của đơn hàng. | AG11: =VLOOKUP(B11,'[1]Danh sách khách hàng'!$B:$G,6,FALSE) -> Quốc lộ 51, Ấp 1A, Xã Phước Thái, Đồng Nai, Việt Nam.
A12: 11 | B12: 2141020130 | C12: 越南智越发贸易服务及生产有限公司 | D12: CÔNG TY TNHH THƯƠNG MẠI DỊCH VỤ VÀ SẢN XUẤT TRÍ VIỆT PHÁT | E12: CONG TY TNHH THUONG MAI DICH VU VA SAN XUAT TRI VIET PHAT | F12: 智越发 | G12: 0312096843 | H12: Số 81 Đường Tân Hòa 2, Khu phố 24, Phường Tăng Nhơn Phú, TP Hồ Chí Minh, Việt Nam. | J12: NGUYỄN THỊ VÂN ANH | K12: NGUYEN THI VAN ANH | L12: GIÁM ĐỐC | M12: 总经理 | N12: 178 Đường Long Thuận, Long Phước, TP Thủ Đức, HCM (quận 9 cũ) | O12: Mr. Tân | P12: 0977905020 (kho) | Q12: CAT LAI PORT ,HO CHI MINH,VIETNAM | R12: 经常 | W12: =B12 -> 2141020130 | X12: BIDV-Ngân hàng Thương mại cổ phần Đầu tư và Phát triển Việt Nam- Chi nhánh Đong Sài Gòn | Y12: 越南投资和发展股份制商业银行（BIDV）-东西贡分行 | Z12: 3141324180 | AA12: 朱建君 | AD12: 越南胡志明市增仁富坊24街区新和2路81号 | AF12: 买方（乙方）须在签订采购订单后立即支付订单总金额的 50%，剩余的 50% 款项必须在收货前（卖方交货前）全部付清。买方付款后，须通过电子邮件或在线聊天软件向卖方提供有效的付款凭证；卖方只有在收到足额款项或有效付款凭证后，才会安排生产、检验、检疫及进出口手续。同时，任何因转账产生的费用（包括但不限于中转行费用）均由买方（乙方）承担。 Bên B thanh toán cho Bên A trước 50% tổng giá trị đơn hàng ngay khi ký Đơn đặt hàng, và 50% còn lại thanh toán hết trước khi nhận hàng (trước khi Bên A giao hàng). Sau khi chuyển khoản, Bên B cần cung cấp chứng từ thanh toán hợp lệ qua email hoặc ứng dụng trò chuyện trực tuyến; Bên A chỉ sắp xếp các thủ tục sản xuất, kiểm tra, kiểm dịch, xuất nhập khẩu sau khi nhận đủ số tiền hoặc chứng từ thanh toán này. Đồng thời, bất kỳ khoản phí chuyển khoản nào phát sinh (bao gồm nhưng không giới hạn ở phí ngân hàng trung chuyển) sẽ hoàn toàn do Bên B chịu. | AG12: =VLOOKUP(B12,'[1]Danh sách khách hàng'!$B:$G,6,FALSE) -> Số 81 Đường Tân Hòa 2, Khu phố 24, Phường Tăng Nhơn Phú, TP Hồ Chí Minh, Việt Nam.
A13: 12 | B13: 2141010080 | C13: 越南全德贸易投资有限公司 | D13: CÔNG TY TNHH ĐẦU TƯ THƯƠNG MẠI TOÀN ĐỨC | E13: CONG TY TNHH DAU TU THUONG MAI TOAN DUC | F13: 全德 | G13: 0106667555 | H13: Số 5, ngõ 2 phố Đại Linh, Phường Đại Mỗ, TP Hà Nội, Việt Nam. | I13: 0967260022 | J13: ĐỖ VĂN LƯƠNG | K13: DO VAN LUONG | L13: GIÁM ĐỐC | M13: 总经理 | N13: D06-NV4 ô 033, khu D, KĐT Gleximco - Lê Trọng Tấn, Xã La Phù, Huyện Hoài Đức, Thành Phố Hà Nội, Việt Nam | O13: ĐỖ VĂN LƯƠNG | P13: 0967260022 | Q13: HUU NGHI, LANG SON ,VIETNAM， 未来火车 | R13: 经常 | U13: '0967260022 | V13: toanducfoodhd@gmail.com | W13: =B13 -> 2141010080 | X13: TECHCOMBANK-Ngân hàng Thương mại cổ phần Kỹ Thương Việt Nam | Y13: 越南科技商业股份银行 | Z13: 19128691892686/19028691892010 | AA13: 郑明黄 | AB13: toanducfood@gmail.com 这张邮箱是公司的，邮箱在row V是收到发票 | AD13: 越南河内市大姥坊大灵街2号巷5号 | AF13: 订单生效之日起3个工作日内，乙方应支付订单金额的【50】%作为预付款；自产品到达越南目的港/站后3个工作日内，乙方应支付订单金额剩余的全部款项。甲方将在收到订单100%款项后送货到乙方指定的收货地点。 Trong vòng 03 ngày làm việc kể từ ngày đơn hàng có hiệu lực, Bên Mua phải thanh toán 【50】% giá trị đơn hàng dưới hình thức tiền tạm ứng; trong vòng 03 ngày làm việc kể từ ngày sản phẩm đến cảng/ga đích tại Việt Nam, Bên Mua phải thanh toán toàn bộ số tiền còn lại của đơn hàng. Bên Bán sẽ giao hàng đến địa điểm nhận hàng do Bên Mua chỉ định sau khi nhận được 100% giá trị thanh toán của đơn hàng. | AG13: =VLOOKUP(B13,'[1]Danh sách khách hàng'!$B:$G,6,FALSE) -> Số 5, ngõ 2 phố Đại Linh, Phường Đại Mỗ, TP Hà Nội, Việt Nam.
A14: 13 | B14: 2141070020 | C14: 越南通达发一成员贸易服务有限公司 | D14: CÔNG TY TNHH MTV THƯƠNG MẠI DỊCH VỤ THÔNG ĐẠT PHÁT | E14: CONG TY TNHH MTV THUONG MAI DICH VU THONG DAT PHAT | F14: 通达发 | G14: 3603857255 | H14: 19/5A, tổ 20, Khu Phố 3, Phường Bửu Long, Thành phố Biên Hoà, Tỉnh Đồng Nai, Việt Nam | I14: 0379774123 | J14: CHỀ ÁNH KIM | K14: CHE ANH KIM | L14: GIÁM ĐỐC | M14: 总经理 | N14: Cụm công nghiệp bảy mẫu thị trấn thái hoà thành phố tân uyên tỉnh Bình Dương | O14: Chị Kim | P14: 379774123 | Q14: CAT LAI PORT ,HO CHI MINH,VIETNAM | R14: 经常 | U14: 379774123 | V14: Thongdatphat22@gmail.com | W14: =B14 -> 2141070020 | X14: BIDV-Ngân hàng Thương mại cổ phần Đầu tư và Phát triển Việt Nam | Y14: 越南投资和发展股份制商业银行（BIDV） | Z14: 67210002953995 | AA14: 朱建君 | AD14: 越南同奈省边和市宝龙坊第3街区20组19/5A号 | AF14: 不作为一级经销商合作。Không hợp tác với tư cách nhà phân phối cấp 1. | AG14: =VLOOKUP(B14,'[1]Danh sách khách hàng'!$B:$G,6,FALSE) -> 19/5A, tổ 20, Khu Phố 3, Phường Bửu Long, Thành phố Biên Hoà, Tỉnh Đồng Nai, Việt Nam
A15: 14 | B15: 2141020020 | C15: 越南VP进出口贸易有限公司 | D15: CÔNG TY TNHH THƯƠNG MẠI THỰC PHẨM VINH PHÁT | E15: CONG TY TNHH THUONG MAI THUC PHAM VINH PHAT | F15: 越南VP | G15: 0310487418 | H15: 450/1 Hòa Hảo, Phường Diên Hồng, TP Hồ Chí Minh, Việt Nam. | I15: 08 39245355 | J15: LIÊU BÁ SÂM | K15: LIEU BA SAM | L15: GIÁM ĐỐC | M15: 总经理 | N15: 252/18P Phan Anh, phường Hiệp Tân, quận Tân Phú | O15: Liên hệ Anh Bân : +84 903003877 | P15: 903003877 | Q15: CAT LAI PORT ,HO CHI MINH,VIETNAM | R15: 经常 | W15: =B15 -> 2141020020 | X15: ACB – PGD Hàm Tử | Y15: 亚洲商业银行 | Z15: 810928 | AA15: 朱建君 | AD15: 越南胡志明市演红坊好好路450/1号 | AF15: 订单生效之日起3个工作日内，乙方应支付订单金额的【100】%作为预付款；自产品到达越南目的港/站后3个工作日内，乙方应支付订单金额剩余的全部款项。甲方将在收到订单100%款项后送货到乙方指定的收货地点。 Trong vòng 03 ngày làm việc kể từ ngày đơn hàng có hiệu lực, Bên Mua phải thanh toán 【100】% giá trị đơn hàng dưới hình thức tiền tạm ứng; trong vòng 03 ngày làm việc kể từ ngày sản phẩm đến cảng/ga đích tại Việt Nam, Bên Mua phải thanh toán toàn bộ số tiền còn lại của đơn hàng. Bên Bán sẽ giao hàng đến địa điểm nhận hàng do Bên Mua chỉ định sau khi nhận được 100% giá trị thanh toán của đơn hàng. | AG15: =VLOOKUP(B15,'[1]Danh sách khách hàng'!$B:$G,6,FALSE) -> 450/1 Hòa Hảo, Phường Diên Hồng, TP Hồ Chí Minh, Việt Nam.
A16: 15 | B16: 2141020140 | C16: 越南芳云进出口有限公司 | D16: CÔNG TY TNHH MTV XNK PHONG VÂN | E16: CONG TY TNHH MTV XNK PHONG VAN | F16: 芳云 | G16: 0310196137 | H16: 20 Huỳnh Thị Bảy, Ấp 1, Xã Tân Nhựt, TP Hồ Chí Minh, Việt Nam. | I16: 0905586622 | J16: NGO THI HUONG HOA | K16: NGO THI HUONG HOA | L16: GIÁM ĐỐC | M16: 总经理 | N16: 168 Quang Trung, Phường 10, Gò vấp, TP. Hồ Chí Minh, Việt Nam. | O16: Bùi Thị Thu Hằng | P16: '0905586622 | Q16: CAT LAI PORT ,HO CHI MINH,VIETNAM | R16: 经常 | U16: 905586622 | V16: hoadon@phongvanfc.com | W16: =B16 -> 2141020140 | X16: Ngân hàng TMCP Công Thương Việt Nam(Vietinbank) – Chi nhánh 8 | Y16: 越南工商银行-第8分行 | Z16: 118002711993 | AA16: 朱建君 | AD16: 越南胡志明市新日乡1邑黄氏七路20号 | AF16: 订单生效之日起3个工作日内，乙方应支付订单金额的【50】%作为预付款；自产品到达越南目的港/站后3个工作日内，乙方应支付订单金额剩余的全部款项。甲方将在收到订单100%款项后送货到乙方指定的收货地点。 Trong vòng 03 ngày làm việc kể từ ngày đơn hàng có hiệu lực, Bên Mua phải thanh toán 【50】% giá trị đơn hàng dưới hình thức tiền tạm ứng; trong vòng 03 ngày làm việc kể từ ngày sản phẩm đến cảng/ga đích tại Việt Nam, Bên Mua phải thanh toán toàn bộ số tiền còn lại của đơn hàng. Bên Bán sẽ giao hàng đến địa điểm nhận hàng do Bên Mua chỉ định sau khi nhận được 100% giá trị thanh toán của đơn hàng. | AG16: =VLOOKUP(B16,'[1]Danh sách khách hàng'!$B:$G,6,FALSE) -> 20 Huỳnh Thị Bảy, Ấp 1, Xã Tân Nhựt, TP Hồ Chí Minh, Việt Nam.
A17: 16 | B17: 2141010090 | C17: 越南食品进出口服务贸易有限公司（工业） | D17: CÔNG TY TNHH THƯƠNG MẠI DỊCH VỤ XUẤT NHẬP KHẨU VIỆT FOODS(CÔNG NGHIỆP) | E17: CONG TY TNHH THUONG MAI DICH VU XUAT NHAP KHAU VIET FOODS | F17: 新俊芳 | G17: 0110615246 | H17: Thôn Đông Trạch, Xã Nam Phù, TP Hà Nội, Việt Nam | I17: 0966506434 | J17: Nguyễn Đức Thành | K17: Nguyen Duc Thanh | L17: GIÁM ĐỐC | M17: 经理 | N17: Khu khả lễ.phường võ cường. Thành phố bắc ninh | O17: Anh Thành Tuấn Phương | P17: 984968999 | Q17: CHI MA, LANG SON，VIETNAM/HAIPHONG ,VIETNAM | R17: 每天晚上10点 | S17: 0 | U17: 0 | V17: congtyvietfood68@gmail.com | W17: =B17 -> 2141010090 | X17: Ngân hàng TMCP Đầu tư và Phát triển Việt Nam (BIDV) | Y17: 越南投资和发展股份制商业银行（BIDV） | Z17: 8600022041 | AA17: 郑明黄 | AB17: 0 | AC17: 0 | AD17: 越南河内市南扶乡东泽村 | AF17: 不作为一级经销商合作。Không hợp tác với tư cách nhà phân phối cấp 1. | AG17: =VLOOKUP(B17,'[1]Danh sách khách hàng'!$B:$G,6,FALSE) -> Thôn Đông Trạch, Xã Nam Phù, TP Hà Nội, Việt Nam
A18: 17 | B18: 2141020160 | C18: 越南诺萨食品股份公司（工业） | D18: CÔNG TY CỔ PHẦN NOSAFOOD(CÔNG NGHIỆP) | E18: NOSAFOOD JOINT STOCK COMPANY | F18: NOSAFOOD(工业) | G18: 0303841040 | H18: E4/20 Nguyễn Hữu Trí, Xã Tân Nhựt, Thành phố Hồ Chí Minh, Việt Nam. | I18: 02862728888 | J18: HO JOONG | K18: HO JOONG | L18: GIÁM ĐỐC | M18: 总经理 | N18: Lô D3/1-4 đường VL7, KCN Vĩnh Lộc 2, xã Long Hiệp, huyện Bến Lức, Long An (cổng KCN đi thẳng đến cuối đường rẽ trái, đi tiếp đến cuối đường) | Q18: CAT LAI PORT ,HO CHI MINH,VIETNAM | R18: 经常 | T18: 0919931349 Ngọc | V18: hanhchinh@nosafood.com | W18: =B18 -> 2141020160 | X18: Ngân hàng Agribank, CN Nam Sài Gòn | Y18: 农业银行南西贡支行（VBAAVNVX） | Z18: 6160201014420 | AA18: 朱建君 | AD18: 越南胡志明市新日乡阮友智路E4/20号 | AF18: 不作为一级经销商合作。Không hợp tác với tư cách nhà phân phối cấp 1. | AG18: =VLOOKUP(B18,'[1]Danh sách khách hàng'!$B:$G,6,FALSE) -> E4/20 Nguyễn Hữu Trí, Xã Tân Nhựt, Thành phố Hồ Chí Minh, Việt Nam.
A19: 18 | B19: 2141020150 | C19: 越南诺萨食品股份公司（OEM） | D19: CÔNG TY CỔ PHẦN NOSAFOOD(OEM) | E19: NOSAFOOD JOINT STOCK COMPANY | F19: NOSAFOOD(OEM) | G19: 0303841040 | H19: E4/20 Nguyễn Hữu Trí, Thị Trấn Tân Túc, Huyện Bình Chánh, Thành phố Hồ Chí Minh, Việt Nam | I19: 02862728888 | J19: HO JOONG | K19: HO JOONG | L19: GIÁM ĐỐC | M19: 总经理 | N19: Lô D3/1-4 đường VL7, KCN Vĩnh Lộc 2, xã Long Hiệp, huyện Bến Lức, Long An (cổng KCN đi thẳng đến cuối đường rẽ trái, đi tiếp đến cuối đường) | Q19: CAT LAI PORT ,HO CHI MINH,VIETNAM | R19: 经常 | V19: hanhchinh@nosafood.com | W19: =B19 -> 2141020150 | X19: Ngân hàng Agribank, CN Nam Sài Gòn | Y19: 农业银行南西贡支行（VBAAVNVX） | Z19: 6160201014420 | AA19: 朱建君 | AD19: 越南胡志明市平政县新足市镇阮友智路E4/20号 | AF19: 不作为一级经销商合作。Không hợp tác với tư cách nhà phân phối cấp 1. | AG19: =VLOOKUP(B19,'[1]Danh sách khách hàng'!$B:$G,6,FALSE) -> E4/20 Nguyễn Hữu Trí, Thị Trấn Tân Túc, Huyện Bình Chánh, Thành phố Hồ Chí Minh, Việt Nam
A20: 19 | B20: 2141010110 | C20: 越南同心投资贸易有限公司 | D20: CÔNG TY TNHH ĐẦU TƯ VÀ THƯƠNG MẠI ĐỒNG TÂM | F20: 同心 | G20: 0105032376 | H20: Số 12, ngách 12, ngõ 23, phố Bồ Đề, tổ 5, Phường Bồ Đề, TP Hà Nội, Việt Nam. | J20: VƯƠNG THỊ THU THỦY | K20: VUONG THI THU THUY | L20: GIÁM ĐỐC | M20: 总经理 | N20: Phường Bồ Đề, quận Long Biên, thành phố Hà Nội, Việt Nam | O20: Ms Duyên | P20: . 0376654989 . | V20: salesdongtamfood@gmail.com | W20: =B20 -> 2141010110 | AA20: 郑明黄 | AD20: 越南河内市菩提坊第5组菩提街23号巷12支巷12号 | AF20: 不作为一级经销商合作。Không hợp tác với tư cách nhà phân phối cấp 1. | AG20: =VLOOKUP(B20,'[1]Danh sách khách hàng'!$B:$G,6,FALSE) -> Số 12, ngách 12, ngõ 23, phố Bồ Đề, tổ 5, Phường Bồ Đề, TP Hà Nội, Việt Nam.
A21: 20 | C21: 越南新绿食品有限公司 | D21: CÔNG TY TNHH NEW GREEN FOOD | E21: CONG TY TNHH NEW GREEN FOOD | F21: MISA新绿食品 | G21: 201878595 | H21: #N/A | I21: 02258831983 | J21: NGUYEN THANH LONG | K21: NGUYEN THANH LONG | L21: GIÁM ĐỐC | M21: 总经理 | T21: Ms Thương | U21: 971350969 | V21: lanhuonght88.hp@gmail.com | W21: =B21 -> 0 | AD21: #N/A | AF21: 不作为一级经销商合作。Không hợp tác với tư cách nhà phân phối cấp 1. | AG21: =VLOOKUP(B21,'[1]Danh sách khách hàng'!$B:$G,6,FALSE) -> #N/A
A22: 21 | B22: 2141010100 | C22: 越南安库生产贸易和服务有限公司 | D22: CÔNG TY TNHH SẢN XUẤT THƯƠNG MẠI VÀ DỊCH VỤ AN KHUÊ | F22: AN KHUE 安库 | G22: 0110318349 | H22: Số 36, Đường Long Biên 2, Phường Bồ Đề, TP Hà Nội, Việt Nam. | I22: 086 9813026 | J22: TRỊNH NGỌC MINH | K22: TRINH NGOC MINH | L22: GIÁM ĐỐC | M22: 总经理 | N22: Số 374A đường Hùng Vương, phường Hùng Vương, quận Hồng Bàng, thành phố Hải Phòng, Việt Nam: 086 9813026: 9,840 kg——40箱 | W22: =B22 -> 2141010100 | AD22: 越南河内市菩提坊龙编2路36号 | AF22: 不作为一级经销商合作。Không hợp tác với tư cách nhà phân phối cấp 1. | AG22: =VLOOKUP(B22,'[1]Danh sách khách hàng'!$B:$G,6,FALSE) -> Số 36, Đường Long Biên 2, Phường Bồ Đề, TP Hà Nội, Việt Nam.
A23: 22 | C23: 黄天发（胡志明工业客户-番茄酱） | H23: #N/A | L23: GIÁM ĐỐC | M23: 总经理 | N23: 189 nguyễn oanh p10 gò vấp， hcmc：Anh Hoàng : 0937778293 : 1,968kg——8箱 | W23: =B23 -> 0 | AD23: #N/A | AF23: 不作为一级经销商合作。Không hợp tác với tư cách nhà phân phối cấp 1. | AG23: =VLOOKUP(B23,'[1]Danh sách khách hàng'!$B:$G,6,FALSE) -> #N/A
A24: 23 | B24: 2141110020 | C24: 越南惠嘉进出口有限公司 | D24: CÔNG TY TNHH MTV XUẤT NHẬP KHẨU HUỆ GIA | E24: CONG TY TNHH MTV XUAT NHAP KHAU HUE GIA | F24: 惠嘉 | G24: 2500728577 | H24: Số 136, đường Tôn Đức Thắng, Phường Vĩnh Phúc, Phú Thọ, Việt Nam. | J24: Nguyễn Thị Kiều Trang | K24: Nguyen Thi Kieu Trang | L24: GIÁM ĐỐC | M24: 总经理 | N24: 77 Nguyễn Tất Thành, P. Khai Quang, TP Vĩnh Yên, tỉnh Vĩnh Phúc | T24: Nguyễn Thị Kiều Trang | V24: kieutrang281097@gmail.com | W24: =B24 -> 2141110020 | X24: Nngân hàng TMCP Công thương Việt Nam chi nhánh Vĩnh Phúc | Y24: 越南工商银行永福分行 | Z24: 111601221555 | AA24: 阮文忠 | AD24: 越南富寿省永福坊孙德胜路136号 | AF24: 订单生效之日起3个工作日内，乙方应支付订单金额的【50】%作为预付款；自产品到达越南目的港/站后3个工作日内，乙方应支付订单金额剩余的全部款项。甲方将在收到订单100%款项后送货到乙方指定的收货地点。 Trong vòng 03 ngày làm việc kể từ ngày đơn hàng có hiệu lực, Bên Mua phải thanh toán 【50】% giá trị đơn hàng dưới hình thức tiền tạm ứng; trong vòng 03 ngày làm việc kể từ ngày sản phẩm đến cảng/ga đích tại Việt Nam, Bên Mua phải thanh toán toàn bộ số tiền còn lại của đơn hàng. Bên Bán sẽ giao hàng đến địa điểm nhận hàng do Bên Mua chỉ định sau khi nhận được 100% giá trị thanh toán của đơn hàng. | AG24: =VLOOKUP(B24,'[1]Danh sách khách hàng'!$B:$G,6,FALSE) -> Số 136, đường Tôn Đức Thắng, Phường Vĩnh Phúc, Phú Thọ, Việt Nam.
A25: 24 | B25: 2141100030 | C25: 越南邻客贸易有限公司 | D25: CÔNG TY TNHH THƯƠNG MẠI LIN KE | G25: 3703139459 | H25: HT1-1B Lô F8,F9, Đường Bùi Thị Xuân, Khu Đô Thị Mới, Phường Bình Dương, TP Hồ Chí Minh, Việt Nam. | I25: '0528062362 | J25: NGUYỄN THỊ LAN | K25: NGUYEN THI LAN | L25: GIÁM ĐỐC | M25: 总经理 | N25: Số 49, Đường Truông Bồng Bông, Phường Định Hòa, Thành phố Thủ Dầu Một, Tỉnh Bình Dương | P25: '0899021119 | V25: congtytnhhlinke@gmail.com | W25: =B25 -> 2141100030 | X25: Ngân hàng Vietcombank-chi nhánh Đông Bình Dương | Y25: 越南商业银行-东平阳分行 | Z25: 1039912723 | AA25: 朱建君 | AD25: 越南胡志明市平阳坊新市区裴氏春路F8、F9地块HT1-1B | AF25: 订单生效之日起3个工作日内，乙方应支付订单金额的【50】%作为预付款；自产品到达越南目的港/站后3个工作日内，乙方应支付订单金额剩余的全部款项。甲方将在收到订单100%款项后送货到乙方指定的收货地点。 Trong vòng 03 ngày làm việc kể từ ngày đơn hàng có hiệu lực, Bên Mua phải thanh toán 【50】% giá trị đơn hàng dưới hình thức tiền tạm ứng; trong vòng 03 ngày làm việc kể từ ngày sản phẩm đến cảng/ga đích tại Việt Nam, Bên Mua phải thanh toán toàn bộ số tiền còn lại của đơn hàng. Bên Bán sẽ giao hàng đến địa điểm nhận hàng do Bên Mua chỉ định sau khi nhận được 100% giá trị thanh toán của đơn hàng. | AG25: =VLOOKUP(B25,'[1]Danh sách khách hàng'!$B:$G,6,FALSE) -> HT1-1B Lô F8,F9, Đường Bùi Thị Xuân, Khu Đô Thị Mới, Phường Bình Dương, TP Hồ Chí Minh, Việt Nam.
A26: 25 | B26: 2141030060 | C26: 越南荷青综合贸易有限公司 | D26: CÔNG TY TNHH KINH DOANH TỔNG HỢP HÀ THANH | E26: CONG TY TNHH KINH DOANH TONG HOP HA THANH | F26: 荷青 | G26: 4900918008 | H26: Số 75, đường Hoàng Văn Thụ, khu Lò Rèn, Xã Đồng Đăng, Lạng Sơn, Việt Nam. | I26: ‘0969049348 | J26: HÀ THỊ THANH | K26: HA THI THANH | L26: GIÁM ĐỐC | M26: 总经理 | N26: Số 164, đường Hoàng Văn Thụ, khu Lò Rèn, Thị trấn Đồng Đăng, Huyện Cao Lộc, Tỉnh Lạng Sơn, Việt Nam | V26: ctyhathanh8689@gmail.com. | W26: =B26 -> 2141030060 | X26: Ngân Hàng TMCP Công Thương Việt Nam CN LẠNG SƠN -PGD ĐỒNG ĐĂNG | Z26: 118190139999 | AA26: 阮文忠 | AD26: 越南谅山省同登乡炉炼区黄文树路75号 | AF26: 订单生效之日起3个工作日内，乙方应支付订单金额的【50】%作为预付款；自产品到达越南目的港/站后3个工作日内，乙方应支付订单金额剩余的全部款项。甲方将在收到订单100%款项后送货到乙方指定的收货地点。 Trong vòng 03 ngày làm việc kể từ ngày đơn hàng có hiệu lực, Bên Mua phải thanh toán 【50】% giá trị đơn hàng dưới hình thức tiền tạm ứng; trong vòng 03 ngày làm việc kể từ ngày sản phẩm đến cảng/ga đích tại Việt Nam, Bên Mua phải thanh toán toàn bộ số tiền còn lại của đơn hàng. Bên Bán sẽ giao hàng đến địa điểm nhận hàng do Bên Mua chỉ định sau khi nhận được 100% giá trị thanh toán của đơn hàng. | AG26: =VLOOKUP(B26,'[1]Danh sách khách hàng'!$B:$G,6,FALSE) -> Số 75, đường Hoàng Văn Thụ, khu Lò Rèn, Xã Đồng Đăng, Lạng Sơn, Việt Nam.
A27: 26 | B27: 2141120020 | C27: 海洋安军一成员责任有限公司 | D27: CÔNG TY TNHH MTV AN QUÂN HẢI DƯƠNG | E27: CONG TY TNHH MTV AN QUAN HAI DUONG | F27: 海阳 | G27: 0801179630 | H27: Số nhà 13/75 Bùi Thị Xuân, Phường Lê Thanh Nghị, TP Hải Phòng, Việt Nam. | I27: ’01675599541 | J27: NGUYỄN VĂN VĨNH | K27: NGUYEN VAN VINH | L27: GIÁM ĐỐC | M27: 总经理 | N27: Số nhà 13/75 Bùi Thị Xuân, Phường Lê Thanh Nghị, Thành phố Hải Dương, Tỉnh Hải Dương, Việt Nam | W27: =B27 -> 2141120020 | AA27: 郑明黄 | AD27: 越南海防市黎青议坊裴氏春路13/75号门牌 | AF27: 订单生效之日起3个工作日内，乙方应支付订单金额的【50】%作为预付款；自产品到达越南目的港/站后3个工作日内，乙方应支付订单金额剩余的全部款项。甲方将在收到订单100%款项后送货到乙方指定的收货地点。 Trong vòng 03 ngày làm việc kể từ ngày đơn hàng có hiệu lực, Bên Mua phải thanh toán 【50】% giá trị đơn hàng dưới hình thức tiền tạm ứng; trong vòng 03 ngày làm việc kể từ ngày sản phẩm đến cảng/ga đích tại Việt Nam, Bên Mua phải thanh toán toàn bộ số tiền còn lại của đơn hàng. Bên Bán sẽ giao hàng đến địa điểm nhận hàng do Bên Mua chỉ định sau khi nhận được 100% giá trị thanh toán của đơn hàng. | AG27: =VLOOKUP(B27,'[1]Danh sách khách hàng'!$B:$G,6,FALSE) -> Số nhà 13/75 Bùi Thị Xuân, Phường Lê Thanh Nghị, TP Hải Phòng, Việt Nam.
A28: 27 | B28: 2141120010 | C28: 越南KEKI股份有限公司（工业） | D28: CÔNG TY CỔ PHẦN KEKI VIỆT NAM | G28: 0801249246 | H28: Thửa đất số 1488, tờ bản đồ số 09, Xã Thanh Miện, TP Hải Phòng, Việt Nam. | I28: 369691298 | J28: Ông Phạm Hữu Tuấn | K28: 范友俊 | L28: Tổng giám đốc | M28: 总经理 | N28: Thửa đất số 1488, tờ bản đồ số 09, Thị Trấn Thanh Miện, Huyện Thanh Miện, Tỉnh Hải Dương, Việt Nam | W28: =B28 -> 2141120010 | X28: Ngân hàng BIDV CN Hải Dương | Y28: 越南投资发展银行海阳支行 | Z28: 4603396905 | AA28: 郑明黄 | AD28: 越南海防市青沔乡第09号地图块1488号地块 | AF28: 订单采用【定金30%】的方式。乙方应自订单生效之日起10个工作日内（以甲方所在地时间为准）将【付定金30%】和在通知到货后付清剩余的70%货款以【电汇】方式支付至甲方指定账户，并以邮件或即时通讯软件的方式提供有效的支付凭证，由此产生的转账费用（包括但不限于中转行手续费）由乙方承担。甲方将在收到足额货款或支付凭证后安排生产、检验检疫及进出口手续。 Đơn đặt hàng theo phương thức thanh toán 【đặt cọc 30%】. Trong vòng 10 ngày làm việc kể từ ngày đơn đặt hàng có hiệu lực (giờ địa phương của Bên A), Bên B cần thanh toán 【đặt cọc 30%】 và thanh toán hết 70% phần còn lại sau khi có thông báo hàng đến bằng 【Chuyển khoản điện tử】 vào tài khoản do Bên A chỉ định và cung cấp chứng từ thanh toán hợp lệ qua email hoặc tin nhắn. Bất kỳ khoản phí chuyển khoản nào phát sinh (bao gồm nhưng không giới hạn ở phí ngân hàng trung chuyển) sẽ do Bên B chịu. Bên A sẽ thu xếp các thủ tục sản xuất, kiểm tra, kiểm dịch và xuất nhập khẩu sau khi nhận đủ tiền thanh toán hoặc chứng từ thanh toán. | AG28: =VLOOKUP(B28,'[1]Danh sách khách hàng'!$B:$G,6,FALSE) -> Thửa đất số 1488, tờ bản đồ số 09, Xã Thanh Miện, TP Hải Phòng, Việt Nam.
A29: 28 | B29: 2141130010 | C29: 越南流行水族有限公司 | D29: CÔNG TY TNHH POP AQUA | E29: CONG TY TNHH POP AQUA | F29: 北江 | G29: 2400944895 | H29: Số nhà 17, Tổ dân phố số 3, Phường Đa Mai, Bắc Ninh, Việt Nam. | I29: 0326296668 | J29: LUONG VAN LOC | K29: LUONG VAN LOC | L29: Tổng giám đốc | M29: 总经理 | N29: Số nhà 17, tổ dân phố số 3, phường Mỹ Độ, thành phố Bắc Giang, tỉnh Bắc Giang | O29: LƯƠNG VĂN LỘC | P29: 0326296668 - 0373826710 | V29: pop.aquarium.sp@gmail.com | W29: =B29 -> 2141130010 | X29: Ngân hàng VietinBank - Bắc Giang | Y29: 越南工商银行北江分行​ | Z29: 119002923696 | AA29: 阮文忠 | AD29: 越南北宁省多梅坊第3居民组17号门牌 | AF29: 订单生效之日起3个工作日内，乙方应支付订单金额的【50】%作为预付款；自产品到达越南目的港/站后3个工作日内，乙方应支付订单金额剩余的全部款项。甲方将在收到订单100%款项后送货到乙方指定的收货地点。 Trong vòng 03 ngày làm việc kể từ ngày đơn hàng có hiệu lực, Bên Mua phải thanh toán 【50】% giá trị đơn hàng dưới hình thức tiền tạm ứng; trong vòng 03 ngày làm việc kể từ ngày sản phẩm đến cảng/ga đích tại Việt Nam, Bên Mua phải thanh toán toàn bộ số tiền còn lại của đơn hàng. Bên Bán sẽ giao hàng đến địa điểm nhận hàng do Bên Mua chỉ định sau khi nhận được 100% giá trị thanh toán của đơn hàng. | AG29: =VLOOKUP(B29,'[1]Danh sách khách hàng'!$B:$G,6,FALSE) -> Số nhà 17, Tổ dân phố số 3, Phường Đa Mai, Bắc Ninh, Việt Nam.
A30: 29 | B30: 2141020190 | C30: 越南亚洲化学股份有限公司（工业） | D30: CÔNG TY CỔ PHẦN HÓA CHẤT Á CHÂU | E30: CONG TY CO PHAN HOA CHAT A CHAU | F30: ACC | G30: 0304918352 | H30: Lô K4B khu công nghiệp Lê Minh Xuân, Đường Số 4, Xã Bình Lợi, TP Hồ Chí Minh, Việt Nam. | I30: 0838868174 | J30: PHAN DUY HIEU | K30: PHAN DUY HIEU | L30: Tổng giám đốc | M30: 总经理 | N30: 12 đại lộ độc lập , khu công nghiệp sóng thần 1 , dĩ an, dĩ an bình dương | P30: Anh Nhân - Thủ kho: 0938939817 | V30: info@asia-chemical.com | W30: =B30 -> 2141020190 | X30: Vietinbank Chi nhánh 7 - thành phố Hồ Chí Minh | Y30: ​​越南工商银行胡志明市​第七分行 | Z30: 117002653125 | AA30: 彭烨 | AD30: 越南胡志明市平利乡4号路黎明春工业区K4B地块 | AF30: 买方（乙方）须在签订采购订单后立即支付订单总金额的 50%，剩余的 50% 款项必须在收货前（卖方交货前）全部付清。买方付款后，须通过电子邮件或在线聊天软件向卖方提供有效的付款凭证；卖方只有在收到足额款项或有效付款凭证后，才会安排生产、检验、检疫及进出口手续。同时，任何因转账产生的费用（包括但不限于中转行费用）均由买方（乙方）承担。 Bên B thanh toán cho Bên A trước 50% tổng giá trị đơn hàng ngay khi ký Đơn đặt hàng, và 50% còn lại thanh toán hết trước khi nhận hàng (trước khi Bên A giao hàng). Sau khi chuyển khoản, Bên B cần cung cấp chứng từ thanh toán hợp lệ qua email hoặc ứng dụng trò chuyện trực tuyến; Bên A chỉ sắp xếp các thủ tục sản xuất, kiểm tra, kiểm dịch, xuất nhập khẩu sau khi nhận đủ số tiền hoặc chứng từ thanh toán này. Đồng thời, bất kỳ khoản phí chuyển khoản nào phát sinh (bao gồm nhưng không giới hạn ở phí ngân hàng trung chuyển) sẽ hoàn toàn do Bên B chịu. | AG30: =VLOOKUP(B30,'[1]Danh sách khách hàng'!$B:$G,6,FALSE) -> Lô K4B khu công nghiệp Lê Minh Xuân, Đường Số 4, Xã Bình Lợi, TP Hồ Chí Minh, Việt Nam.
A31: 30 | B31: 2141010120 | C31: 越南美越食品供应有限公司 | D31: CÔNG TY TNHH CUNG CẤP THỰC PHẨM MỸ VIỆT | E31: CONG TY TNHH CUNG CAP THUC PHAM MY VIET | F31: 美越 | G31: 0110189527 | H31: Kiot 19-20-21 Tòa CT9 Khu đô thị Định Công, Phường Phương Liệt, TP Hà Nội, Việt Nam. | I31: 0899803689 | J31: BA DANG THU ANH | K31: BA DANG THU ANH | L31: Tổng giám đốc | M31: 总经理 | V31: pptpvietmy@gmail.com | W31: =B31 -> 2141010120 | X31: MB Bank CN Hai Bà Trưng | Y31: 越南军队商业银行二征夫人区分行 | Z31: 2689368999 | AA31: 郑明黄 | AD31: 越南河内市芳烈坊定功新市区CT9大楼19-20-21号商铺 | AF31: 订单生效之日起3个工作日内，乙方应支付订单金额的【50】%作为预付款；自产品到达越南目的港/站后3个工作日内，乙方应支付订单金额剩余的全部款项。甲方将在收到订单100%款项后送货到乙方指定的收货地点。 Trong vòng 03 ngày làm việc kể từ ngày đơn hàng có hiệu lực, Bên Mua phải thanh toán 【50】% giá trị đơn hàng dưới hình thức tiền tạm ứng; trong vòng 03 ngày làm việc kể từ ngày sản phẩm đến cảng/ga đích tại Việt Nam, Bên Mua phải thanh toán toàn bộ số tiền còn lại của đơn hàng. Bên Bán sẽ giao hàng đến địa điểm nhận hàng do Bên Mua chỉ định sau khi nhận được 100% giá trị thanh toán của đơn hàng. | AG31: =VLOOKUP(B31,'[1]Danh sách khách hàng'!$B:$G,6,FALSE) -> Kiot 19-20-21 Tòa CT9 Khu đô thị Định Công, Phường Phương Liệt, TP Hà Nội, Việt Nam.
A32: 31 | B32: 2141010130 | C32: 越南山水发商贸服务股份公司 | D32: CÔNG TY CỔ PHẦN THƯƠNG MẠI VÀ DỊCH VỤ SƠN THỦY PHÁT | E32: CONG TY CO PHAN THUONG MAI VA DICH VU SON THUY PHAT | F32: 山水发 | G32: 0105021487 | H32: Số 7, hẻm 823/19/2 đường Hồng Hà, Phường Hồng Hà, TP Hà Nội, Việt Nam. | I32: 0912961292 | J32: VU THI THUY | K32: VU THI THUY | L32: Tổng giám đốc | M32: 总经理 | V32: sonthuyphat@gmail.com | W32: =B32 -> 2141010130 | X32: Ngân hàng á Châu ACB - chi nhánh Nguyễn Thị Định | Y32: 亚洲商业银行阮氏定区分行​ | Z32: 195695889 | AA32: 郑明黄 | AD32: 越南河内市红河坊红河路823/19/2号巷7号 | AF32: 订单生效之日起3个工作日内，乙方应支付订单金额的【50】%作为预付款；自产品到达越南目的港/站后3个工作日内，乙方应支付订单金额剩余的全部款项。甲方将在收到订单100%款项后送货到乙方指定的收货地点。 Trong vòng 03 ngày làm việc kể từ ngày đơn hàng có hiệu lực, Bên Mua phải thanh toán 【50】% giá trị đơn hàng dưới hình thức tiền tạm ứng; trong vòng 03 ngày làm việc kể từ ngày sản phẩm đến cảng/ga đích tại Việt Nam, Bên Mua phải thanh toán toàn bộ số tiền còn lại của đơn hàng. Bên Bán sẽ giao hàng đến địa điểm nhận hàng do Bên Mua chỉ định sau khi nhận được 100% giá trị thanh toán của đơn hàng. | AG32: =VLOOKUP(B32,'[1]Danh sách khách hàng'!$B:$G,6,FALSE) -> Số 7, hẻm 823/19/2 đường Hồng Hà, Phường Hồng Hà, TP Hà Nội, Việt Nam.
A33: 32 | B33: 2141140010 | C33: 越南秋香贸易经营有限责任公司​ | D33: CÔNG TY TNHH KINH DOANH THƯƠNG MẠI THU HƯƠNG | E33: CONG TY TNHH KINH DOANH THUONG MAI THU HUONG | F33: 秋香 | G33: 0601287156 | H33: Số 16 đường Hưng Yên, Phường Nam Định, Ninh Bình, Việt Nam. | I33: 0913344477 | J33: DINH THI THU HUONG | K33: DINH THI THU HUONG | L33: Tổng giám đốc | M33: 总经理 | V33: thuhuong.trading@gmail.com | W33: =B33 -> 2141140010 | X33: Ngân hàng á Châu ACB - chi nhánh tỉnh Nam Định | Y33: 亚洲商业银行 南定省分行​ | Z33: 2366856 | AA33: 郑明黄 | AD33: 越南宁平省南定坊兴安路16号 | AF33: 订单生效之日起3个工作日内，乙方应支付订单金额的【50】%作为预付款；自产品到达越南目的港/站后3个工作日内，乙方应支付订单金额剩余的全部款项。甲方将在收到订单100%款项后送货到乙方指定的收货地点。 Trong vòng 03 ngày làm việc kể từ ngày đơn hàng có hiệu lực, Bên Mua phải thanh toán 【50】% giá trị đơn hàng dưới hình thức tiền tạm ứng; trong vòng 03 ngày làm việc kể từ ngày sản phẩm đến cảng/ga đích tại Việt Nam, Bên Mua phải thanh toán toàn bộ số tiền còn lại của đơn hàng. Bên Bán sẽ giao hàng đến địa điểm nhận hàng do Bên Mua chỉ định sau khi nhận được 100% giá trị thanh toán của đơn hàng. | AG33: =VLOOKUP(B33,'[1]Danh sách khách hàng'!$B:$G,6,FALSE) -> Số 16 đường Hưng Yên, Phường Nam Định, Ninh Bình, Việt Nam.
A34: 33 | B34: 2141160010 | C34: 越南泰东兴有限公司 | D34: CÔNG TY TNHH THÁI ĐÔNG HƯNG | E34: CONG TY TNHH THAI DONG HUNG | F34: 泰东兴 | G34: 0401493641 | H34: 130 Phạm Đình Hổ, Phường Thanh Khê, TP Đà Nẵng, Việt Nam. | I34: 0982156159 | J34: Đinh Ngọc Dinh | K34: 丁玉圣 | L34: Tổng giám đốc | M34: 总经理 | N34: 172-178 Bùi Tấn Diên, phường Hòa Khánh, thành phố Đà Nẵng, Việt Nam | O34: Đinh Ngọc Dinh | P34: 0932159830 | V34: dinhcaor@gmail.com | W34: =B34 -> 2141160010 | X34: Ngân hàng Nông nghiệp và Phát triển Nông thôn Việt Nam - Chi nhánh Thanh Khê Đà Nẵng - phòng giao dịch Thanh Lộc Đán | Y34: 越南农业与农村发展银行 - 岘港市清溪区清禄旦营业点 | Z34: 2003201085786 | AA34: 朱建君 | AD34: 越南岘港市清溪郡范廷琥路130号 | AF34: 订单生效之日起3个工作日内，乙方应支付订单金额的【50】%作为预付款；自产品到达越南目的港/站后3个工作日内，乙方应支付订单金额剩余的全部款项。甲方将在收到订单100%款项后送货到乙方指定的收货地点。 Trong vòng 03 ngày làm việc kể từ ngày đơn hàng có hiệu lực, Bên Mua phải thanh toán 【50】% giá trị đơn hàng dưới hình thức tiền tạm ứng; trong vòng 03 ngày làm việc kể từ ngày sản phẩm đến cảng/ga đích tại Việt Nam, Bên Mua phải thanh toán toàn bộ số tiền còn lại của đơn hàng. Bên Bán sẽ giao hàng đến địa điểm nhận hàng do Bên Mua chỉ định sau khi nhận được 100% giá trị thanh toán của đơn hàng. | AG34: =VLOOKUP(B34,'[1]Danh sách khách hàng'!$B:$G,6,FALSE) -> 130 Phạm Đình Hổ, Phường Thanh Khê, TP Đà Nẵng, Việt Nam.
A35: 34 | B35: 2141170010 | C35: 越南宝芳林有限责任公司 | D35: CÔNG TY TNHH BẢO PHƯƠNG LÂM | E35: CONG TY TNHH BAO PHUONG LAM | F35: 宝芳林 | G35: '0111304719 | H35: NO13-LK13-04, Khu đất dịch vụ LK8, LK9, LK10, LK15, LK21, LK23, LK24, LK26, C6, TH17 đường Nguyễn Thanh Bình, Phường Hà Đông, TP Hà Nội, Việt Nam. | I35: 0765526888 | J35: TRẦN THỊ NGỌC ANH | K35: TRAN THI NGOC ANH | L35: Tổng giám đốc | M35: 总经理 | N35: NO13-LK13-04, Khu đất dịch vụ LK8, LK9, LK10, LK15, LK21, LK23, LK24, LK26, C6, TH17 đường Nguyễn Thanh Bình, Phường Hà Đông, TP Hà Nội, Việt Nam | O35: TRẦN THỊ NGỌC ANH | P35: '0765526888 | V35: ngocanhtran17081993@gmail.com | W35: =B35 -> 2141170010 | X35: Ngân hàng Techcombank - Chi nhánh Ba Đình | Y35: 越南科技商业银行巴亭分行 | Z35: 65526888 | AA35: 阮文忠 | AD35: 越南河内市河东郡阮青平路，LK8、LK9、LK10、LK15、LK21、LK23、LK24、LK26、C6、TH17服务用地地块NO13-LK13-04号 (文本右侧被截断) | AF35: 订单生效之日起3个工作日内，乙方应支付订单金额的【50】%作为预付款；自产品到达越南目的港/站后3个工作日内，乙方应支付订单金额剩余的全部款项。甲方将在收到订单100%款项后送货到乙方指定的收货地点。 Trong vòng 03 ngày làm việc kể từ ngày đơn hàng có hiệu lực, Bên Mua phải thanh toán 【50】% giá trị đơn hàng dưới hình thức tiền tạm ứng; trong vòng 03 ngày làm việc kể từ ngày sản phẩm đến cảng/ga đích tại Việt Nam, Bên Mua phải thanh toán toàn bộ số tiền còn lại của đơn hàng. Bên Bán sẽ giao hàng đến địa điểm nhận hàng do Bên Mua chỉ định sau khi nhận được 100% giá trị thanh toán của đơn hàng. | AG35: =VLOOKUP(B35,'[1]Danh sách khách hàng'!$B:$G,6,FALSE) -> NO13-LK13-04, Khu đất dịch vụ LK8, LK9, LK10, LK15, LK21, LK23, LK24, LK26, C6, TH17 đường Nguyễn Thanh Bình, Phường Hà Đông, TP Hà Nội, Việt Nam.
A36: 35 | B36: 2141190020 | C36: 越南卷芝贸易服务有限公司 | D36: CÔNG TY TNHH THƯƠNG MẠI VÀ DỊCH VỤ QUYẾN CHI | E36: CONG TY TNHH THUONG MAI VA DICH VU QUYEN CHI | F36: 北宁 | G36: 2301335973 | H36: Xóm Già A, Khu 3, Phường Vũ Ninh, Bắc Ninh, Việt Nam. | I36: 0387882186 | J36: VŨ XUÂN QUYẾN | K36: VŨ XUÂN QUYẾN | L36: GIÁM ĐỐC | M36: 总经理 | N36: Số 9 Trần Đăng Tuyển ,Vũ Ninh , Bắc Ninh | O36: VŨ XUÂN QUYẾN | P36: 387882186 | V36: quyenchi7783@gmail.com | W36: =B36 -> 2141190020 | X36: VIETNAM JOINT STOCK COMMERCIAL BANK FOR INDUSTRY AND TRADE (VIETIN BANK) | Y36: 越南工商银行 | Z36: 21228383 | AA36: 阮文忠 | AD36: 越南北宁省武宁坊第3区老A村 | AF36: 订单生效之日起3个工作日内，乙方应支付订单金额的【50】%作为预付款；自产品到达越南目的港/站后3个工作日内，乙方应支付订单金额剩余的全部款项。甲方将在收到订单100%款项后送货到乙方指定的收货地点。 Trong vòng 03 ngày làm việc kể từ ngày đơn hàng có hiệu lực, Bên Mua phải thanh toán 【50】% giá trị đơn hàng dưới hình thức tiền tạm ứng; trong vòng 03 ngày làm việc kể từ ngày sản phẩm đến cảng/ga đích tại Việt Nam, Bên Mua phải thanh toán toàn bộ số tiền còn lại của đơn hàng. Bên Bán sẽ giao hàng đến địa điểm nhận hàng do Bên Mua chỉ định sau khi nhận được 100% giá trị thanh toán của đơn hàng. | AG36: =VLOOKUP(B36,'[1]Danh sách khách hàng'!$B:$G,6,FALSE) -> Xóm Già A, Khu 3, Phường Vũ Ninh, Bắc Ninh, Việt Nam.
A37: 36 | B37: 2141190010 | C37: 越南福禄BG进出口有限公司 | D37: CONG TY TNHH XNK PHUC LOC BG | E37: CONG TY TNHH XNK PHUC LOC BG | F37: 北江 | G37: 2401061878 | H37: Đường Nguyễn Thái Học, Tổ Dân Phố Xóm Ba, Phường Đa Mai, Bắc Ninh, Việt Nam. | I37: 0983915597 | J37: LƯƠNG VĂN PHÚC | K37: LƯƠNG VĂN PHÚC | L37: GIÁM ĐỐC | M37: 总经理 | N37: Tổ 3 phường đa mai tỉnh bắc ninh | O37: LƯƠNG VĂN LỘC | P37: 0326296668 - 0373826710 | V37: locbgphuc@gmail.com | W37: =B37 -> 2141190010 | X37: VIETNAM JOINT STOCK COMMERCIAL BANK FOR INDUSTRY AND TRADE (VIETIN BANK) | Y37: 越南工商银行 | Z37: 110646848886 | AA37: 阮文忠 | AD37: 越南北宁省多梅坊三村居民组阮太学路 | AF37: 订单生效之日起3个工作日内，乙方应支付订单金额的【50】%作为预付款；自产品到达越南目的港/站后3个工作日内，乙方应支付订单金额剩余的全部款项。甲方将在收到订单100%款项后送货到乙方指定的收货地点。 Trong vòng 03 ngày làm việc kể từ ngày đơn hàng có hiệu lực, Bên Mua phải thanh toán 【50】% giá trị đơn hàng dưới hình thức tiền tạm ứng; trong vòng 03 ngày làm việc kể từ ngày sản phẩm đến cảng/ga đích tại Việt Nam, Bên Mua phải thanh toán toàn bộ số tiền còn lại của đơn hàng. Bên Bán sẽ giao hàng đến địa điểm nhận hàng do Bên Mua chỉ định sau khi nhận được 100% giá trị thanh toán của đơn hàng. | AG37: =VLOOKUP(B37,'[1]Danh sách khách hàng'!$B:$G,6,FALSE) -> Đường Nguyễn Thái Học, Tổ Dân Phố Xóm Ba, Phường Đa Mai, Bắc Ninh, Việt Nam.
A38: 37 | B38: 2141290010 | C38: 越南鸿发MC进出口有限公司 | D38: CÔNG TY TNHH XUẤT NHẬP KHÂU HOÀN PHÁT MC | E38: CONG TY TNHH XUAT NHAP KHAU HOAN PHAT MC | F38: 芒街 | G38: 5702163540 | H38: SN B11, S17 Khu Đô Thị Phượng Hoàng, Thôn 13, Phường Móng Cái 1, Quảng Ninh, Việt Nam. | I38: 0913237269 | J38: NGUYỄN XUÂN HOÀN | K38: NGUYỄN XUÂN HOÀN | L38: GIÁM ĐỐC | M38: 总经理 | N38: Ngã 5 ninh dương , cảng quang phát 1 , phường mc 2 | O38: NGUYỄN XUÂN HOÀN | P38: 913237269 | V38: tamtithxmc@gmail.com | W38: =B38 -> 2141290010 | X38: AGRIBANK PLC | Y38: 农业银行 | Z38: 8090666663999 | AA38: 阮文忠 | AD38: 越南广宁省芒街1坊13村凤皇新市区B11, S17号门牌 | AF38: 订单生效之日起3个工作日内，乙方应支付订单金额的【50】%作为预付款；自产品到达越南目的港/站后3个工作日内，乙方应支付订单金额剩余的全部款项。甲方将在收到订单100%款项后送货到乙方指定的收货地点。 Trong vòng 03 ngày làm việc kể từ ngày đơn hàng có hiệu lực, Bên Mua phải thanh toán 【50】% giá trị đơn hàng dưới hình thức tiền tạm ứng; trong vòng 03 ngày làm việc kể từ ngày sản phẩm đến cảng/ga đích tại Việt Nam, Bên Mua phải thanh toán toàn bộ số tiền còn lại của đơn hàng. Bên Bán sẽ giao hàng đến địa điểm nhận hàng do Bên Mua chỉ định sau khi nhận được 100% giá trị thanh toán của đơn hàng. | AG38: =VLOOKUP(B38,'[1]Danh sách khách hàng'!$B:$G,6,FALSE) -> SN B11, S17 Khu Đô Thị Phượng Hoàng, Thôn 13, Phường Móng Cái 1, Quảng Ninh, Việt Nam.
A39: 38 | B39: 2141040020 | C39: 越南明缘进出口有限公司 | D39: CÔNG TY TNHH XUẤT NHẬP KHẨU MINH DUYÊN | E39: CONG TY TNHH XUAT NHAP KHAU MINH DUYEN | F39: 老街 | G39: 5300836228 | H39: Số nhà 073, Thôn Hồng Giang, Phường Lào Cai, Lào Cai, Việt Nam. | I39: 0868251224 | J39: ĐẢO ĐỨC MINH | K39: ĐẢO ĐỨC MINH | L39: GIÁM ĐỐC | M39: 总经理 | N39: Kho lưu bằng, kcn bắc duyên hải, tp lào cai tỉnh lào cai | O39: ĐẢO ĐỨC MINH | P39: 868251224 | V39: xnkminhduyenlc@gmail.com | W39: =B39 -> 2141040020 | X39: MILITARY COMMERCIAL JOINT STOCK BANK | Y39: 越南军队商业银行 | Z39: 5300836228 | AA39: 阮文忠 | AD39: 越南老街省老街坊红江村073号门牌 | AF39: 订单生效之日起3个工作日内，乙方应支付订单金额的【50】%作为预付款；自产品到达越南目的港/站后3个工作日内，乙方应支付订单金额剩余的全部款项。甲方将在收到订单100%款项后送货到乙方指定的收货地点。 Trong vòng 03 ngày làm việc kể từ ngày đơn hàng có hiệu lực, Bên Mua phải thanh toán 【50】% giá trị đơn hàng dưới hình thức tiền tạm ứng; trong vòng 03 ngày làm việc kể từ ngày sản phẩm đến cảng/ga đích tại Việt Nam, Bên Mua phải thanh toán toàn bộ số tiền còn lại của đơn hàng. Bên Bán sẽ giao hàng đến địa điểm nhận hàng do Bên Mua chỉ định sau khi nhận được 100% giá trị thanh toán của đơn hàng. | AG39: =VLOOKUP(B39,'[1]Danh sách khách hàng'!$B:$G,6,FALSE) -> Số nhà 073, Thôn Hồng Giang, Phường Lào Cai, Lào Cai, Việt Nam.
A40: 39 | B40: 2141020200 | C40: 越南国宴云厨房有限公司（工业） | D40: CONG TY TNHH QUỐC YẾN CLOUD KITCHEN | E40: CONG TY TNHH QUOC YEN CLOUD KITCHEN | F40: 国宴 | G40: 0309576416 | H40: 3SB1-12 Đường số 20, Khu phố Mỹ Viên, Khu đô thị Phú Mỹ Hưng, Phường Tân Mỹ, Thành phố Hồ Chí Minh, Việt Nam | I40: 0888058989 | J40: LÝ TRƯƠNG HUY | K40: 黎长辉 | L40: Chủ tịch Công ty | M40: 公司主席 | W40: =B40 -> 2141020200 | X40: Ngân Hàng Agribank | Y40: 越南农业与农村发展银行 | Z40: 6240238000389 | AD40: 越南胡志明市新富坊富美兴新城美缘小区20号路3SB1-12 | AF40: 订单生效之日起3个工作日内，乙方应支付订单金额的【50】%作为预付款；自产品到达越南目的港/站后3个工作日内，乙方应支付订单金额剩余的全部款项。甲方将在收到订单100%款项后送货到乙方指定的收货地点。 Trong vòng 03 ngày làm việc kể từ ngày đơn hàng có hiệu lực, Bên Mua phải thanh toán 【50】% giá trị đơn hàng dưới hình thức tiền tạm ứng; trong vòng 03 ngày làm việc kể từ ngày sản phẩm đến cảng/ga đích tại Việt Nam, Bên Mua phải thanh toán toàn bộ số tiền còn lại của đơn hàng. Bên Bán sẽ giao hàng đến địa điểm nhận hàng do Bên Mua chỉ định sau khi nhận được 100% giá trị thanh toán của đơn hàng.
A41: 40 | B41: 2141020240 | C41: 越南陈日儿有限公司 | D41: CÔNG TY TNHH NHẬT NHI TRẦN | E41: CONG TY TNHH NHAT NHI TRAN | F41: 陈日儿 | G41: 0305684805 | H41: 766 Sư Vạn Hạnh, Phường Hòa Hưng, Thành Phố Hồ Chí Minh, Việt Nam | I41: 0898084868 | J41: LƯU QUỐC HOÀNG | K41: 刘国煌 | L41: GIÁM ĐỐC | M41: 总经理 | T41: Nguyễn Ngọc Huy | U41: 08 9941 5732 | V41: hoang@dora.vn；Huy.nguyen@dora.vn | W41: =B41 -> 2141020240 | X41: Ngân hàng MB - Cơ sở 2 | Y41: 越南军队股份商业银行2号营业点/分行 | Z41: 655667899 | AA41: 朱建君 | AD41: 越南胡志明市和兴坊师万行路 766号 | AF41: 订单生效之日起3个工作日内，乙方应支付订单金额的【50】%作为预付款；自产品到达越南目的港/站后3个工作日内，乙方应支付订单金额剩余的全部款项。甲方将在收到订单100%款项后送货到乙方指定的收货地点。 Trong vòng 03 ngày làm việc kể từ ngày đơn hàng có hiệu lực, Bên Mua phải thanh toán 【50】% giá trị đơn hàng dưới hình thức tiền tạm ứng; trong vòng 03 ngày làm việc kể từ ngày sản phẩm đến cảng/ga đích tại Việt Nam, Bên Mua phải thanh toán toàn bộ số tiền còn lại của đơn hàng. Bên Bán sẽ giao hàng đến địa điểm nhận hàng do Bên Mua chỉ định sau khi nhận được 100% giá trị thanh toán của đơn hàng.
A42: 41 | B42: 2141180010 | C42: 越南-安平发添加剂公司（食品工业） | D42: CÔNG TY TNHH XUẤT NHẬP KHẨU VÀ THƯƠNG MẠI AN BÌNH PHÁT | E42: CONG TY TNHH XUAT NHAP KHAU VA THUONG MAI AN BINH PHAT | F42: 安平发 | G42: 0110903413 | H42: Số 344 đường Hà Huy Tập, Xã Phù Đổng, Thành phố Hà Nội, Việt Nam | I42: 0919 999 893 | J42: NGUYỄN MẠNH CƯỜNG | K42: 阮孟强 | L42: GIÁM ĐỐC | M42: 总经理 | W42: =B42 -> 2141180010 | X42: Ngân hàng TMCP Kỹ Thương Việt Nam – CN Bà Triệu | Y42: 越南科技商业股份银行 - 百万支行 | Z42: 2225667888 | AD42: 越南河内市光明县富池社夏辉集路 344 号 | AF42: 乙方（买方）在签署订单时向甲方支付总金额的 30% 作为预付款；其余 70% 须在甲方收货前全部付清。Bên B thanh toán cho Bên A trước 30% tổng giá trị đơn hàng ngay khi ký Đơn đặt hàng, 70% còn lại thanh toán hết trước khi nhận hàng.
A43: 42 | B43: 2141150010 | C43: 越南味丹股份有限公司(OEM) | D43: CÔNG TY CỔ PHẦN HỮU HẠN VEDAN VIỆT NAM | E43: CONG TY CO PHAN HUU HAN VEDAN VIET NAM | F43: 味丹(OEM) | G43: 3600239719 | H43: Quốc lộ 51, Ấp 1A, Xã Phước Thái, Đồng Nai, Việt Nam. | J43: TANG DAW SEN | K43: TANG DAW SEN | L43: GIÁM ĐỐC | M43: 总经理 | N43: Quốc lộ 51, Ấp 1A, Xã Phước Thái, Huyện Long Thành, Tỉnh Đồng Nai, Việt Nam. | Q43: CAT LAI PORT ,HO CHI MINH,VIETNAM | R43: 经常 | V43: huyen-tt@vedaninternational.com | W43: =B43 -> 2141150010 | AA43: 朱建君 | AD43: 越南同奈省福泰乡1A邑51号国道 | AF43: 甲方（买方）须在乙方（卖方）交货前，预付（押金）100% 的订单金额。Bên A đặt cọc 100% giá trị đơn đặt hàng trước thời điểm bên B giao hàng.

Sheet 三品订单
C1: 三品清单 | D1: 如遇三品缺货，直接取消发该三品，不作换货沟通，请知悉
B2: 序号 | C2: 物料编码 | D2: 物料描述 | E2: 统一售价 (CNY) | F2: 单位 | G2: 毛重 | H2: 体积(M3) | I2: 包装尺寸 | J2: 数量 | K2: 总毛重(KG) | L2: 总体积(M3)
A3: =IFERROR(RANK(J3,$J$3:$J$23,1)+COUNTIFS(J$3:J3,J3)-1,"") | B3: 1 | C3: 41005059 | D3: 海天白色味碟（2个/盒，60盒/箱） | E3: 267.35 | F3: 箱 | G3: 13 | H3: 0.02559375 | I3: 35*32.5*22.5cm | K3: =J3*G3 -> 0 | L3: =H3*J3 -> 0
A4: =IFERROR(RANK(J4,$J$3:$J$23,1)+COUNTIFS(J$3:J4,J4)-1,"") | B4: 2 | C4: 41005175 | D4: 自动开合桌上瓶（箱，48盒/箱） | E4: 231.84 | F4: 箱 | G4: 10.5 | H4: 0.036366 | I4: 44*29*28.5cm | K4: =J4*G4 -> 0 | L4: =H4*J4 -> 0
A5: =IFERROR(RANK(J5,$J$3:$J$23,1)+COUNTIFS(J$3:J5,J5)-1,"") | B5: 3 | C5: 41005116 | D5: 能抗菌的洗洁布（200包/箱） | E5: 239.4 | F5: 箱 | G5: 8.1 | H5: 0.05928 | I5: 65*32*28.5cm | K5: =J5*G5 -> 0 | L5: =H5*J5 -> 0
A6: =IFERROR(RANK(J6,$J$3:$J$23,1)+COUNTIFS(J$3:J6,J6)-1,"") | B6: 4 | C6: 41004086 | D6: 味极鲜覆膜环保购物袋（50个/扎） | E6: 48.83 | F6: 扎 | G6: 2.4 | H6: 0.020475 | I6: 35*39*15cm | K6: =J6*G6 -> 0 | L6: =H6*J6 -> 0
A7: =IFERROR(RANK(J7,$J$3:$J$23,1)+COUNTIFS(J$3:J7,J7)-1,"") | B7: 5 | C7: 41004119 | D7: 黄豆酱覆膜环保购物袋（50个/扎） | E7: 48.83 | F7: 扎 | G7: 2.34 | H7: 0.01296 | I7: 30*24*18cm | K7: =J7*G7 -> 0 | L7: =H7*J7 -> 0
A8: =IFERROR(RANK(J8,$J$3:$J$23,1)+COUNTIFS(J$3:J8,J8)-1,"") | B8: 6 | C8: 41004134 | D8: 海天福字购物袋（50个/扎） | E8: 48.83 | F8: 扎 | G8: 2.34 | H8: 0.018081 | I8: 42*41*10.5cm | K8: =J8*G8 -> 0 | L8: =H8*J8 -> 0
A9: =IFERROR(RANK(J9,$J$3:$J$23,1)+COUNTIFS(J$3:J9,J9)-1,"") | B9: 7 | C9: 41004752 | D9: 出口版海天覆膜环保购物袋（扎，50个/扎） | E9: 48.83 | F9: 扎 | G9: 2.34 | H9: 0.018081 | I9: 42*41*10.5cm | K9: =J9*G9 -> 0 | L9: =H9*J9 -> 0
A10: =IFERROR(RANK(J10,$J$3:$J$23,1)+COUNTIFS(J$3:J10,J10)-1,"") | B10: 8 | C10: 41003010 | D10: 品牌帐篷（1套/箱） | E10: 225.72 | F10: 箱 | G10: 20.5 | H10: 0.0588 | I10: 147*20*20cm | K10: =J10*G10 -> 0 | L10: =H10*J10 -> 0
A11: =IFERROR(RANK(J11,$J$3:$J$23,1)+COUNTIFS(J$3:J11,J11)-1,"") | B11: 9 | C11: 41003071 | D11: 酱油版大包装陈列架简易版（1套/箱） | E11: 302.4 | F11: 箱 | G11: 21.57 | H11: 0.1296 | I11: 96*75*18cm | K11: =J11*G11 -> 0 | L11: =H11*J11 -> 0
A12: =IFERROR(RANK(J12,$J$3:$J$23,1)+COUNTIFS(J$3:J12,J12)-1,"") | B12: 10 | C12: 41003072 | D12: 蚝油版大包装陈列架简易版（1套/箱） | E12: 302.4 | F12: 箱 | G12: 21.57 | H12: 0.1296 | I12: 96*75*18cm | K12: =J12*G12 -> 0 | L12: =H12*J12 -> 0
A13: =IFERROR(RANK(J13,$J$3:$J$23,1)+COUNTIFS(J$3:J13,J13)-1,"") | B13: 11 | C13: 41003070 | D13: 海天阳光小店陈列架简易版（1套/箱） | E13: 199.8 | F13: 箱 | G13: 15.95 | H13: 0.079 | I13: 81*61*16cm | K13: =J13*G13 -> 0 | L13: =H13*J13 -> 0
A14: =IFERROR(RANK(J14,$J$3:$J$23,1)+COUNTIFS(J$3:J14,J14)-1,"") | B14: 12 | C14: 41002036 | D14: 大包装价格贴（200张/包） | E14: 19.55 | F14: 包 | G14: 1.241 | H14: 0.001 | I14: 18.5*17.2*0.1cm | K14: =J14*G14 -> 0 | L14: =H14*J14 -> 0
... A24: =IFERROR(RANK(J24,$J$3:$J$23,1)+COUNTIFS(J$3:J24,J24)-1,"") | B24: 22 | C24: 41003081 | D24: 2024年小台历礼盒（箱，10盒/箱） | E24: 239 | F24: 箱 | G24: 12 | H24: 0.005 | I24: 28*28*6cm | K24: =J24*G24 -> 0 | L24: =H24*J24 -> 0
B25: TOTAL | J25: =SUM(J3:J24) -> 0 | K25: =SUM(K3:K24) -> 0 | L25: =SUM(L3:L24) -> 0

Sheet 越南文大写金额计算
A1: Hàm chuyển số thành chữ | C1: =#REF! -> #REF! | G1: Nhập số vào đây
B2: =C1+10^12 -> #REF! | C2: 1 | D2: 2 | E2: 3 | F2: 4 | G2: 5 | H2: 6 | I2: 7 | J2: 8 | K2: 9 | L2: 10 | M2: 11 | N2: 12
A3: Tách từng vị trí | C3: =VALUE(MID(B2,C2+1,1)) -> #REF! | D3: =VALUE(MID(B2,D2+1,1)) -> #REF! | E3: =VALUE(MID(B2,E2+1,1)) -> #REF! | F3: =VALUE(MID(B2,F2+1,1)) -> #REF! | G3: =VALUE(MID(B2,G2+1,1)) -> #REF! | H3: =VALUE(MID(B2,H2+1,1)) -> #REF! | I3: =VALUE(MID(B2,I2+1,1)) -> #REF! | J3: =VALUE(MID(B2,J2+1,1)) -> #REF! | K3: =VALUE(MID(B2,K2+1,1)) -> #REF! | L3: =VALUE(MID(B2,L2+1,1)) -> #REF! | M3: =VALUE(MID(B2,M2+1,1)) -> #REF! | N3: =VALUE(MID(B2,N2+1,1)) -> #REF!
A4: Chọn đơn vị | D4: linh | E4: tỷ | G4: linh | H4: triệu | J4: linh | K4: ngàn | M4: lẻ | N4: đồng
A5: Đọc ra chữ | C5: =IF(C3=0,"",CHOOSE(C3,"một","hai","ba","bốn","năm","sáu","bảy","tám","chín")&" trăm") -> #REF! | D5: =IF(SUM(C3:D3)=0,"",IF(AND(D3=0,E3=0),"",IF(AND(D3=0,E3<>0),D4,CHOOSE(D3,"mười","hai mươi","ba mươi","bốn mươi","năm mươi","sáu mươi","bảy mươi","tám mươi","chín mươi")))) -> #REF! | E5: =IF(SUM(C3:E3)=0,"",IF(AND(SUM(C3:D3)>0,E3=0)," "&E4,CHOOSE(E3,IF(D3>0,"mốt","một"),"hai","ba","bốn",IF(D3>0,"lăm","năm"),"sáu","bảy","tám","chín")&" "&E4)) -> #REF! | F5: =IF(SUM(C3:F3)=0,"",IF(SUM(F3:H3)=0,"",IF(F3=0,"không trăm",CHOOSE(F3,"một","hai","ba","bốn","năm","sáu","bảy","tám","chín")&" trăm"))) -> #REF! | G5: =IF(SUM(C3:G3)=0,"",IF(AND(G3=0,H3=0),"",IF(AND(G3=0,H3<>0),G4,CHOOSE(G3,"mười","hai mươi","ba mươi","bốn mươi","năm mươi","sáu mươi","bảy mươi","tám mươi","chín mươi")))) -> #REF! | H5: =IF(SUM(F3:H3)=0,"",IF(AND(SUM(C3:G3)>0,H3=0)," "&H4,CHOOSE(H3,IF(G3>0,"mốt","một"),"hai","ba","bốn",IF(G3>0,"lăm","năm"),"sáu","bảy","tám","chín")&" "&H4)) -> #REF! | I5: =IF(SUM(C3:I3)=0,"",IF(SUM(I3:K3)=0,"",IF(I3=0,"không trăm",CHOOSE(I3,"một","hai","ba","bốn","năm","sáu","bảy","tám","chín")&" trăm"))) -> #REF! | J5: =IF(SUM(C3:J3)=0,"",IF(AND(J3=0,K3=0),"",IF(AND(J3=0,K3<>0),J4,CHOOSE(J3,"mười","hai mươi","ba mươi","bốn mươi","năm mươi","sáu mươi","bảy mươi","tám mươi","chín mươi")))) -> #REF! | K5: =IF(SUM(I3:K3)=0,"",IF(AND(SUM(C3:J3)>0,K3=0)," "&K4,CHOOSE(K3,IF(J3>0,"mốt","một"),"hai","ba","bốn",IF(J3>0,"lăm","năm"),"sáu","bảy","tám","chín")&" "&K4)) -> #REF! | L5: =IF(SUM(C3:L3)=0,"",IF(SUM(L3:N3)=0,"",IF(L3=0,"không trăm",CHOOSE(L3,"một","hai","ba","bốn","năm","sáu","bảy","tám","chín")&" trăm"))) -> #REF! | M5: =IF(SUM(C3:M3)=0,"",IF(AND(M3=0,N3=0),"",IF(AND(M3=0,N3<>0),M4,CHOOSE(M3,"mười","hai mươi","ba mươi","bốn mươi","năm mươi","sáu mươi","bảy mươi","tám mươi","chín mươi")))) -> #REF! | N5: =IF(SUM(C3:N3)=0,"Không "&N4,IF(AND(SUM(C3:K3)>0,SUM(L3:N3)=0)," "&N4&" chẵn",IF(N3=0," "&N4,CHOOSE(N3,IF(M3>0,"mốt","một"),"hai","ba","bốn",IF(M3>0,"lăm","năm"),"sáu","bảy","tám","chín")&" "&N4)))&"./." -> #REF!
A6: Viết hoa chữ cái đầu trong chuỗi | C6: =IF(C5="","",IF(COUNTIF(B5,"")=C2,UPPER(LEFT(C5,1))&RIGHT(C5,LEN(C5)-1),C5)) -> #REF! | D6: =IF(D5="","",IF(COUNTIF(B5:C5,"")=D2,UPPER(LEFT(D5,1))&RIGHT(D5,LEN(D5)-1),D5)) -> #REF! | E6: =IF(E5="","",IF(COUNTIF(B5:D5,"")=E2,UPPER(LEFT(E5,1))&RIGHT(E5,LEN(E5)-1),E5)) -> #REF! | F6: =IF(F5="","",IF(COUNTIF(B5:E5,"")=F2,UPPER(LEFT(F5,1))&RIGHT(F5,LEN(F5)-1),F5)) -> #REF! | G6: =IF(G5="","",IF(COUNTIF(B5:F5,"")=G2,UPPER(LEFT(G5,1))&RIGHT(G5,LEN(G5)-1),G5)) -> #REF! | H6: =IF(H5="","",IF(COUNTIF(B5:G5,"")=H2,UPPER(LEFT(H5,1))&RIGHT(H5,LEN(H5)-1),H5)) -> #REF! | I6: =IF(I5="","",IF(COUNTIF(B5:H5,"")=I2,UPPER(LEFT(I5,1))&RIGHT(I5,LEN(I5)-1),I5)) -> #REF! | J6: =IF(J5="","",IF(COUNTIF(B5:I5,"")=J2,UPPER(LEFT(J5,1))&RIGHT(J5,LEN(J5)-1),J5)) -> #REF! | K6: =IF(K5="","",IF(COUNTIF(B5:J5,"")=K2,UPPER(LEFT(K5,1))&RIGHT(K5,LEN(K5)-1),K5)) -> #REF! | L6: =IF(L5="","",IF(COUNTIF(B5:K5,"")=L2,UPPER(LEFT(L5,1))&RIGHT(L5,LEN(L5)-1),L5)) -> #REF! | M6: =IF(M5="","",IF(COUNTIF(B5:L5,"")=M2,UPPER(LEFT(M5,1))&RIGHT(M5,LEN(M5)-1),M5)) -> #REF! | N6: =IF(N5="","",IF(COUNTIF(B5:M5,"")=N2,UPPER(LEFT(N5,1))&RIGHT(N5,LEN(N5)-1),N5)) -> #REF!
A7: Kết quả: | B7: =TRIM(C6&" "&D6&" "&E6&" "&F6&" "&G6&" "&H6&" "&I6&" "&J6&" "&K6&" "&L6&" "&M6&" "&N6) -> #REF!

Sheet 付款条款参考
A1: ”付款方式”条款模板
A2: 先款后货 | C2: 自买方同意本确认书之日起3个工作日内，买方应以电汇方式向卖方支付上述“总值”的全部金额。卖方将在收到足额付款后安排生产及海关检验检疫手续（如适用）。 Within 3 business days after this Confirmation is accepted by the Buyer, the Buyer shall pay the Seller the full amount of the aforementioned Total Value via telegraphic transfer. The Seller will arrange for production, and Customs inspection and quarantine procedures (if applicable), after receipt of full payment. | D2: 自买方同意本确认书之日起3个工作日内，买方应以电汇方式向卖方支付上述“总值”的全部金额。卖方将在收到足额付款后安排生产及海关检验检疫手续（如适用）。 Trong vòng 03 ngày làm việc kể từ ngày Bên Mua chấp thuận Bản Xác nhận này, Bên Mua phải thanh toán toàn bộ số tiền của "Tổng giá trị" nói trên cho Bên Bán bằng hình thức chuyển khoản bằng điện (T/T). Bên Bán sẽ sắp xếp sản xuất và các thủ tục kiểm tra, kiểm dịch hải quan (nếu có) sau khi nhận được thanh toán đầy đủ.
A3: 先款后货RDC | B3: RDC仓库发运日 | C3: 自买方同意本确认书之日起3个工作日内，买方应以电汇方式向卖方支付上述“总值”的全部金额。卖方将在收到足额付款后的【X】个工作日内，安排从其在越南境内的RDC仓库发货。 Within 3 business days after this Confirmation is accepted by the Buyer, the Buyer shall pay the Seller the full amount of the aforementioned "Total Value" via telegraphic transfer (T/T). The Seller will arrange to dispatch the Products from its RDC warehouse in Vietnam within 【X】 business days upon receipt of the full payment. | D3: 自买方同意本确认书之日起3个工作日内，买方应以电汇方式向卖方支付上述“总值”的全部金额。卖方将在收到足额付款后的【X】个工作日内，安排从其在越南境内的RDC仓库发货。 Trong vòng 03 ngày làm việc kể từ ngày Bên Mua chấp thuận Bản Xác nhận này, Bên Mua phải thanh toán toàn bộ số tiền của "Tổng giá trị" nói trên cho Bên Bán bằng hình thức chuyển khoản bằng điện (T/T). Bên Bán sẽ sắp xếp xuất hàng từ kho RDC của mình tại Việt Nam trong vòng 【X】 ngày làm việc kể từ khi nhận được thanh toán đầy đủ.
B4: 送达约定到货地点 | C4: 订单生效之日起14个工作日内，乙方应支付订单金额的【100】%作为预付款；自产品到达越南目的港/站后3个工作日内，乙方应支付订单金额剩余的全部款项。甲方将在收到订单100%款项后送货到乙方指定的收货地点。 Within 14 business days after the effective date of the order, the Buyer shall pay 【100】% of the order amount as advance payment; within 3 business days after the Products arrive at the port/station of destination in Vietnam, the Buyer shall pay the remaining full amount of the order. The Seller will deliver the Products to the receiving location designated by the Buyer upon receipt of 100% of the order payment. | D4: 订单生效之日起14个工作日内，乙方应支付订单金额的【100】%作为预付款；自产品到达越南目的港/站后3个工作日内，乙方应支付订单金额剩余的全部款项。甲方将在收到订单100%款项后送货到乙方指定的收货地点。 Trong vòng 14 ngày làm việc kể từ ngày đơn hàng có hiệu lực, Bên Mua phải thanh toán 【100】% giá trị đơn hàng dưới hình thức tiền tạm ứng; trong vòng 03 ngày làm việc kể từ ngày sản phẩm đến cảng/ga đích tại Việt Nam, Bên Mua phải thanh toán toàn bộ số tiền còn lại của đơn hàng. Bên Bán sẽ giao hàng đến địa điểm nhận hàng do Bên Mua chỉ định sau khi nhận được 100% giá trị thanh toán của đơn hàng.
B5: 送达约定到货地点 | C5: 订单生效之日起3个工作日内，乙方应支付订单金额的【100】%作为预付款；自产品到达越南目的港/站后3个工作日内，乙方应支付订单金额剩余的全部款项。甲方将在收到订单100%款项后送货到乙方指定的收货地点。 Within 3 business days after the effective date of the order, the Buyer shall pay 【100】% of the order amount as advance payment; within 3 business days after the Products arrive at the port/station of destination in Vietnam, the Buyer shall pay the remaining full amount of the order. The Seller will deliver the Products to the receiving location designated by the Buyer upon receipt of 100% of the order payment. | D5: 订单生效之日起3个工作日内，乙方应支付订单金额的【100】%作为预付款；自产品到达越南目的港/站后3个工作日内，乙方应支付订单金额剩余的全部款项。甲方将在收到订单100%款项后送货到乙方指定的收货地点。 Trong vòng 03 ngày làm việc kể từ ngày đơn hàng có hiệu lực, Bên Mua phải thanh toán 【100】% giá trị đơn hàng dưới hình thức tiền tạm ứng; trong vòng 03 ngày làm việc kể từ ngày sản phẩm đến cảng/ga đích tại Việt Nam, Bên Mua phải thanh toán toàn bộ số tiền còn lại của đơn hàng. Bên Bán sẽ giao hàng đến địa điểm nhận hàng do Bên Mua chỉ định sau khi nhận được 100% giá trị thanh toán của đơn hàng.
A6: 赊销 | B6: 卖方工厂装货日后XX天 | C6: 自卖方发货之日起【X日】内，买方应以电汇方式向卖方支付上述“总值”的全部金额。 Within【x days】 after the date on which the Products are dispatched by the Seller, the Buyer shall pay the Seller the full amount of the aforementioned Total Value via telegraphic transfer. | D6: 自卖方发货之日起【X】日内，买方应以电汇方式向卖方支付上述“总值”的全部金额。 Trong vòng 【X】 ngày kể từ ngày Bên Bán giao hàng (phát hàng), Bên Mua phải thanh toán toàn bộ số tiền của "Tổng giá trị" nói trên cho Bên Bán bằng hình thức chuyển khoản bằng điện (T/T).
B7: 提单装船日后XX天 | C7: 自提单装船日起【X日】内，买方应以电汇方式向卖方支付上述“总值”的全部金额。 Within 【x days】 after the date on which the Products are laden on board the vessel in accordance with the Bill of Lading, the Buyer shall pay the Seller the full amount of the aforementioned Total Value via telegraphic transfer. | D7: 自提单装船日起【X】日内，买方应以电汇方式向卖方支付上述“总值”的全部金额。 Trong vòng 【X】 ngày kể từ ngày Sản phẩm được xếp lên tàu theo Vận đơn (Bill of Lading), Bên Mua phải thanh toán toàn bộ số tiền của "Tổng giá trị" nói trên cho Bên Bán bằng hình thức chuyển khoản bằng điện (T/T).
B8: RDC仓库发运日 | C8: 自卖方从其在越南境内的RDC仓库发货之日起【X日】内，买方应以电汇方式向卖方支付上述“总值”的全部金额。 Within 【x days】 from the date on which the Seller ships the Products from its RDC warehouse in Vietnam, the Buyer shall pay the Seller the full amount of the aforementioned Total Value via telegraphic transfer. | D8: 自卖方从其在越南境内的RDC仓库发货之日起【X】日内，买方应以电汇方式向卖方支付上述“总值”的全部金额。 Trong vòng 【X】 ngày kể từ ngày Bên Bán xuất hàng từ kho RDC của mình tại Việt Nam, Bên Mua phải thanh toán toàn bộ số tiền của "Tổng giá trị" nói trên cho Bên Bán bằng hình thức chuyển khoản bằng điện (T/T).
B9: 送达约定到货地点 | C9: 自卖方将产品送达至到货地点之日起【X日】内，买方应以电汇方式向卖方支付上述“总值”的全部金额。 Within 【x days】 from the date on which the Seller delivers the Products to the Delivery Location, the Buyer shall pay the Seller the full amount of the aforementioned Total Value via telegraphic transfer. | D9: 自卖方将产品送达至约定到货地点之日起【X】日内，买方应以电汇方式向卖方支付上述“总值”的全部金额。 Trong vòng 【X】 ngày kể từ ngày Bên Bán giao Sản phẩm đến Địa điểm giao hàng đã thỏa thuận, Bên Mua phải thanh toán toàn bộ số tiền của "Tổng giá trị" nói trên cho Bên Bán bằng hình thức chuyển khoản bằng điện (T/T).
B10: 送达约定到货地点 | C10: 订单生效之日起3个工作日内，乙方应支付订单金额的【30】%作为预付款；自产品到达越南目的港/站后3个工作日内，乙方应支付订单金额剩余的全部款项。甲方将在收到订单100%款项后送货到乙方指定的收货地点。 Within 3 business days after the effective date of the order, the Buyer shall pay 【30】% of the order amount as advance payment; within 3 business days after the Products arrive at the port/station of destination in Vietnam, the Buyer shall pay the remaining full amount of the order. The Seller will deliver the Products to the receiving location designated by the Buyer upon receipt of 100% of the order payment. | D10: 订单生效之日起3个工作日内，乙方应支付订单金额的【30】%作为预付款；自产品到达越南目的港/站后3个工作日内，乙方应支付订单金额剩余的全部款项。甲方将在收到订单100%款项后送货到乙方指定的收货地点。 Trong vòng 03 ngày làm việc kể từ ngày đơn hàng có hiệu lực, Bên Mua phải thanh toán 【30】% giá trị đơn hàng dưới hình thức tiền tạm ứng; trong vòng 03 ngày làm việc kể từ ngày sản phẩm đến cảng/ga đích tại Việt Nam, Bên Mua phải thanh toán toàn bộ số tiền còn lại của đơn hàng. Bên Bán sẽ giao hàng đến địa điểm nhận hàng do Bên Mua chỉ định sau khi nhận được 100% giá trị thanh toán của đơn hàng.
B11: 送达约定到货地点 | C11: 订单生效之日起3个工作日内，乙方应支付订单金额的【50】%作为预付款；自产品到达越南目的港/站后3个工作日内，乙方应支付订单金额剩余的全部款项。甲方将在收到订单100%款项后送货到乙方指定的收货地点。 Within 3 business days after the effective date of the order, the Buyer shall pay 【50】% of the order amount as advance payment; within 3 business days after the Products arrive at the port/station of destination in Vietnam, the Buyer shall pay the remaining full amount of the order. The Seller will deliver the Products to the receiving location designated by the Buyer upon receipt of 100% of the order payment. | D11: 订单生效之日起3个工作日内，乙方应支付订单金额的【50】%作为预付款；自产品到达越南目的港/站后3个工作日内，乙方应支付订单金额剩余的全部款项。甲方将在收到订单100%款项后送货到乙方指定的收货地点。 Trong vòng 03 ngày làm việc kể từ ngày đơn hàng có hiệu lực, Bên Mua phải thanh toán 【50】% giá trị đơn hàng dưới hình thức tiền tạm ứng; trong vòng 03 ngày làm việc kể từ ngày sản phẩm đến cảng/ga đích tại Việt Nam, Bên Mua phải thanh toán toàn bộ số tiền còn lại của đơn hàng. Bên Bán sẽ giao hàng đến địa điểm nhận hàng do Bên Mua chỉ định sau khi nhận được 100% giá trị thanh toán của đơn hàng.
B12: 实际以信用证要求为准 | C12: 买方应使用信用证向卖方支付上述“总值”的全部金额，详细约定见卖方同意的信用证内容以及双方就信用证另行签订的《补充协议》（具体名称以双方实际签订的协议为准）。 The Buyer shall pay the Seller the full amount of the aforementioned Total Value via letter of credit, in accordance with the content of the letter of credit agreed by the Seller and the Supplementary Agreement (the specific title of which shall be subject to the actual agreement concluded) separately entered into by the Parties regarding payment via letter of credit. | D12: 买方应使用信用证向卖方支付上述“总值”的全部金额，详细约定见卖方同意的信用证内容以及双方就信用证另行签订的《补充协议》（具体名称以双方实际签订的协议为准）。 Bên Mua phải thanh toán toàn bộ số tiền của "Tổng giá trị" nói trên cho Bên Bán bằng Thư tín dụng (L/C), chi tiết quy định theo nội dung L/C đã được Bên Bán chấp thuận và "Thỏa thuận bổ sung" (tên gọi cụ thể sẽ theo hợp đồng thực tế được ký kết giữa hai bên) được hai Bên ký kết riêng liên quan đến việc thanh toán bằng L/C.
C13: 不作为一级经销商合作。Not cooperating as a Tier 1 distributor. | D13: 不作为一级经销商合作。Không hợp tác với tư cách nhà phân phối cấp 1.
B14: 送达约定到货地点 | D14: 买方（乙方）须在签订采购订单后立即支付订单总金额的 50%，剩余的 50% 款项必须在收货前（卖方交货前）全部付清。买方付款后，须通过电子邮件或在线聊天软件向卖方提供有效的付款凭证；卖方只有在收到足额款项或有效付款凭证后，才会安排生产、检验、检疫及进出口手续。同时，任何因转账产生的费用（包括但不限于中转行费用）均由买方（乙方）承担。 Bên B thanh toán cho Bên A trước 50% tổng giá trị đơn hàng ngay khi ký Đơn đặt hàng, và 50% còn lại thanh toán hết trước khi nhận hàng (trước khi Bên A giao hàng). Sau khi chuyển khoản, Bên B cần cung cấp chứng từ thanh toán hợp lệ qua email hoặc ứng dụng trò chuyện trực tuyến; Bên A chỉ sắp xếp các thủ tục sản xuất, kiểm tra, kiểm dịch, xuất nhập khẩu sau khi nhận đủ số tiền hoặc chứng từ thanh toán này. Đồng thời, bất kỳ khoản phí chuyển khoản nào phát sinh (bao gồm nhưng không giới hạn ở phí ngân hàng trung chuyển) sẽ hoàn toàn do Bên B chịu.
B15: 送达约定到货地点 | D15: 订单采用【定金30%】的方式。乙方应自订单生效之日起10个工作日内（以甲方所在地时间为准）将【付定金30%】和在通知到货后付清剩余的70%货款以【电汇】方式支付至甲方指定账户，并以邮件或即时通讯软件的方式提供有效的支付凭证，由此产生的转账费用（包括但不限于中转行手续费）由乙方承担。甲方将在收到足额货款或支付凭证后安排生产、检验检疫及进出口手续。 Đơn đặt hàng theo phương thức thanh toán 【đặt cọc 30%】. Trong vòng 10 ngày làm việc kể từ ngày đơn đặt hàng có hiệu lực (giờ địa phương của Bên A), Bên B cần thanh toán 【đặt cọc 30%】 và thanh toán hết 70% phần còn lại sau khi có thông báo hàng đến bằng 【Chuyển khoản điện tử】 vào tài khoản do Bên A chỉ định và cung cấp chứng từ thanh toán hợp lệ qua email hoặc tin nhắn. Bất kỳ khoản phí chuyển khoản nào phát sinh (bao gồm nhưng không giới hạn ở phí ngân hàng trung chuyển) sẽ do Bên B chịu. Bên A sẽ thu xếp các thủ tục sản xuất, kiểm tra, kiểm dịch và xuất nhập khẩu sau khi nhận đủ tiền thanh toán hoặc chứng từ thanh toán.
B16: 送达约定到货地点 | D16: 甲方（买方）须在乙方（卖方）交货前，预付（押金）100% 的订单金额。Bên A đặt cọc 100% giá trị đơn đặt hàng trước thời điểm bên B giao hàng.
B17: 送达约定到货地点 | D17: 乙方（买方）在签署订单时向甲方支付总金额的 30% 作为预付款；其余 70% 须在甲方收货前全部付清。Bên B thanh toán cho Bên A trước 30% tổng giá trị đơn hàng ngay khi ký Đơn đặt hàng, 70% còn lại thanh toán hết trước khi nhận hàng.

Sheet 产品订单（暂不含工业物料，待更新物料编码及装运信息）
E1: =IF(ISNUMBER(SEARCH("海运",G4)),"海运，请选择1*20'或2*20'或1*40'或2*40’等",IF(ISNUMBER(SEARCH("铁路运输",G4)),"铁路运输，请选择1*20'或2*20'或1*40'或2*40’等","汽运请选择1*32吨汽车或2*32吨汽车")) -> 汽运请选择1*32吨汽车或2*32吨汽车 | F1: 柜量 | G1: 1*20' | J1: 买方名称(中文) | K1: 越南黄天发贸易有限公司 | N1: 客户编号 | P1: =VLOOKUP(K1,客户基础数据!C:W,21,FALSE) -> 2141020110 | R1: Số tài khoản công ty: | S1: =VLOOKUP(K1,客户基础数据!C:Z,24,FALSE) -> 1363638888 | V1: 区域 | W1: =VLOOKUP(P1,付款条款汇总!A:D,4,FALSE()) -> 南部 | AJ1: 订单备注 | AK1: 如有特殊装柜要求或者额外的订单要求，请在此处做好备注说明 | AR1: 请选择 | AS1: 请选择 | AT1: 请选择 | AU1: 请选择 | AW1: 请选择 | AX1: 请选择 | AY1: 请选择
F2: 订单号 | G2: =TEXT(G3,"yyyymmdd")&"001" -> 20261001001 | H2: 和天贸系统中海外订单号码一致 | J2: 买方名称(VN) | K2: =VLOOKUP(K1,客户基础数据!C1:E195,2,FALSE) -> CÔNG TY TNHH THƯƠNG MẠI HOÀNG THIÊN PHÁT | N2: 客户税号 | P2: =VLOOKUP(K1,客户基础数据!C:V,5,FALSE) -> 0316353410 | R2: 公司账号： | S2: =VLOOKUP(K1,客户基础数据!C:Z,24,FALSE) -> 1363638888 | V2: 仓库地址 | W2: Số 132 đường Trần Phú, Phường Kỳ Lừa, Lạng Sơn | X2: 手动选择仓库地址，如果没有正确地址可以选择，请告知 | AR2: 1*40' | AS2: HAIPHONG ,VIETNAM | AT2: C&F | AU2: 海运 | AW2: 专柜8送1 | AX2: 1月 | AY2: 红河区
F3: 订单日期 | G3: 46296 | H3: 必须录入合同时间 | J3: 买方地址(VN) | K3: =VLOOKUP(K1,客户基础数据!C1:H195,6,FALSE) -> 387 Phan Văn Trị, Phường Bình Lợi Trung, TP Hồ Chí Minh, Việt Nam. | N3: Người đại diện theo pháp luật: | P3: =VLOOKUP(K1,客户基础数据!C:V,8,FALSE) -> TRAN MINH HOANG | R3: Tại Ngân hàng: | S3: =VLOOKUP(K1,客户基础数据!C:Y,22,FALSE) -> Ngân hàng TMCP Á Châu (ACB) | V3: 仓库联系人 | W3: =VLOOKUP(W2,客户地址信息汇总!K:N,4,FALSE()) -> Anh Long（谅山） | AR3: 2*40' | AS3: HUU NGHI, LANG SON ,VIETNAM | AT3: FOB | AU3: 铁路运输 | AW3: 常规10送1 | AX3: 2月 | AY3: 东北区
F4: 运输方式 | G4: RDC仓交货 | H4: 必须选择运输方式 | J4: 买方电话 | K4: =VLOOKUP(K1,客户基础数据!C1:I195,7,FALSE) -> 0939368123 | N4: 公司法人代表： | P4: =VLOOKUP(K1,客户基础数据!C:V,9,FALSE) -> 陈明黄 | R4: 银行名称： | S4: =VLOOKUP(K1,客户基础数据!C:Y,23,FALSE) -> 亚洲贸易股份银行（ACB) | V4: 仓库联系电话 | W4: =VLOOKUP(W2,客户地址信息汇总!K:N,2,FALSE()) -> 0942854827 | AJ4: 交付说明 | AK4: 目前出口料酒产品、古道系列产品、陈醋和香醋产品均在宿迁工厂生产，未达整柜发运量的均需调拨至高明安排发运，受此影响交付需延长7-10天，请知悉。 | AR4: 3*40' | AS4: CAT LAI PORT ,HO CHI MINH,VIETNAM | AT4: EXW | AU4: 公路运输 | AW4: 营销费用申请表 | AX4: 3月 | AY4: 南部区
E5: =IF(ISNUMBER(SEARCH("海运",G4)),"海运，请选择C&F",IF(ISNUMBER(SEARCH("铁路运输",G4)),"铁路运输，请选择C&F","汽运/RDC仓交付,请选择DAP")) -> 汽运/RDC仓交付,请选择DAP | F5: 贸易条款 | G5: DAP | N5: Chức vụ: | P5: =VLOOKUP(K1,客户基础数据!C:V,10,FALSE) -> TỔNG GIÁM ĐỐC | R5: 买方地址(非VN) | S5: =VLOOKUP(K1,客户基础数据!C:AD,28,FALSE) -> 越南胡志明市平盛郡潘文治路387号 | V5: 支付条款 | W5: 订单生效之日起3个工作日内，乙方应支付订单金额的【50】%作为预付款；自产品到达越南目的港/站后3个工作日内，乙方应支付订单金额剩余的全部款项。甲方将在收到订单100%款项后送货到乙方指定的收货地点。 Trong vòng 03 ngày làm việc kể từ ngày đơn hàng có hiệu lực, Bên Mua phải thanh toán 【50】% giá trị đơn hàng dưới hình thức tiền tạm ứng; trong vòng 03 ngày làm việc kể từ ngày sản phẩm đến cảng/ga đích tại Việt Nam, Bên Mua phải thanh toán toàn bộ số tiền còn lại của đơn hàng. Bên Bán sẽ giao hàng đến địa điểm nhận hàng do Bên Mua chỉ định sau khi nhận được 100% giá trị thanh toán của đơn hàng. | X5: =IF(W1="北部","暂不考虑RDC仓发货，支付条款请选择不涉及RDC仓","可以考虑RDC仓发货，支付条款请根据实际情况选择") -> 可以考虑RDC仓发货，支付条款请根据实际情况选择 | AR5: 1*20' | AS5: CHI MA, LANG SON，VIETNAM | AT5: DAP | AU5: RDC仓交货 | AX5: 4月
E6: =IF(ISNUMBER(SEARCH("海运",G4)),"海运，请选择HAI PHONG或者CAT LAI PORT, HCM或者DA NANG,VIETNAM",IF(ISNUMBER(SEARCH("铁路运输",G4)),"铁路运输，YENVIEN，VIETNAM","汽运或铁路运输请选择CHI MA,LAN SON或HUU NGHI ,LANSON")) -> 汽运或铁路运输请选择CHI MA,LAN SON或HUU NGHI ,LANSON | F6: 目的港 | G6: HAIPHONG ,VIETNAM | H6: 必须选择目的港 | N6: 代表职位（中文） | P6: =VLOOKUP(K1,客户基础数据!C:V,11,FALSE) -> 总经理 | AI6: 总毛重 | AJ6: =AD127 -> 971.4 | AK6: 港口限重：部分国家的港口/公路对货柜有限重要求，请注意提前了解避免货柜超重 | AR6: 2*20' | AS6: DA NANG,VIETNAM | AX6: 5月
F7: 交货期 | G7: IN 2026 | AI7: 合计满柜数 | AJ7: =ROUND(AI127,1) -> 0.1 | AK7: 多个品种或者多个规格混装的单柜，满柜系数不能超过0.98 !!! | AR7: 3*20' | AS7: YENVIEN，VIETNAM | AX7: 6月
C8: 单元格C12开始，自动排列序号“如1-8” ，根据A列数到的“1”的数量，生成数字。不需要手动修改 | AI8: SKU数量 | AJ8: =COUNTA(L12:L125) -> 5 | AK8: 多柜的请自行做好分柜并核算好满柜系数，避免产生满载情况 | AR8: 4*20' | AS8: DONG DANG，VIETNAM | AX8: 7月
A9: 单元格A12开始，序号“1” 已经设定好公式，只要总箱数不等于“0”，均会显示为“1” | G9: 唛头(Marks)： | L9: 请注意：个别物料有最低起订量需求，譬如海鲜酱油等。 请查看单元格：AK20 | AE9: 未特殊备注的产品最低起订量为100箱 | AI9: 专柜数量 | AJ9: =AJ127 -> 0 | AK9: 客户如需下40尺柜，货物总毛重不能超过26吨。 | AR9: 1*32吨汽车 | AX9: 8月
B10: 小类汇总 | D10: 物料编码 | E10: 标签 | F10: 小类 | G10: 商 品 名 称 (英语) | H10: 商 品 名 称(越南语） | I10: 商 品 名 称(中文） | J10: 商 品 名 称(中文） | K10: 价格(VND) | L10: 产品数量 | M10: 赠品数量 | N10: 总数量 | O10: 折扣比例预判 | P10: 产品价值*VAT- | Q10: 赠品价值*VAT- | R10: 总价值*VAT- | S10: VAT税率 | T10: 产品价值*VAT+ | U10: 赠品价值*VAT+ | V10: 总价值*VAT+ | W10: 报检报关用产品品名 | X10: 产品规格 | Y10: 每 箱 Per Carton | AE10: 全 部 Total | AG10: CTNS/20' | AH10: CTNS/40' | AR10: 2*32吨汽车 | AX10: 9月
G11: Commodities Name(EN) | H11: Commodities Name(VN) | I11: Commodities Name(CN) | J11: Commodities Name(CN) | K11: Price (VND) | L11: (箱) | M11: (箱) | N11: (箱) | P11: (VND) | Q11: (VND) | R11: (VND) | S11: % | T11: (VND) | U11: (VND) | V11: (VND) | Y11: 毛重(KG) | Z11: 净重(KG) | AA11: 尺码(M) | AD11: 毛重(KG) | AE11: 净重(KG) | AF11: 体积(M3) | AI11: 20'满柜核算 | AJ11: 20'专柜数量 | AK11: 40'满柜核算 | AL11: 下单备注 | AY11: 10月
A12: =IF(N12<>0,1,"") | B12: 招牌味极鲜酿造酱油 | C12: =IFERROR(RANK(A12,$A$12:$A$125,0)+COUNTIFS(A$12:A12,A12)-1,"") | D12: 89180275005 | E12: 中文标签 | F12: 招牌味极鲜酿造酱油 | G12: SEASONING SOY SAUCE 750ML*6 | H12: HADAY NƯỚC TƯƠNG CAO CẤP 750ML*6 | I12: 出口海天牌招牌味极鲜酿造酱油750ML*6(越南公司用)(玻璃瓶) | J12: 海天牌招牌味极鲜酿造酱油750ML*6 | K12: 226600 | N12: =L12+M12 -> 0 | O12: =IF(M12/N12>1/9,"大于8送1",IF(ABS(M12/N12-1/9)<0.0001,"8送1",IF(M12/N12<1/9,IF(M12/N12>1/10,"8送1和9送1之间",IF(ABS(M12/N12-1/10)<0.0001,"9送1",IF(M12/N12<1/10,IF(M12/N12>1/11,"9送1和10送1之间",IF(ABS(M12/N12-1/11)<0.0001,"10送1","小于10送1")))))))) -> #DIV/0! | P12: =K12*L12 -> 0 | Q12: =K12*M12 -> 0 | R12: =N12*K12 -> 0 | S12: 0.08 | T12: =P12*(1+$S12) -> 0 | U12: =Q12*(1+$S12) -> 0 | V12: =R12*(1+$S12) -> 0 | W12: ="海天牌"&F12 -> 海天牌招牌味极鲜酿造酱油 | X12: 750ML*6 | Y12: 8.20 | Z12: 5.40 | AA12: 0.273 | AB12: 0.181 | AC12: 0.277 | AD12: =(L12+M12)*Y12 -> 0 | AE12: =(L12+M12)*Z12 -> 0 | AF12: =ROUND((L12+M12)*AA12*AB12*AC12,2) -> 0 | AG12: 2000.00 | AH12: 3410.00 | AI12: =(L12+M12)/AG12 -> 0 | AJ12: =ROUNDDOWN(AI12/0.95,0) -> 0 | AK12: =(L12+M12)/AH12 -> 0 | AY12: 11月
A13: =IF(N13<>0,1,"") | C13: =IFERROR(RANK(A13,$A$12:$A$125,0)+COUNTIFS(A$12:A13,A13)-1,"") | D13: 89180210903 | E13: 中文标签 | F13: 招牌味极鲜酿造酱油 | G13: SEASONING SOY SAUCE 1.9L*6 | H13: HADAY NƯỚC TƯƠNG CAO CẤP 1.9L*6 | I13: 出口海天牌招牌味极鲜酿造酱油1.9L*6(越南公司用)(PET瓶) | J13: 海天牌招牌味极鲜酿造酱油1.9L*6 | K13: 466600 | N13: =L13+M13 -> 0 | O13: =IF(M13/N13>1/9,"大于8送1",IF(ABS(M13/N13-1/9)<0.0001,"8送1",IF(M13/N13<1/9,IF(M13/N13>1/10,"8送1和9送1之间",IF(ABS(M13/N13-1/10)<0.0001,"9送1",IF(M13/N13<1/10,IF(M13/N13>1/11,"9送1和10送1之间",IF(ABS(M13/N13-1/11)<0.0001,"10送1","小于10送1")))))))) -> #DIV/0! | P13: =K13*L13 -> 0 | Q13: =K13*M13 -> 0 | R13: =N13*K13 -> 0 | S13: 0.08 | T13: =P13*(1+$S13) -> 0 | U13: =Q13*(1+$S13) -> 0 | V13: =R13*(1+$S13) -> 0 | W13: ="海天牌"&F13 -> 海天牌招牌味极鲜酿造酱油 | X13: 1.9L*6 | Y13: 14.90 | Z13: 14.00 | AA13: 0.351 | AB13: 0.238 | AC13: 0.303 | AD13: =(L13+M13)*Y13 -> 0 | AE13: =(L13+M13)*Z13 -> 0 | AF13: =ROUND((L13+M13)*AA13*AB13*AC13,2) -> 0 | AG13: 1100.00 | AH13: 1880.00 | AI13: =(L13+M13)/AG13 -> 0 | AJ13: =ROUNDDOWN(AI13/0.95,0) -> 0 | AK13: =(L13+M13)/AH13 -> 0 | AY13: 12月
A14: =IF(N14<>0,1,"") | B14: 味极鲜酱油(经典版) | C14: =IFERROR(RANK(A14,$A$12:$A$125,0)+COUNTIFS(A$12:A14,A14)-1,"") | D14: 89107275005 | E14: 中文标签 | F14: 味极鲜酱油(经典版) | G14: PREMIUM SOY SAUCE (CLASSIC VERSION) 750ML*6 | H14: NƯỚC TƯƠNG CAO CẤP (VỊ TRUYỀN THỐNG) 750ML*6 | I14: 出口海天牌味极鲜酱油(经典版)750ML*6(越南公司用)(玻璃瓶) | J14: 海天牌味极鲜酱油(经典版)750ML*6 | K14: 204500 | N14: =L14+M14 -> 0 | O14: =IF(M14/N14>1/9,"大于8送1",IF(ABS(M14/N14-1/9)<0.0001,"8送1",IF(M14/N14<1/9,IF(M14/N14>1/10,"8送1和9送1之间",IF(ABS(M14/N14-1/10)<0.0001,"9送1",IF(M14/N14<1/10,IF(M14/N14>1/11,"9送1和10送1之间",IF(ABS(M14/N14-1/11)<0.0001,"10送1","小于10送1")))))))) -> #DIV/0! | P14: =K14*L14 -> 0 | Q14: =K14*M14 -> 0 | R14: =N14*K14 -> 0 | S14: 0.08 | T14: =P14*(1+$S14) -> 0 | U14: =Q14*(1+$S14) -> 0 | V14: =R14*(1+$S14) -> 0 | W14: ="海天牌"&F14 -> 海天牌味极鲜酱油(经典版) | X14: 750ML*6 | Y14: 8.3 | Z14: 5.6 | AA14: 0.273 | AB14: 0.181 | AC14: 0.277 | AD14: =(L14+M14)*Y14 -> 0 | AE14: =(L14+M14)*Z14 -> 0 | AF14: =ROUND((L14+M14)*AA14*AB14*AC14,2) -> 0 | AG14: 2000.00 | AH14: 3330.00 | AI14: =(L14+M14)/AG14 -> 0 | AJ14: =ROUNDDOWN(AI14/0.95,0) -> 0 | AK14: =(L14+M14)/AH14 -> 0
A15: =IF(N15<>0,1,"") | C15: =IFERROR(RANK(A15,$A$12:$A$125,0)+COUNTIFS(A$12:A15,A15)-1,"") | D15: 89107238005 | E15: 中文标签 | F15: 味极鲜酱油(经典版) | G15: PREMIUM SOY SAUCE (CLASSIC VERSION) 380ML*12 | H15: NƯỚC TƯƠNG CAO CẤP (VỊ TRUYỀN THỐNG) 380ML*12 | I15: 出口海天牌味极鲜酱油(经典版)380ML*12(越南公司用)(玻璃瓶) | J15: 海天牌味极鲜酱油(经典版)380ML*12 | K15: 236000 | N15: =L15+M15 -> 0 | O15: =IF(M15/N15>1/9,"大于8送1",IF(ABS(M15/N15-1/9)<0.0001,"8送1",IF(M15/N15<1/9,IF(M15/N15>1/10,"8送1和9送1之间",IF(ABS(M15/N15-1/10)<0.0001,"9送1",IF(M15/N15<1/10,IF(M15/N15>1/11,"9送1和10送1之间",IF(ABS(M15/N15-1/11)<0.0001,"10送1","小于10送1")))))))) -> #DIV/0! | P15: =K15*L15 -> 0 | Q15: =K15*M15 -> 0 | R15: =N15*K15 -> 0 | S15: 0.08 | T15: =P15*(1+$S15) -> 0 | U15: =Q15*(1+$S15) -> 0 | V15: =R15*(1+$S15) -> 0 | W15: ="海天牌"&F15 -> 海天牌味极鲜酱油(经典版) | X15: 380ML*12 | Y15: 8.9 | Z15: 5.6 | AA15: 0.284 | AB15: 0.213 | AC15: 0.217 | AD15: =(L15+M15)*Y15 -> 0 | AE15: =(L15+M15)*Z15 -> 0 | AF15: =ROUND((L15+M15)*AA15*AB15*AC15,2) -> 0 | AG15: 2050.00 | AH15: 3150.00 | AI15: =(L15+M15)/AG15 -> 0 | AJ15: =ROUNDDOWN(AI15/0.95,0) -> 0 | AK15: =(L15+M15)/AH15 -> 0
A16: =IF(N16<>0,1,"") | C16: =IFERROR(RANK(A16,$A$12:$A$125,0)+COUNTIFS(A$12:A16,A16)-1,"") | D16: 89107210905 | E16: 中文标签 | F16: 味极鲜酱油(经典版) | G16: PREMIUM SOY SAUCE (CLASSIC VERSION) 1.9L*6 | H16: NƯỚC TƯƠNG CAO CẤP (VỊ TRUYỀN THỐNG) 1.9L*6 | I16: 出口海天牌味极鲜酱油(经典版)1.9L*6(越南公司用)(PET瓶) | J16: 海天牌味极鲜酱油(经典版)1.9L*6 | K16: 369600 | N16: =L16+M16 -> 0 | O16: =IF(M16/N16>1/9,"大于8送1",IF(ABS(M16/N16-1/9)<0.0001,"8送1",IF(M16/N16<1/9,IF(M16/N16>1/10,"8送1和9送1之间",IF(ABS(M16/N16-1/10)<0.0001,"9送1",IF(M16/N16<1/10,IF(M16/N16>1/11,"9送1和10送1之间",IF(ABS(M16/N16-1/11)<0.0001,"10送1","小于10送1")))))))) -> #DIV/0! | P16: =K16*L16 -> 0 | Q16: =K16*M16 -> 0 | R16: =N16*K16 -> 0 | S16: 0.08 | T16: =P16*(1+$S16) -> 0 | U16: =Q16*(1+$S16) -> 0 | V16: =R16*(1+$S16) -> 0 | W16: ="海天牌"&F16 -> 海天牌味极鲜酱油(经典版) | X16: 1.9L*6 | Y16: 15 | Z16: 14.1 | AA16: 0.351 | AB16: 0.234 | AC16: 0.299 | AD16: =(L16+M16)*Y16 -> 0 | AE16: =(L16+M16)*Z16 -> 0 | AF16: =ROUND((L16+M16)*AA16*AB16*AC16,2) -> 0 | AG16: 1120.00 | AH16: 1870.00 | AI16: =(L16+M16)/AG16 -> 0 | AJ16: =ROUNDDOWN(AI16/0.95,0) -> 0 | AK16: =(L16+M16)/AH16 -> 0
A17: =IF(N17<>0,1,"") | C17: =IFERROR(RANK(A17,$A$12:$A$125,0)+COUNTIFS(A$12:A17,A17)-1,"") | D17: 89107240905 | E17: 中文标签 | F17: 味极鲜酱油(经典版) | G17: PREMIUM SOY SAUCE (CLASSIC VERSION) 4.9L*6 | H17: NƯỚC TƯƠNG CAO CẤP (VỊ TRUYỀN THỐNG) 4.9L*2 | I17: 出口海天牌味极鲜酱油(经典版)4.9L*2(越南公司用)(PET瓶) | J17: 海天牌味极鲜酱油(经典版)4.9L*2 | K17: 279900 | N17: =L17+M17 -> 0 | O17: =IF(M17/N17>1/9,"大于8送1",IF(ABS(M17/N17-1/9)<0.0001,"8送1",IF(M17/N17<1/9,IF(M17/N17>1/10,"8送1和9送1之间",IF(ABS(M17/N17-1/10)<0.0001,"9送1",IF(M17/N17<1/10,IF(M17/N17>1/11,"9送1和10送1之间",IF(ABS(M17/N17-1/11)<0.0001,"10送1","小于10送1")))))))) -> #DIV/0! | P17: =K17*L17 -> 0 | Q17: =K17*M17 -> 0 | R17: =N17*K17 -> 0 | S17: 0.08 | T17: =P17*(1+$S17) -> 0 | U17: =Q17*(1+$S17) -> 0 | V17: =R17*(1+$S17) -> 0 | W17: ="海天牌"&F17 -> 海天牌味极鲜酱油(经典版) | X17: 4.9L*2 | Y17: 12.7 | Z17: 12.1 | AA17: 0.31 | AB17: 0.155 | AC17: 0.347 | AD17: =(L17+M17)*Y17 -> 0 | AE17: =(L17+M17)*Z17 -> 0 | AF17: =ROUND((L17+M17)*AA17*AB17*AC17,2) -> 0 | AG17: 1580.00 | AH17: 2200.00 | AI17: =(L17+M17)/AG17 -> 0 | AJ17: =ROUNDDOWN(AI17/0.95,0) -> 0 | AK17: =(L17+M17)/AH17 -> 0
A18: =IF(N18<>0,1,"") | B18: 0味极鲜酱油 | C18: =IFERROR(RANK(A18,$A$12:$A$125,0)+COUNTIFS(A$12:A18,A18)-1,"") | D18: 89101838005 | E18: 中文标签 | F18: 0味极鲜酱油 | G18: 0 PREMIUM SOY SAUCE 380ML*12 | H18: HADAY NƯỚC TƯƠNG CAO CẤP 0 PHỤ GIA THỰC PHẨM 380ML*12 | I18: 出口海天牌0味极鲜酱油380ML*12(越南公司用)(玻璃瓶) | J18: 海天牌0味极鲜酱油380ML*12 | K18: 282600 | N18: =L18+M18 -> 0 | O18: =IF(M18/N18>1/9,"大于8送1",IF(ABS(M18/N18-1/9)<0.0001,"8送1",IF(M18/N18<1/9,IF(M18/N18>1/10,"8送1和9送1之间",IF(ABS(M18/N18-1/10)<0.0001,"9送1",IF(M18/N18<1/10,IF(M18/N18>1/11,"9送1和10送1之间",IF(ABS(M18/N18-1/11)<0.0001,"10送1","小于10送1")))))))) -> #DIV/0! | P18: =K18*L18 -> 0 | Q18: =K18*M18 -> 0 | R18: =N18*K18 -> 0 | S18: 0.08 | T18: =P18*(1+$S18) -> 0 | U18: =Q18*(1+$S18) -> 0 | V18: =R18*(1+$S18) -> 0 | W18: ="海天牌"&F18 -> 海天牌0味极鲜酱油 | X18: 380ML*12 | Y18: 8.80 | Z18: 5.50 | AA18: 0.284 | AB18: 0.213 | AC18: 0.217 | AD18: =(L18+M18)*Y18 -> 0 | AE18: =(L18+M18)*Z18 -> 0 | AF18: =ROUND((L18+M18)*AA18*AB18*AC18,2) -> 0 | AG18: 2050.00 | AH18: 3180.00 | AI18: =(L18+M18)/AG18 -> 0 | AJ18: =ROUNDDOWN(AI18/0.95,0) -> 0 | AK18: =(L18+M18)/AH18 -> 0
A19: =IF(N19<>0,1,"") | C19: =IFERROR(RANK(A19,$A$12:$A$125,0)+COUNTIFS(A$12:A19,A19)-1,"") | D19: 89101875005 | E19: 中文标签 | F19: =F18 -> 0味极鲜酱油 | G19: 0 PREMIUM SOY SAUCE 750ML*6 | H19: HADAY NƯỚC TƯƠNG CAO CẤP 0 PHỤ GIA THỰC PHẨM 750ML*6 | I19: 出口海天牌0味极鲜酱油750ML*6(越南公司用)(玻璃瓶) | J19: 海天牌0味极鲜酱油750ML*6 | K19: 242600 | N19: =L19+M19 -> 0 | O19: =IF(M19/N19>1/9,"大于8送1",IF(ABS(M19/N19-1/9)<0.0001,"8送1",IF(M19/N19<1/9,IF(M19/N19>1/10,"8送1和9送1之间",IF(ABS(M19/N19-1/10)<0.0001,"9送1",IF(M19/N19<1/10,IF(M19/N19>1/11,"9送1和10送1之间",IF(ABS(M19/N19-1/11)<0.0001,"10送1","小于10送1")))))))) -> #DIV/0! | P19: =K19*L19 -> 0 | Q19: =K19*M19 -> 0 | R19: =N19*K19 -> 0 | S19: 0.08 | T19: =P19*(1+$S19) -> 0 | U19: =Q19*(1+$S19) -> 0 | V19: =R19*(1+$S19) -> 0 | W19: ="海天牌"&F19 -> 海天牌0味极鲜酱油 | X19: 750ML*6 | Y19: 8.20 | Z19: 5.50 | AA19: 0.273 | AB19: 0.181 | AC19: 0.277 | AD19: =(L19+M19)*Y19 -> 0 | AE19: =(L19+M19)*Z19 -> 0 | AF19: =ROUND((L19+M19)*AA19*AB19*AC19,2) -> 0 | AG19: 2000.00 | AH19: 3410.00 | AI19: =(L19+M19)/AG19 -> 0 | AJ19: =ROUNDDOWN(AI19/0.95,0) -> 0 | AK19: =(L19+M19)/AH19 -> 0
A20: =IF(N20<>0,1,"") | C20: =IFERROR(RANK(A20,$A$12:$A$125,0)+COUNTIFS(A$12:A20,A20)-1,"") | D20: 89101817503 | E20: 中文标签 | F20: =F19 -> 0味极鲜酱油 | G20: 0 PREMIUM SOY SAUCE 1.75L*6 | H20: HADAY NƯỚC TƯƠNG CAO CẤP 0 PHỤ GIA THỰC PHẨM 1.75L*6 | I20: 出口海天牌0味极鲜酱油1.75L*6(越南公司用)(PET瓶) | J20: 海天牌0味极鲜酱油1.75L*6 | K20: 455900 | N20: =L20+M20 -> 0 | O20: =IF(M20/N20>1/9,"大于8送1",IF(ABS(M20/N20-1/9)<0.0001,"8送1",IF(M20/N20<1/9,IF(M20/N20>1/10,"8送1和9送1之间",IF(ABS(M20/N20-1/10)<0.0001,"9送1",IF(M20/N20<1/10,IF(M20/N20>1/11,"9送1和10送1之间",IF(ABS(M20/N20-1/11)<0.0001,"10送1","小于10送1")))))))) -> #DIV/0! | P20: =K20*L20 -> 0 | Q20: =K20*M20 -> 0 | R20: =N20*K20 -> 0 | S20: 0.08 | T20: =P20*(1+$S20) -> 0 | U20: =Q20*(1+$S20) -> 0 | V20: =R20*(1+$S20) -> 0 | W20: ="海天牌"&F20 -> 海天牌0味极鲜酱油 | X20: 1.75L*6 | Y20: 13.60 | Z20: 12.80 | AA20: 0.34 | AB20: 0.224 | AC20: 0.294 | AD20: =(L20+M20)*Y20 -> 0 | AE20: =(L20+M20)*Z20 -> 0 | AF20: =ROUND((L20+M20)*AA20*AB20*AC20,2) -> 0 | AG20: 1260.00 | AH20: 2060.00 | AI20: =(L20+M20)/AG20 -> 0 | AJ20: =ROUNDDOWN(AI20/0.95,0) -> 0 | AK20: =(L20+M20)/AH20 -> 0
A21: =IF(N21<>0,1,"") | B21: 海鲜酱油（经典版） | C21: =IFERROR(RANK(A21,$A$12:$A$125,0)+COUNTIFS(A$12:A21,A21)-1,"") | D21: 89102050006 | E21: 中文标签 | F21: 海鲜酱油（经典版） | G21: TASTY SEAFOOD FLAVORED SOY SAUCE (CLASSIC VERSION) 500ML*12 | H21: HADAY NƯỚC TƯƠNG HẢI SẢN 500ML*12 | I21: 出口海天牌海鲜酱油(经典版)500ML*12(越南公司用)(玻璃瓶) | J21: 海天牌海鲜酱油(经典版)500ML*12 | K21: 277800 | N21: =L21+M21 -> 0 | O21: =IF(M21/N21>1/9,"大于8送1",IF(ABS(M21/N21-1/9)<0.0001,"8送1",IF(M21/N21<1/9,IF(M21/N21>1/10,"8送1和9送1之间",IF(ABS(M21/N21-1/10)<0.0001,"9送1",IF(M21/N21<1/10,IF(M21/N21>1/11,"9送1和10送1之间",IF(ABS(M21/N21-1/11)<0.0001,"10送1","小于10送1")))))))) -> #DIV/0! | P21: =K21*L21 -> 0 | Q21: =K21*M21 -> 0 | R21: =N21*K21 -> 0 | S21: 0.08 | T21: =P21*(1+$S21) -> 0 | U21: =Q21*(1+$S21) -> 0 | V21: =R21*(1+$S21) -> 0 | W21: ="海天牌"&F21 -> 海天牌海鲜酱油（经典版） | X21: 500ML*12 | Y21: 10.50 | Z21: 7.40 | AA21: 0.272 | AB21: 0.206 | AC21: 0.258 | AD21: =(L21+M21)*Y21 -> 0 | AE21: =(L21+M21)*Z21 -> 0 | AF21: =ROUND((L21+M21)*AA21*AB21*AC21,2) -> 0 | AG21: 1850.00 | AH21: 2670.00 | AI21: =(L21+M21)/AG21 -> 0 | AJ21: =ROUNDDOWN(AI21/0.95,0) -> 0 | AK21: =(L21+M21)/AH21 -> 0
A22: =IF(N22<>0,1,"") | C22: =IFERROR(RANK(A22,$A$12:$A$125,0)+COUNTIFS(A$12:A22,A22)-1,"") | D22: 89102017506 | E22: 中文标签 | F22: =F21 -> 海鲜酱油（经典版） | G22: TASTY SEAFOOD FLAVORED SOY SAUCE (CLASSIC VERSION) 1.75L*6 | H22: HADAY NƯỚC TƯƠNG HẢI SẢN 1.75L*6 | I22: 出口海天牌海鲜酱油(经典版)1.75L*6(越南公司用)(PET瓶) | J22: 海天牌海鲜酱油(经典版)1.75L*6 | K22: 388900 | N22: =L22+M22 -> 0 | O22: =IF(M22/N22>1/9,"大于8送1",IF(ABS(M22/N22-1/9)<0.0001,"8送1",IF(M22/N22<1/9,IF(M22/N22>1/10,"8送1和9送1之间",IF(ABS(M22/N22-1/10)<0.0001,"9送1",IF(M22/N22<1/10,IF(M22/N22>1/11,"9送1和10送1之间",IF(ABS(M22/N22-1/11)<0.0001,"10送1","小于10送1")))))))) -> #DIV/0! | P22: =K22*L22 -> 0 | Q22: =K22*M22 -> 0 | R22: =N22*K22 -> 0 | S22: 0.08 | T22: =P22*(1+$S22) -> 0 | U22: =Q22*(1+$S22) -> 0 | V22: =R22*(1+$S22) -> 0 | W22: ="海天牌"&F22 -> 海天牌海鲜酱油（经典版） | X22: 1.75L*6 | Y22: 13.70 | Z22: 12.90 | AA22: 0.338 | AB22: 0.226 | AC22: 0.3 | AD22: =(L22+M22)*Y22 -> 0 | AE22: =(L22+M22)*Z22 -> 0 | AF22: =ROUND((L22+M22)*AA22*AB22*AC22,2) -> 0 | AG22: 1200.00 | AH22: 2040.00 | AI22: =(L22+M22)/AG22 -> 0 | AJ22: =ROUNDDOWN(AI22/0.95,0) -> 0 | AK22: =(L22+M22)/AH22 -> 0
A23: =IF(N23<>0,1,"") | B23: 海鲜酱油（经典版） | C23: =IFERROR(RANK(A23,$A$12:$A$125,0)+COUNTIFS(A$12:A23,A23)-1,"") | D23: 89102050005 | E23: 越南文标签 | F23: 海鲜酱油（经典版） | G23: TASTY SEAFOOD FLAVORED SOY SAUCE (CLASSIC VERSION) 500ML*12 | H23: HADAY NƯỚC TƯƠNG HẢI SẢN 500ML*12 | I23: 出口海天牌海鲜酱油(经典版)500ML*12(越南版；越南公司用)(玻璃瓶) | J23: 海天牌海鲜酱油(经典版)500ML*12 | K23: 277800 | N23: =L23+M23 -> 0 | O23: =IF(M23/N23>1/9,"大于8送1",IF(ABS(M23/N23-1/9)<0.0001,"8送1",IF(M23/N23<1/9,IF(M23/N23>1/10,"8送1和9送1之间",IF(ABS(M23/N23-1/10)<0.0001,"9送1",IF(M23/N23<1/10,IF(M23/N23>1/11,"9送1和10送1之间",IF(ABS(M23/N23-1/11)<0.0001,"10送1","小于10送1")))))))) -> #DIV/0! | P23: =K23*L23 -> 0 | Q23: =K23*M23 -> 0 | R23: =N23*K23 -> 0 | S23: 0.08 | T23: =P23*(1+$S23) -> 0 | U23: =Q23*(1+$S23) -> 0 | V23: =R23*(1+$S23) -> 0 | W23: ="海天牌"&F23 -> 海天牌海鲜酱油（经典版） | X23: 500ML*12 | Y23: 10.50 | Z23: 7.40 | AA23: 0.272 | AB23: 0.206 | AC23: 0.258 | AD23: =(L23+M23)*Y23 -> 0 | AE23: =(L23+M23)*Z23 -> 0 | AF23: =ROUND((L23+M23)*AA23*AB23*AC23,2) -> 0 | AG23: 1850.00 | AH23: 2670.00 | AI23: =(L23+M23)/AG23 -> 0 | AJ23: =ROUNDDOWN(AI23/0.95,0) -> 0 | AK23: =(L23+M23)/AH23 -> 0
A24: =IF(N24<>0,1,"") | C24: =IFERROR(RANK(A24,$A$12:$A$125,0)+COUNTIFS(A$12:A24,A24)-1,"") | D24: 89102017505 | E24: 越南文标签 | F24: =F23 -> 海鲜酱油（经典版） | G24: TASTY SEAFOOD FLAVORED SOY SAUCE (CLASSIC VERSION) 1.75L*6 | H24: HADAY NƯỚC TƯƠNG HẢI SẢN 1.75L*6 | I24: 出口海天牌海鲜酱油(经典版)1.75L*6(越南版；越南公司用)(PET瓶) | J24: 海天牌海鲜酱油(经典版)1.75L*6 | K24: 388900 | N24: =L24+M24 -> 0 | O24: =IF(M24/N24>1/9,"大于8送1",IF(ABS(M24/N24-1/9)<0.0001,"8送1",IF(M24/N24<1/9,IF(M24/N24>1/10,"8送1和9送1之间",IF(ABS(M24/N24-1/10)<0.0001,"9送1",IF(M24/N24<1/10,IF(M24/N24>1/11,"9送1和10送1之间",IF(ABS(M24/N24-1/11)<0.0001,"10送1","小于10送1")))))))) -> #DIV/0! | P24: =K24*L24 -> 0 | Q24: =K24*M24 -> 0 | R24: =N24*K24 -> 0 | S24: 0.08 | T24: =P24*(1+$S24) -> 0 | U24: =Q24*(1+$S24) -> 0 | V24: =R24*(1+$S24) -> 0 | W24: ="海天牌"&F24 -> 海天牌海鲜酱油（经典版） | X24: 1.75L*6 | Y24: 13.70 | Z24: 12.90 | AA24: 0.338 | AB24: 0.226 | AC24: 0.3 | AD24: =(L24+M24)*Y24 -> 0 | AE24: =(L24+M24)*Z24 -> 0 | AF24: =ROUND((L24+M24)*AA24*AB24*AC24,2) -> 0 | AG24: 1200.00 | AH24: 2040.00 | AI24: =(L24+M24)/AG24 -> 0 | AJ24: =ROUNDDOWN(AI24/0.95,0) -> 0 | AK24: =(L24+M24)/AH24 -> 0
A25: =IF(N25<>0,1,"") | B25: 海天金标生抽（经典版） | C25: =IFERROR(RANK(A25,$A$12:$A$125,0)+COUNTIFS(A$12:A25,A25)-1,"") | D25: 89101900801 | E25: 越南文标签 | F25: 海天金标生抽（经典版） | G25: HADAY GOLDEN LABEL LIGHT SOY SAUCE (CLASSIC VERSION) 8ML*500 | H25: HADAY NƯỚC TƯƠNG NHÃN VÀNG 8ML*500 | I25: 出口海天牌海天金标生抽(经典版)8ML*500(越南版；越南公司用)(普通袋) | J25: 海天牌海天金标生抽(经典版)8ML*500 | K25: 356000 | N25: =L25+M25 -> 0 | O25: =IF(M25/N25>1/9,"大于8送1",IF(ABS(M25/N25-1/9)<0.0001,"8送1",IF(M25/N25<1/9,IF(M25/N25>1/10,"8送1和9送1之间",IF(ABS(M25/N25-1/10)<0.0001,"9送1",IF(M25/N25<1/10,IF(M25/N25>1/11,"9送1和10送1之间",IF(ABS(M25/N25-1/11)<0.0001,"10送1","小于10送1")))))))) -> #DIV/0! | P25: =K25*L25 -> 0 | Q25: =K25*M25 -> 0 | R25: =N25*K25 -> 0 | S25: 0.08 | T25: =P25*(1+$S25) -> 0 | U25: =Q25*(1+$S25) -> 0 | V25: =R25*(1+$S25) -> 0 | W25: ="海天牌"&F25 -> 海天牌海天金标生抽（经典版） | X25: 8ML*500 | Y25: 5.30 | Z25: 4.90 | AA25: 0.3 | AB25: 0.22 | AC25: 0.175 | AD25: =(L25+M25)*Y25 -> 0 | AE25: =(L25+M25)*Z25 -> 0 | AF25: =ROUND((L25+M25)*AA25*AB25*AC25,2) -> 0 | AG25: 2430.00 | AH25: 5280.00 | AI25: =(L25+M25)/AG25 -> 0 | AJ25: =ROUNDDOWN(AI25/0.95,0) -> 0 | AK25: =(L25+M25)/AH25 -> 0 | AN25: 需要注意的产品最低排产量说明
A26: =IF(N26<>0,1,"") | C26: =IFERROR(RANK(A26,$A$12:$A$125,0)+COUNTIFS(A$12:A26,A26)-1,"") | D26: 89101915007 | E26: 越南文标签 | F26: 海天金标生抽（经典版） | G26: HADAY GOLDEN LABEL LIGHT SOY SAUCE (CLASSIC VERSION) 150ML*24 | H26: HADAY NƯỚC TƯƠNG NHÃN VÀNG 150ML*24 | I26: 出口海天牌海天金标生抽(经典版)150ML*24(越南版；越南公司用)(玻璃瓶) | J26: 海天牌海天金标生抽(经典版)150ML*24 | K26: 197000 | N26: =L26+M26 -> 0 | O26: =IF(M26/N26>1/9,"大于8送1",IF(ABS(M26/N26-1/9)<0.0001,"8送1",IF(M26/N26<1/9,IF(M26/N26>1/10,"8送1和9送1之间",IF(ABS(M26/N26-1/10)<0.0001,"9送1",IF(M26/N26<1/10,IF(M26/N26>1/11,"9送1和10送1之间",IF(ABS(M26/N26-1/11)<0.0001,"10送1","小于10送1")))))))) -> #DIV/0! | P26: =K26*L26 -> 0 | Q26: =K26*M26 -> 0 | R26: =N26*K26 -> 0 | S26: 0.08 | T26: =P26*(1+$S26) -> 0 | U26: =Q26*(1+$S26) -> 0 | V26: =R26*(1+$S26) -> 0 | W26: ="海天牌"&F26 -> 海天牌海天金标生抽（经典版） | X26: 150ML*24 | Y26: 7.80 | Z26: 4.40 | AA26: 0.307 | AB26: 0.206 | AC26: 0.189 | AD26: =(L26+M26)*Y26 -> 0 | AE26: =(L26+M26)*Z26 -> 0 | AF26: =ROUND((L26+M26)*AA26*AB26*AC26,2) -> 0 | AG26: 2370.00 | AH26: 3590.00 | AI26: =(L26+M26)/AG26 -> 0 | AJ26: =ROUNDDOWN(AI26/0.95,0) -> 0 | AK26: =(L26+M26)/AH26 -> 0 | AN26: 最低排产量 | AO26: 因产品为独立品质(需单独排产)或小宗产品(内销排产次数极低)，如单独排产会造成极高的生产成本。 事业部提出针对该类型产品提出最低排产量要求：单次截单日出口汇总的产品需求须满足最低排产量方可启动排产，如单次截单日不满足，则需要等下次截单日或者内销排产凑够最低排产量才安排生产。
A27: =IF(N27<>0,1,"") | C27: =IFERROR(RANK(A27,$A$12:$A$125,0)+COUNTIFS(A$12:A27,A27)-1,"") | D27: 89101915013 | E27: 越南文标签 | F27: 海天金标生抽（经典版） | G27: HADAY GOLDEN LABEL LIGHT SOY SAUCE (CLASSIC VERSION) 155ML*48 | H27: HADAY NƯỚC TƯƠNG NHÃN VÀNG 150ML*24 | I27: 出口海天牌海天金标生抽(经典版)150ML*24(越南版；越南公司用；南宁生产)(玻璃瓶) | J27: 海天牌海天金标生抽(经典版)150ML*24 | K27: 197000 | N27: =L27+M27 -> 0 | O27: =IF(M27/N27>1/9,"大于8送1",IF(ABS(M27/N27-1/9)<0.0001,"8送1",IF(M27/N27<1/9,IF(M27/N27>1/10,"8送1和9送1之间",IF(ABS(M27/N27-1/10)<0.0001,"9送1",IF(M27/N27<1/10,IF(M27/N27>1/11,"9送1和10送1之间",IF(ABS(M27/N27-1/11)<0.0001,"10送1","小于10送1")))))))) -> #DIV/0! | P27: =K27*L27 -> 0 | Q27: =K27*M27 -> 0 | R27: =N27*K27 -> 0 | S27: 0.08 | T27: =P27*(1+$S27) -> 0 | U27: =Q27*(1+$S27) -> 0 | V27: =R27*(1+$S27) -> 0 | W27: ="海天牌"&F27 -> 海天牌海天金标生抽（经典版） | X27: 150ML*24 | Y27: 7.80 | Z27: 4.40 | AA27: 0.307 | AB27: 0.206 | AC27: 0.189 | AD27: =(L27+M27)*Y27 -> 0 | AE27: =(L27+M27)*Z27 -> 0 | AF27: =ROUND((L27+M27)*AA27*AB27*AC27,2) -> 0 | AG27: 2370.00 | AH27: 3590.00 | AI27: =(L27+M27)/AG27 -> 0 | AJ27: =ROUNDDOWN(AI27/0.95,0) -> 0 | AK27: =(L27+M27)/AH27 -> 0
A28: =IF(N28<>0,1,"") | C28: =IFERROR(RANK(A28,$A$12:$A$125,0)+COUNTIFS(A$12:A28,A28)-1,"") | D28: 89101915017 | E28: 越南文标签 | F28: 海天金标生抽（经典版） | G28: HADAY GOLDEN LABEL LIGHT SOY SAUCE (CLASSIC VERSION) 150ML*24 | H28: HADAY NƯỚC TƯƠNG NHÃN VÀNG 155ML*48 | I28: 出口海天牌海天金标生抽(经典版)155ML*48(越南版；越南公司用)(PET瓶) | J28: 海天牌海天金标生抽(经典版)155ML*48 | K28: =392364/1.08 -> 363300 | N28: =L28+M28 -> 0 | O28: =IF(M28/N28>1/9,"大于8送1",IF(ABS(M28/N28-1/9)<0.0001,"8送1",IF(M28/N28<1/9,IF(M28/N28>1/10,"8送1和9送1之间",IF(ABS(M28/N28-1/10)<0.0001,"9送1",IF(M28/N28<1/10,IF(M28/N28>1/11,"9送1和10送1之间",IF(ABS(M28/N28-1/11)<0.0001,"10送1","小于10送1")))))))) -> #DIV/0! | P28: =K28*L28 -> 0 | Q28: =K28*M28 -> 0 | R28: =N28*K28 -> 0 | S28: 0.08 | T28: =P28*(1+$S28) -> 0 | U28: =Q28*(1+$S28) -> 0 | V28: =R28*(1+$S28) -> 0 | W28: ="海天牌"&F28 -> 海天牌海天金标生抽（经典版） | X28: 155ML*48 | Y28: 10.30 | Z28: 8.80 | AA28: 0.385 | AB28: 0.284 | AC28: 0.184 | AD28: =(L28+M28)*Y28 -> 0 | AE28: =(L28+M28)*Z28 -> 0 | AF28: =ROUND((L28+M28)*AA28*AB28*AC28,2) -> 0 | AG28: 1350.00 | AH28: 2720.00 | AI28: =(L28+M28)/AG28 -> 0 | AJ28: =ROUNDDOWN(AI28/0.95,0) -> 0 | AK28: =(L28+M28)/AH28 -> 0
A29: =IF(N29<>0,1,"") | C29: =IFERROR(RANK(A29,$A$12:$A$125,0)+COUNTIFS(A$12:A29,A29)-1,"") | D29: 89101950014 | E29: 越南文标签 | F29: 海天金标生抽（经典版） | G29: HADAY GOLDEN LABEL LIGHT SOY SAUCE (CLASSIC VERSION) 500ML*12 | H29: HADAY NƯỚC TƯƠNG NHÃN VÀNG 500ML*12 | I29: 出口海天牌海天金标生抽(经典版)500ML*12(越南版；越南公司用)(玻璃瓶) | J29: 海天牌海天金标生抽(经典版)500ML*12 | K29: 266600 | N29: =L29+M29 -> 0 | O29: =IF(M29/N29>1/9,"大于8送1",IF(ABS(M29/N29-1/9)<0.0001,"8送1",IF(M29/N29<1/9,IF(M29/N29>1/10,"8送1和9送1之间",IF(ABS(M29/N29-1/10)<0.0001,"9送1",IF(M29/N29<1/10,IF(M29/N29>1/11,"9送1和10送1之间",IF(ABS(M29/N29-1/11)<0.0001,"10送1","小于10送1")))))))) -> #DIV/0! | P29: =K29*L29 -> 0 | Q29: =K29*M29 -> 0 | R29: =N29*K29 -> 0 | S29: 0.08 | T29: =P29*(1+$S29) -> 0 | U29: =Q29*(1+$S29) -> 0 | V29: =R29*(1+$S29) -> 0 | W29: ="海天牌"&F29 -> 海天牌海天金标生抽（经典版） | X29: 500ML*12 | Y29: 10.40 | Z29: 7.30 | AA29: 0.272 | AB29: 0.206 | AC29: 0.258 | AD29: =(L29+M29)*Y29 -> 0 | AE29: =(L29+M29)*Z29 -> 0 | AF29: =ROUND((L29+M29)*AA29*AB29*AC29,2) -> 0 | AG29: 1850.00 | AH29: 2690.00 | AI29: =(L29+M29)/AG29 -> 0 | AJ29: =ROUNDDOWN(AI29/0.95,0) -> 0 | AK29: =(L29+M29)/AH29 -> 0
A30: =IF(N30<>0,1,"") | C30: =IFERROR(RANK(A30,$A$12:$A$125,0)+COUNTIFS(A$12:A30,A30)-1,"") | D30: 89101950025 | E30: 越南文标签 | F30: 海天金标生抽（经典版） | G30: HADAY GOLDEN LABEL LIGHT SOY SAUCE (CLASSIC VERSION) 500ML*12 | H30: HADAY NƯỚC TƯƠNG NHÃN VÀNG 500ML*12 | I30: 出口海天牌海天金标生抽(经典版)500ML*12(越南版；越南公司用；南宁生产)(玻璃瓶) | J30: 海天牌海天金标生抽(经典版)500mL*12 | K30: 266600 | N30: =L30+M30 -> 0 | O30: =IF(M30/N30>1/9,"大于8送1",IF(ABS(M30/N30-1/9)<0.0001,"8送1",IF(M30/N30<1/9,IF(M30/N30>1/10,"8送1和9送1之间",IF(ABS(M30/N30-1/10)<0.0001,"9送1",IF(M30/N30<1/10,IF(M30/N30>1/11,"9送1和10送1之间",IF(ABS(M30/N30-1/11)<0.0001,"10送1","小于10送1")))))))) -> #DIV/0! | P30: =K30*L30 -> 0 | Q30: =K30*M30 -> 0 | R30: =N30*K30 -> 0 | S30: 0.08 | T30: =P30*(1+$S30) -> 0 | U30: =Q30*(1+$S30) -> 0 | V30: =R30*(1+$S30) -> 0 | W30: ="海天牌"&F30 -> 海天牌海天金标生抽（经典版） | X30: 500ML*12 | Y30: 10.40 | Z30: 7.30 | AA30: 0.273 | AB30: 0.202 | AC30: 0.255 | AD30: =(L30+M30)*Y30 -> 0 | AE30: =(L30+M30)*Z30 -> 0 | AF30: =ROUND((L30+M30)*AA30*AB30*AC30,2) -> 0 | AG30: 2000.00 | AH30: 2690.00 | AI30: =(L30+M30)/AG30 -> 0 | AJ30: =ROUNDDOWN(AI30/0.95,0) -> 0 | AK30: =(L30+M30)/AH30 -> 0 | AN30: 品种 | AO30: 品类 | AP30: 最低排产量 | AQ30: 说明 | AR30: 规格说明 | AS30: 备注
A31: =IF(N31<>0,1,"") | C31: =IFERROR(RANK(A31,$A$12:$A$125,0)+COUNTIFS(A$12:A31,A31)-1,"") | D31: 89101950011 | E31: 中文标签 | F31: 海天金标生抽（经典版） | G31: HADAY GOLDEN LABEL LIGHT SOY SAUCE (CLASSIC VERSION) 500ML*12 | H31: HADAY NƯỚC TƯƠNG NHÃN VÀNG 500ML*12 | I31: 出口海天牌海天金标生抽(经典版)500ML*12(越南公司用)(玻璃瓶) | J31: 海天牌海天金标生抽(经典版)500ML*12 | K31: 266600 | N31: =L31+M31 -> 0 | O31: =IF(M31/N31>1/9,"大于8送1",IF(ABS(M31/N31-1/9)<0.0001,"8送1",IF(M31/N31<1/9,IF(M31/N31>1/10,"8送1和9送1之间",IF(ABS(M31/N31-1/10)<0.0001,"9送1",IF(M31/N31<1/10,IF(M31/N31>1/11,"9送1和10送1之间",IF(ABS(M31/N31-1/11)<0.0001,"10送1","小于10送1")))))))) -> #DIV/0! | P31: =K31*L31 -> 0 | Q31: =K31*M31 -> 0 | R31: =N31*K31 -> 0 | S31: 0.08 | T31: =P31*(1+$S31) -> 0 | U31: =Q31*(1+$S31) -> 0 | V31: =R31*(1+$S31) -> 0 | W31: ="海天牌"&F31 -> 海天牌海天金标生抽（经典版） | X31: 500ML*12 | Y31: 10.40 | Z31: 7.30 | AA31: 0.272 | AB31: 0.206 | AC31: 0.258 | AD31: =(L31+M31)*Y31 -> 0 | AE31: =(L31+M31)*Z31 -> 0 | AF31: =ROUND((L31+M31)*AA31*AB31*AC31,2) -> 0 | AG31: 1850.00 | AH31: 2690.00 | AI31: =(L31+M31)/AG31 -> 0 | AJ31: =ROUNDDOWN(AI31/0.95,0) -> 0 | AK31: =(L31+M31)/AH31 -> 0 | AN31: 酱油 | AO31: 海鲜酱油（经典版） | AP31: 950箱 | AQ31: 独立品质产品 需单独排产 | AR31: 规格不受限制，同单品不同规格的订单量可拼凑 | AS31: 单次截单日订单累计满足最低排产量才会启动排产，否则计划不予排产，等下次截单日凑够订单量再排产
A32: =IF(N32<>0,1,"") | C32: =IFERROR(RANK(A32,$A$12:$A$125,0)+COUNTIFS(A$12:A32,A32)-1,"") | D32: 89101950023 | E32: 中文标签 | F32: 海天金标生抽（经典版） | G32: HADAY GOLDEN LABEL LIGHT SOY SAUCE (CLASSIC VERSION) 500ML*12 | H32: HADAY NƯỚC TƯƠNG NHÃN VÀNG 500ML*12 | I32: 出口海天牌海天金标生抽(经典版)500ML*12(越南公司用；南宁生产)(玻璃瓶) | J32: 海天牌海天金标生抽(经典版)500mL*12 | K32: 266600 | N32: =L32+M32 -> 0 | O32: =IF(M32/N32>1/9,"大于8送1",IF(ABS(M32/N32-1/9)<0.0001,"8送1",IF(M32/N32<1/9,IF(M32/N32>1/10,"8送1和9送1之间",IF(ABS(M32/N32-1/10)<0.0001,"9送1",IF(M32/N32<1/10,IF(M32/N32>1/11,"9送1和10送1之间",IF(ABS(M32/N32-1/11)<0.0001,"10送1","小于10送1")))))))) -> #DIV/0! | P32: =K32*L32 -> 0 | Q32: =K32*M32 -> 0 | R32: =N32*K32 -> 0 | S32: 0.08 | T32: =P32*(1+$S32) -> 0 | U32: =Q32*(1+$S32) -> 0 | V32: =R32*(1+$S32) -> 0 | W32: ="海天牌"&F32 -> 海天牌海天金标生抽（经典版） | X32: 500ML*12 | Y32: 10.40 | Z32: 7.30 | AA32: 0.273 | AB32: 0.202 | AC32: 0.255 | AD32: =(L32+M32)*Y32 -> 0 | AE32: =(L32+M32)*Z32 -> 0 | AF32: =ROUND((L32+M32)*AA32*AB32*AC32,2) -> 0 | AG32: 2000.00 | AH32: 2690.00 | AI32: =(L32+M32)/AG32 -> 0 | AJ32: =ROUNDDOWN(AI32/0.95,0) -> 0 | AK32: =(L32+M32)/AH32 -> 0 | AO32: 金标生抽（经典版） | AP32: 1200箱
A33: =IF(N33<>0,1,"") | C33: =IFERROR(RANK(A33,$A$12:$A$125,0)+COUNTIFS(A$12:A33,A33)-1,"") | D33: 89101950012 | E33: 越南文标签 | F33: 海天金标生抽（经典版） | G33: HADAY GOLDEN LABEL LIGHT SOY SAUCE (CLASSIC VERSION) 500ML*12 | H33: HADAY NƯỚC TƯƠNG NHÃN VÀNG 500ML*12 | I33: 出口海天牌海天金标生抽(经典版)500ML*12(越南版；越南公司用)(PET瓶) | J33: 海天牌海天金标生抽(经典版)(PET瓶)500ML*12 | K33: 266600 | N33: =L33+M33 -> 0 | O33: =IF(M33/N33>1/9,"大于8送1",IF(ABS(M33/N33-1/9)<0.0001,"8送1",IF(M33/N33<1/9,IF(M33/N33>1/10,"8送1和9送1之间",IF(ABS(M33/N33-1/10)<0.0001,"9送1",IF(M33/N33<1/10,IF(M33/N33>1/11,"9送1和10送1之间",IF(ABS(M33/N33-1/11)<0.0001,"10送1","小于10送1")))))))) -> #DIV/0! | P33: =K33*L33 -> 0 | Q33: =K33*M33 -> 0 | R33: =N33*K33 -> 0 | S33: 0.08 | T33: =P33*(1+$S33) -> 0 | U33: =Q33*(1+$S33) -> 0 | V33: =R33*(1+$S33) -> 0 | W33: ="海天牌"&F33 -> 海天牌海天金标生抽（经典版） | X33: 500ML*12 | Y33: 8.20 | Z33: 7.30 | AA33: 0.266 | AB33: 0.197 | AC33: 0.25 | AD33: =(L33+M33)*Y33 -> 0 | AE33: =(L33+M33)*Z33 -> 0 | AF33: =ROUND((L33+M33)*AA33*AB33*AC33,2) -> 0 | AG33: 2050.00 | AH33: 3410.00 | AI33: =(L33+M33)/AG33 -> 0 | AJ33: =ROUNDDOWN(AI33/0.95,0) -> 0 | AK33: =(L33+M33)/AH33 -> 0 | AL33: 单支包装为PET材质 | AO33: 金标生抽（精选版） | AP33: 800箱
A34: =IF(N34<>0,1,"") | C34: =IFERROR(RANK(A34,$A$12:$A$125,0)+COUNTIFS(A$12:A34,A34)-1,"") | D34: 89101910908 | E34: 越南文标签 | F34: 海天金标生抽（经典版） | G34: HADAY GOLDEN LABEL LIGHT SOY SAUCE (CLASSIC VERSION) 1.9L*6 | H34: HADAY NƯỚC TƯƠNG NHÃN VÀNG 1.9L*6 | I34: 出口海天牌海天金标生抽(经典版)1.9L*6(越南版；越南公司用)(PET瓶) | J34: 海天牌海天金标生抽(经典版)1.9L*6 | K34: 389200 | N34: =L34+M34 -> 0 | O34: =IF(M34/N34>1/9,"大于8送1",IF(ABS(M34/N34-1/9)<0.0001,"8送1",IF(M34/N34<1/9,IF(M34/N34>1/10,"8送1和9送1之间",IF(ABS(M34/N34-1/10)<0.0001,"9送1",IF(M34/N34<1/10,IF(M34/N34>1/11,"9送1和10送1之间",IF(ABS(M34/N34-1/11)<0.0001,"10送1","小于10送1")))))))) -> #DIV/0! | P34: =K34*L34 -> 0 | Q34: =K34*M34 -> 0 | R34: =N34*K34 -> 0 | S34: 0.08 | T34: =P34*(1+$S34) -> 0 | U34: =Q34*(1+$S34) -> 0 | V34: =R34*(1+$S34) -> 0 | W34: ="海天牌"&F34 -> 海天牌海天金标生抽（经典版） | X34: 1.9L*6 | Y34: 14.80 | Z34: 13.90 | AA34: 0.351 | AB34: 0.238 | AC34: 0.303 | AD34: =(L34+M34)*Y34 -> 0 | AE34: =(L34+M34)*Z34 -> 0 | AF34: =ROUND((L34+M34)*AA34*AB34*AC34,2) -> 0 | AG34: 1100.00 | AH34: 1890.00 | AI34: =(L34+M34)/AG34 -> 0 | AJ34: =ROUNDDOWN(AI34/0.95,0) -> 0 | AK34: =(L34+M34)/AH34 -> 0 | AO34: 招牌金标生抽 | AP34: 1200箱
A35: =IF(N35<>0,1,"") | C35: =IFERROR(RANK(A35,$A$12:$A$125,0)+COUNTIFS(A$12:A35,A35)-1,"") | D35: 89101910917 | E35: 越南文标签 | F35: 海天金标生抽（经典版） | G35: HADAY GOLDEN LABEL LIGHT SOY SAUCE (CLASSIC VERSION) 1.9L*6 | H35: HADAY NƯỚC TƯƠNG NHÃN VÀNG 1.9L*6 | I35: 出口海天牌海天金标生抽(经典版)1.9L*6(越南版；越南公司用；南宁生产)(PET瓶) | J35: 海天牌海天金标生抽(经典版)1.9L*6 | K35: 389200 | N35: =L35+M35 -> 0 | O35: =IF(M35/N35>1/9,"大于8送1",IF(ABS(M35/N35-1/9)<0.0001,"8送1",IF(M35/N35<1/9,IF(M35/N35>1/10,"8送1和9送1之间",IF(ABS(M35/N35-1/10)<0.0001,"9送1",IF(M35/N35<1/10,IF(M35/N35>1/11,"9送1和10送1之间",IF(ABS(M35/N35-1/11)<0.0001,"10送1","小于10送1")))))))) -> #DIV/0! | P35: =K35*L35 -> 0 | Q35: =K35*M35 -> 0 | R35: =N35*K35 -> 0 | S35: 0.08 | T35: =P35*(1+$S35) -> 0 | U35: =Q35*(1+$S35) -> 0 | V35: =R35*(1+$S35) -> 0 | W35: ="海天牌"&F35 -> 海天牌海天金标生抽（经典版） | X35: 1.9L*6 | Y35: 14.70 | Z35: 13.90 | AA35: 0.351 | AB35: 0.234 | AC35: 0.299 | AD35: =(L35+M35)*Y35 -> 0 | AE35: =(L35+M35)*Z35 -> 0 | AF35: =ROUND((L35+M35)*AA35*AB35*AC35,2) -> 0 | AG35: 1120.00 | AH35: 1900.00 | AI35: =(L35+M35)/AG35 -> 0 | AJ35: =ROUNDDOWN(AI35/0.95,0) -> 0 | AK35: =(L35+M35)/AH35 -> 0 | AO35: 金标生抽王 | AP35: 1200箱
A36: =IF(N36<>0,1,"") | C36: =IFERROR(RANK(A36,$A$12:$A$125,0)+COUNTIFS(A$12:A36,A36)-1,"") | D36: 89101910907 | E36: 中文标签 | F36: 海天金标生抽（经典版） | G36: HADAY GOLDEN LABEL LIGHT SOY SAUCE (CLASSIC VERSION) 1.9L*6 | H36: HADAY NƯỚC TƯƠNG NHÃN VÀNG 1.9L*6 | I36: 出口海天牌海天金标生抽(经典版)1.9L*6(越南公司用)(PET瓶) | J36: 海天牌海天金标生抽(经典版)1.9L*6 | K36: 389200 | N36: =L36+M36 -> 0 | O36: =IF(M36/N36>1/9,"大于8送1",IF(ABS(M36/N36-1/9)<0.0001,"8送1",IF(M36/N36<1/9,IF(M36/N36>1/10,"8送1和9送1之间",IF(ABS(M36/N36-1/10)<0.0001,"9送1",IF(M36/N36<1/10,IF(M36/N36>1/11,"9送1和10送1之间",IF(ABS(M36/N36-1/11)<0.0001,"10送1","小于10送1")))))))) -> #DIV/0! | P36: =K36*L36 -> 0 | Q36: =K36*M36 -> 0 | R36: =N36*K36 -> 0 | S36: 0.08 | T36: =P36*(1+$S36) -> 0 | U36: =Q36*(1+$S36) -> 0 | V36: =R36*(1+$S36) -> 0 | W36: ="海天牌"&F36 -> 海天牌海天金标生抽（经典版） | X36: 1.9L*6 | Y36: 14.80 | Z36: 13.90 | AA36: 0.351 | AB36: 0.238 | AC36: 0.303 | AD36: =(L36+M36)*Y36 -> 0 | AE36: =(L36+M36)*Z36 -> 0 | AF36: =ROUND((L36+M36)*AA36*AB36*AC36,2) -> 0 | AG36: 1100.00 | AH36: 1890.00 | AI36: =(L36+M36)/AG36 -> 0 | AJ36: =ROUNDDOWN(AI36/0.95,0) -> 0 | AK36: =(L36+M36)/AH36 -> 0 | AO36: 生抽王 | AP36: 1200箱
A37: =IF(N37<>0,1,"") | C37: =IFERROR(RANK(A37,$A$12:$A$125,0)+COUNTIFS(A$12:A37,A37)-1,"") | D37: 89101910915 | E37: 中文标签 | F37: 海天金标生抽（经典版） | G37: HADAY GOLDEN LABEL LIGHT SOY SAUCE (CLASSIC VERSION) 1.9L*6 | H37: HADAY NƯỚC TƯƠNG NHÃN VÀNG 1.9L*6 | I37: 出口海天牌海天金标生抽(经典版)1.9L*6(越南公司用；南宁生产)(PET瓶) | J37: 海天牌海天金标生抽(经典版)1.9L*6 | K37: 389200 | N37: =L37+M37 -> 0 | O37: =IF(M37/N37>1/9,"大于8送1",IF(ABS(M37/N37-1/9)<0.0001,"8送1",IF(M37/N37<1/9,IF(M37/N37>1/10,"8送1和9送1之间",IF(ABS(M37/N37-1/10)<0.0001,"9送1",IF(M37/N37<1/10,IF(M37/N37>1/11,"9送1和10送1之间",IF(ABS(M37/N37-1/11)<0.0001,"10送1","小于10送1")))))))) -> #DIV/0! | P37: =K37*L37 -> 0 | Q37: =K37*M37 -> 0 | R37: =N37*K37 -> 0 | S37: 0.08 | T37: =P37*(1+$S37) -> 0 | U37: =Q37*(1+$S37) -> 0 | V37: =R37*(1+$S37) -> 0 | W37: ="海天牌"&F37 -> 海天牌海天金标生抽（经典版） | X37: 1.9L*6 | Y37: 14.70 | Z37: 13.90 | AA37: 0.351 | AB37: 0.234 | AC37: 0.299 | AD37: =(L37+M37)*Y37 -> 0 | AE37: =(L37+M37)*Z37 -> 0 | AF37: =ROUND((L37+M37)*AA37*AB37*AC37,2) -> 0 | AG37: 1120.00 | AH37: 1900.00 | AI37: =(L37+M37)/AG37 -> 0 | AJ37: =ROUNDDOWN(AI37/0.95,0) -> 0 | AK37: =(L37+M37)/AH37 -> 0 | AO37: 老抽王 | AP37: 800箱
A38: =IF(N38<>0,1,"") | C38: =IFERROR(RANK(A38,$A$12:$A$125,0)+COUNTIFS(A$12:A38,A38)-1,"") | D38: 89101940903 | E38: 中文标签 | F38: 海天金标生抽（经典版） | G38: HADAY GOLDEN LABEL LIGHT SOY SAUCE (CLASSIC VERSION) 4.9L*2 | H38: HADAY NƯỚC TƯƠNG NHÃN VÀNG 4.9L*2 | I38: 出口海天牌海天金标生抽(经典版)4.9L*2(越南公司用)(PET瓶) | J38: 海天牌海天金标生抽(经典版)4.9L*2 | K38: 244000 | N38: =L38+M38 -> 0 | O38: =IF(M38/N38>1/9,"大于8送1",IF(ABS(M38/N38-1/9)<0.0001,"8送1",IF(M38/N38<1/9,IF(M38/N38>1/10,"8送1和9送1之间",IF(ABS(M38/N38-1/10)<0.0001,"9送1",IF(M38/N38<1/10,IF(M38/N38>1/11,"9送1和10送1之间",IF(ABS(M38/N38-1/11)<0.0001,"10送1","小于10送1")))))))) -> #DIV/0! | P38: =K38*L38 -> 0 | Q38: =K38*M38 -> 0 | R38: =N38*K38 -> 0 | S38: 0.08 | T38: =P38*(1+$S38) -> 0 | U38: =Q38*(1+$S38) -> 0 | V38: =R38*(1+$S38) -> 0 | W38: ="海天牌"&F38 -> 海天牌海天金标生抽（经典版） | X38: 4.9L*2 | Y38: 12.6 | Z38: 11.9 | AA38: 0.31 | AB38: 0.155 | AC38: 0.347 | AD38: =(L38+M38)*Y38 -> 0 | AE38: =(L38+M38)*Z38 -> 0 | AF38: =ROUND((L38+M38)*AA38*AB38*AC38,2) -> 0 | AG38: 1580.00 | AH38: 2220.00 | AI38: =(L38+M38)/AG38 -> 0 | AJ38: =ROUNDDOWN(AI38/0.95,0) -> 0 | AK38: =(L38+M38)/AH38 -> 0
A39: =IF(N39<>0,1,"") | B39: 海天招牌草菇老抽 | C39: =IFERROR(RANK(A39,$A$12:$A$125,0)+COUNTIFS(A$12:A39,A39)-1,"") | D39: 89140550006 | E39: 中文标签 | F39: 海天招牌草菇老抽 | G39: HADAY SIGNATURE MUSHROOM DARK SOY SAUCE 500ML*12 | H39: HADAY HẮC XÌ DẦU HƯƠNG NẤM THƯỢNG HẠNG 500ML*12 | I39: 出口海天牌海天招牌草菇老抽500ML*12(越南公司用)(玻璃瓶) | J39: 海天牌海天招牌草菇老抽500ML*12 | K39: 287900 | N39: =L39+M39 -> 0 | O39: =IF(M39/N39>1/9,"大于8送1",IF(ABS(M39/N39-1/9)<0.0001,"8送1",IF(M39/N39<1/9,IF(M39/N39>1/10,"8送1和9送1之间",IF(ABS(M39/N39-1/10)<0.0001,"9送1",IF(M39/N39<1/10,IF(M39/N39>1/11,"9送1和10送1之间",IF(ABS(M39/N39-1/11)<0.0001,"10送1","小于10送1")))))))) -> #DIV/0! | P39: =K39*L39 -> 0 | Q39: =K39*M39 -> 0 | R39: =N39*K39 -> 0 | S39: 0.08 | T39: =P39*(1+$S39) -> 0 | U39: =Q39*(1+$S39) -> 0 | V39: =R39*(1+$S39) -> 0 | W39: ="海天牌"&F39 -> 海天牌海天招牌草菇老抽 | X39: 500ML*12 | Y39: 10.80 | Z39: 7.80 | AA39: 0.292 | AB39: 0.215 | AC39: 0.247 | AD39: =(L39+M39)*Y39 -> 0 | AE39: =(L39+M39)*Z39 -> 0 | AF39: =ROUND((L39+M39)*AA39*AB39*AC39,2) -> 0 | AG39: 1780.00 | AH39: 2590.00 | AI39: =(L39+M39)/AG39 -> 0 | AJ39: =ROUNDDOWN(AI39/0.95,0) -> 0 | AK39: =(L39+M39)/AH39 -> 0 | AO39: 草菇老抽 | AP39: 800箱
A40: =IF(N40<>0,1,"") | C40: =IFERROR(RANK(A40,$A$12:$A$125,0)+COUNTIFS(A$12:A40,A40)-1,"") | D40: 89140517504 | E40: 中文标签 | F40: 海天招牌草菇老抽 | G40: HADAY SIGNATURE MUSHROOM DARK SOY SAUCE 1.75L*6 | H40: HADAY HẮC XÌ DẦU HƯƠNG NẤM THƯỢNG HẠNG 1.75L*6 | I40: 出口海天牌海天招牌草菇老抽1.75L*6(越南公司用)(PET瓶) | J40: 海天牌海天招牌草菇老抽1.75L*6 | K40: 410600 | N40: =L40+M40 -> 0 | O40: =IF(M40/N40>1/9,"大于8送1",IF(ABS(M40/N40-1/9)<0.0001,"8送1",IF(M40/N40<1/9,IF(M40/N40>1/10,"8送1和9送1之间",IF(ABS(M40/N40-1/10)<0.0001,"9送1",IF(M40/N40<1/10,IF(M40/N40>1/11,"9送1和10送1之间",IF(ABS(M40/N40-1/11)<0.0001,"10送1","小于10送1")))))))) -> #DIV/0! | P40: =K40*L40 -> 0 | Q40: =K40*M40 -> 0 | R40: =N40*K40 -> 0 | S40: 0.08 | T40: =P40*(1+$S40) -> 0 | U40: =Q40*(1+$S40) -> 0 | V40: =R40*(1+$S40) -> 0 | W40: ="海天牌"&F40 -> 海天牌海天招牌草菇老抽 | X40: 1.75L*6 | Y40: 14.50 | Z40: 13.70 | AA40: 0.338 | AB40: 0.226 | AC40: 0.3 | AD40: =(L40+M40)*Y40 -> 0 | AE40: =(L40+M40)*Z40 -> 0 | AF40: =ROUND((L40+M40)*AA40*AB40*AC40,2) -> 0 | AG40: 1200.00 | AH40: 1930.00 | AI40: =(L40+M40)/AG40 -> 0 | AJ40: =ROUNDDOWN(AI40/0.95,0) -> 0 | AK40: =(L40+M40)/AH40 -> 0 | AO40: 珍选生抽5gal | AP40: 550桶
A41: =IF(N41<>0,1,"") | B41: 一品鲜 | C41: =IFERROR(RANK(A41,$A$12:$A$125,0)+COUNTIFS(A$12:A41,A41)-1,"") | D41: 89702017501 | E41: 中文标签 | F41: 海天一品鲜(复合调味料) | G41: HADAY SEASONED DIPPING SAUCE 1.75L*6 | H41: NƯỚC CHẤM HADAY THƯỢNG HẠNG 1.75L*6 | I41: 出口海天牌海天一品鲜(复合调味料)1.75L*6(越南公司用)(PET瓶) | J41: 海天牌海天一品鲜(复合调味料)1.75L*6 | K41: 350000 | N41: =L41+M41 -> 0 | O41: =IF(M41/N41>1/9,"大于8送1",IF(ABS(M41/N41-1/9)<0.0001,"8送1",IF(M41/N41<1/9,IF(M41/N41>1/10,"8送1和9送1之间",IF(ABS(M41/N41-1/10)<0.0001,"9送1",IF(M41/N41<1/10,IF(M41/N41>1/11,"9送1和10送1之间",IF(ABS(M41/N41-1/11)<0.0001,"10送1","小于10送1")))))))) -> #DIV/0! | P41: =K41*L41 -> 0 | Q41: =K41*M41 -> 0 | R41: =N41*K41 -> 0 | S41: 0.08 | T41: =P41*(1+$S41) -> 0 | U41: =Q41*(1+$S41) -> 0 | V41: =R41*(1+$S41) -> 0 | W41: ="海天牌"&F41 -> 海天牌海天一品鲜(复合调味料) | X41: 1.75L*6 | Y41: 13.70 | Z41: 12.90 | AA41: 0.338 | AB41: 0.226 | AC41: 0.3 | AD41: =(L41+M41)*Y41 -> 0 | AE41: =(L41+M41)*Z41 -> 0 | AF41: =ROUND((L41+M41)*AA41*AB41*AC41,2) -> 0 | AG41: 1200.00 | AH41: 2040.00 | AI41: =(L41+M41)/AG41 -> 0 | AJ41: =ROUNDDOWN(AI41/0.95,0) -> 0 | AK41: =(L41+M41)/AH41 -> 0
A42: =IF(N42<>0,1,"") | C42: =IFERROR(RANK(A42,$A$12:$A$125,0)+COUNTIFS(A$12:A42,A42)-1,"") | D42: 89702050001 | E42: 中文标签 | F42: 海天一品鲜(复合调味料) | G42: HADAY SEASONED DIPPING SAUCE 500ML*12 | H42: NƯỚC CHẤM HADAY THƯỢNG HẠNG 500ML*12 | I42: 出口海天牌海天一品鲜(复合调味料)500ML*12(越南公司用)(PET瓶) | J42: 海天牌海天一品鲜(复合调味料)(PET瓶)500ML*12 | K42: 216000 | N42: =L42+M42 -> 0 | O42: =IF(M42/N42>1/9,"大于8送1",IF(ABS(M42/N42-1/9)<0.0001,"8送1",IF(M42/N42<1/9,IF(M42/N42>1/10,"8送1和9送1之间",IF(ABS(M42/N42-1/10)<0.0001,"9送1",IF(M42/N42<1/10,IF(M42/N42>1/11,"9送1和10送1之间",IF(ABS(M42/N42-1/11)<0.0001,"10送1","小于10送1")))))))) -> #DIV/0! | P42: =K42*L42 -> 0 | Q42: =K42*M42 -> 0 | R42: =N42*K42 -> 0 | S42: 0.08 | T42: =P42*(1+$S42) -> 0 | U42: =Q42*(1+$S42) -> 0 | V42: =R42*(1+$S42) -> 0 | W42: ="海天牌"&F42 -> 海天牌海天一品鲜(复合调味料) | X42: 500ML*12 | Y42: 8.20 | Z42: 7.40 | AA42: 0.273 | AB42: 0.204 | AC42: 0.245 | AD42: =(L42+M42)*Y42 -> 0 | AE42: =(L42+M42)*Z42 -> 0 | AF42: =ROUND((L42+M42)*AA42*AB42*AC42,2) -> 0 | AG42: 2050.00 | AH42: 3410.00 | AI42: =(L42+M42)/AG42 -> 0 | AJ42: =ROUNDDOWN(AI42/0.95,0) -> 0 | AK42: =(L42+M42)/AH42 -> 0
A43: =IF(N43<>0,1,"") | B43: 生抽酱油 | C43: =IFERROR(RANK(A43,$A$12:$A$125,0)+COUNTIFS(A$12:A43,A43)-1,"") | D43: 89103510923 | E43: 越南文标签 | F43: 生抽酱油(经典版) | G43: LIGHT SOY SAUCE (CLASSIC VERSION) 1.9L*6 | H43: NƯỚC TƯƠNG THANH DỊU (VỊ TRUYỀN THỐNG) 1.9L*6 | I43: 出口海天牌生抽酱油(经典版)1.9L*6(越南版；越南公司用)(PET瓶) | J43: 海天牌生抽酱油(经典版)1.9L*6(PET瓶) | K43: 217900 | N43: =L43+M43 -> 0 | O43: =IF(M43/N43>1/9,"大于8送1",IF(ABS(M43/N43-1/9)<0.0001,"8送1",IF(M43/N43<1/9,IF(M43/N43>1/10,"8送1和9送1之间",IF(ABS(M43/N43-1/10)<0.0001,"9送1",IF(M43/N43<1/10,IF(M43/N43>1/11,"9送1和10送1之间",IF(ABS(M43/N43-1/11)<0.0001,"10送1","小于10送1")))))))) -> #DIV/0! | P43: =K43*L43 -> 0 | Q43: =K43*M43 -> 0 | R43: =N43*K43 -> 0 | S43: 0.08 | T43: =P43*(1+$S43) -> 0 | U43: =Q43*(1+$S43) -> 0 | V43: =R43*(1+$S43) -> 0 | W43: ="海天牌"&F43 -> 海天牌生抽酱油(经典版) | X43: 1.9L*6 | Y43: 14.1 | Z43: 13.2 | AA43: 0.351 | AB43: 0.238 | AC43: 0.303 | AD43: =(L43+M43)*Y43 -> 0 | AE43: =(L43+M43)*Z43 -> 0 | AF43: =ROUND((L43+M43)*AA43*AB43*AC43,2) -> 0 | AG43: 1100.00 | AH43: 1990.00 | AI43: =(L43+M43)/AG43 -> 0 | AJ43: =ROUNDDOWN(AI43/0.95,0) -> 0 | AK43: =(L43+M43)/AH43 -> 0
A44: =IF(N44<>0,1,"") | C44: =IFERROR(RANK(A44,$A$12:$A$125,0)+COUNTIFS(A$12:A44,A44)-1,"") | D44: 89103550023 | E44: 越南文标签 | F44: 生抽酱油(经典版) | G44: LIGHT SOY SAUCE (CLASSIC VERSION) 500ML*12 | H44: NƯỚC TƯƠNG THANH DỊU (VỊ TRUYỀN THỐNG) 500ML*12 | I44: 出口海天牌生抽酱油(经典版)500ML*12(越南版；越南公司用)(玻璃瓶) | J44: 海天牌生抽酱油(经典版)500mL*12(玻璃瓶) | K44: 128500 | N44: =L44+M44 -> 0 | O44: =IF(M44/N44>1/9,"大于8送1",IF(ABS(M44/N44-1/9)<0.0001,"8送1",IF(M44/N44<1/9,IF(M44/N44>1/10,"8送1和9送1之间",IF(ABS(M44/N44-1/10)<0.0001,"9送1",IF(M44/N44<1/10,IF(M44/N44>1/11,"9送1和10送1之间",IF(ABS(M44/N44-1/11)<0.0001,"10送1","小于10送1")))))))) -> #DIV/0! | P44: =K44*L44 -> 0 | Q44: =K44*M44 -> 0 | R44: =N44*K44 -> 0 | S44: 0.08 | T44: =P44*(1+$S44) -> 0 | U44: =Q44*(1+$S44) -> 0 | V44: =R44*(1+$S44) -> 0 | W44: ="海天牌"&F44 -> 海天牌生抽酱油(经典版) | X44: 500ML*12 | Y44: 10 | Z44: 7 | AA44: 0.288 | AB44: 0.212 | AC44: 0.245 | AD44: =(L44+M44)*Y44 -> 0 | AE44: =(L44+M44)*Z44 -> 0 | AF44: =ROUND((L44+M44)*AA44*AB44*AC44,2) -> 0 | AG44: 1850.00 | AH44: 2800.00 | AI44: =(L44+M44)/AG44 -> 0 | AJ44: =ROUNDDOWN(AI44/0.95,0) -> 0 | AK44: =(L44+M44)/AH44 -> 0
A45: =IF(N45<>0,1,"") | B45: 老抽酱油 | C45: =IFERROR(RANK(A45,$A$12:$A$125,0)+COUNTIFS(A$12:A45,A45)-1,"") | D45: 89103610917 | E45: 越南文标签 | F45: 老抽酱油(经典版) | G45: DARK SOY SAUCE (CLASSIC VERSION) 1.9L*6 | H45: HẮC XÌ DẦU (VỊ TRUYỀN THỐNG) 1.9L*6 | I45: 出口海天牌老抽酱油(经典版)1.9L*6(越南版；越南公司用)(PET瓶) | J45: 海天牌老抽酱油(经典版)1.9L*6(PET瓶) | K45: 229100 | N45: =L45+M45 -> 0 | O45: =IF(M45/N45>1/9,"大于8送1",IF(ABS(M45/N45-1/9)<0.0001,"8送1",IF(M45/N45<1/9,IF(M45/N45>1/10,"8送1和9送1之间",IF(ABS(M45/N45-1/10)<0.0001,"9送1",IF(M45/N45<1/10,IF(M45/N45>1/11,"9送1和10送1之间",IF(ABS(M45/N45-1/11)<0.0001,"10送1","小于10送1")))))))) -> #DIV/0! | P45: =K45*L45 -> 0 | Q45: =K45*M45 -> 0 | R45: =N45*K45 -> 0 | S45: 0.08 | T45: =P45*(1+$S45) -> 0 | U45: =Q45*(1+$S45) -> 0 | V45: =R45*(1+$S45) -> 0 | W45: ="海天牌"&F45 -> 海天牌老抽酱油(经典版) | X45: 1.9L*6 | Y45: 14.8 | Z45: 13.91 | AA45: 0.351 | AB45: 0.238 | AC45: 0.303 | AD45: =(L45+M45)*Y45 -> 0 | AE45: =(L45+M45)*Z45 -> 0 | AF45: =ROUND((L45+M45)*AA45*AB45*AC45,2) -> 0 | AG45: 1100.00 | AH45: 1890.00 | AI45: =(L45+M45)/AG45 -> 0 | AJ45: =ROUNDDOWN(AI45/0.95,0) -> 0 | AK45: =(L45+M45)/AH45 -> 0
A46: =IF(N46<>0,1,"") | C46: =IFERROR(RANK(A46,$A$12:$A$125,0)+COUNTIFS(A$12:A46,A46)-1,"") | D46: 89103650019 | E46: 越南文标签 | F46: 老抽酱油(经典版) | G46: DARK SOY SAUCE (CLASSIC VERSION) 500ML*12 | H46: HẮC XÌ DẦU (VỊ TRUYỀN THỐNG) 500ML*12 | I46: 出口海天牌老抽酱油(经典版)500ML*12(越南版；越南公司用)(玻璃瓶) | J46: 海天牌老抽酱油(经典版)500mL*12(玻璃瓶) | K46: 142500 | N46: =L46+M46 -> 0 | O46: =IF(M46/N46>1/9,"大于8送1",IF(ABS(M46/N46-1/9)<0.0001,"8送1",IF(M46/N46<1/9,IF(M46/N46>1/10,"8送1和9送1之间",IF(ABS(M46/N46-1/10)<0.0001,"9送1",IF(M46/N46<1/10,IF(M46/N46>1/11,"9送1和10送1之间",IF(ABS(M46/N46-1/11)<0.0001,"10送1","小于10送1")))))))) -> #DIV/0! | P46: =K46*L46 -> 0 | Q46: =K46*M46 -> 0 | R46: =N46*K46 -> 0 | S46: 0.08 | T46: =P46*(1+$S46) -> 0 | U46: =Q46*(1+$S46) -> 0 | V46: =R46*(1+$S46) -> 0 | W46: ="海天牌"&F46 -> 海天牌老抽酱油(经典版) | X46: 500ML*12 | Y46: 10.3 | Z46: 7.31 | AA46: 0.288 | AB46: 0.212 | AC46: 0.245 | AD46: =(L46+M46)*Y46 -> 0 | AE46: =(L46+M46)*Z46 -> 0 | AF46: =ROUND((L46+M46)*AA46*AB46*AC46,2) -> 0 | AG46: 1850.00 | AH46: 2720.00 | AI46: =(L46+M46)/AG46 -> 0 | AJ46: =ROUNDDOWN(AI46/0.95,0) -> 0 | AK46: =(L46+M46)/AH46 -> 0
A47: =IF(N47<>0,1,"") | B47: 蒸鱼豉油 | C47: =IFERROR(RANK(A47,$A$12:$A$125,0)+COUNTIFS(A$12:A47,A47)-1,"") | D47: 89100345006 | E47: 中文标签 | F47: 蒸鱼豉油 | G47: SEASONED SOY SAUCE FOR SEAFOOD 450ML*12 | H47: HADAY NƯỚC TƯƠNG HẤP CÁ 450ML*12 | I47: 出口海天牌蒸鱼豉油450ML*12(越南公司用)(玻璃瓶) | J47: 海天牌蒸鱼豉油450ML*12 | K47: 325300 | N47: =L47+M47 -> 0 | O47: =IF(M47/N47>1/9,"大于8送1",IF(ABS(M47/N47-1/9)<0.0001,"8送1",IF(M47/N47<1/9,IF(M47/N47>1/10,"8送1和9送1之间",IF(ABS(M47/N47-1/10)<0.0001,"9送1",IF(M47/N47<1/10,IF(M47/N47>1/11,"9送1和10送1之间",IF(ABS(M47/N47-1/11)<0.0001,"10送1","小于10送1")))))))) -> #DIV/0! | P47: =K47*L47 -> 0 | Q47: =K47*M47 -> 0 | R47: =N47*K47 -> 0 | S47: 0.08 | T47: =P47*(1+$S47) -> 0 | U47: =Q47*(1+$S47) -> 0 | V47: =R47*(1+$S47) -> 0 | W47: ="海天牌"&F47 -> 海天牌蒸鱼豉油 | X47: 450ML*12 | Y47: 10.00 | Z47: 6.70 | AA47: 0.271 | AB47: 0.201 | AC47: 0.271 | AD47: =(L47+M47)*Y47 -> 0 | AE47: =(L47+M47)*Z47 -> 0 | AF47: =ROUND((L47+M47)*AA47*AB47*AC47,2) -> 0 | AG47: 1800.00 | AH47: 2800.00 | AI47: =(L47+M47)/AG47 -> 0 | AJ47: =ROUNDDOWN(AI47/0.95,0) -> 0 | AK47: =(L47+M47)/AH47 -> 0 | AO47: 本酿造酱油5gal | AP47: 550桶
A48: =IF(N48<>0,1,"") | C48: =IFERROR(RANK(A48,$A$12:$A$125,0)+COUNTIFS(A$12:A48,A48)-1,"") | D48: 89100345010 | E48: 中文标签 | F48: 蒸鱼豉油 | G48: SEASONED SOY SAUCE FOR SEAFOOD 450ML*12 | H48: HADAY NƯỚC TƯƠNG HẤP CÁ 450ML*12 | I48: 出口海天牌蒸鱼豉油450ML*12(越南公司用；南宁生产)(玻璃瓶) | J48: 海天牌蒸鱼豉油450ML*12 | K48: 325300 | N48: =L48+M48 -> 0 | O48: =IF(M48/N48>1/9,"大于8送1",IF(ABS(M48/N48-1/9)<0.0001,"8送1",IF(M48/N48<1/9,IF(M48/N48>1/10,"8送1和9送1之间",IF(ABS(M48/N48-1/10)<0.0001,"9送1",IF(M48/N48<1/10,IF(M48/N48>1/11,"9送1和10送1之间",IF(ABS(M48/N48-1/11)<0.0001,"10送1","小于10送1")))))))) -> #DIV/0! | P48: =K48*L48 -> 0 | Q48: =K48*M48 -> 0 | R48: =N48*K48 -> 0 | S48: 0.08 | T48: =P48*(1+$S48) -> 0 | U48: =Q48*(1+$S48) -> 0 | V48: =R48*(1+$S48) -> 0 | W48: ="海天牌"&F48 -> 海天牌蒸鱼豉油 | X48: 450ML*12 | Y48: 10.00 | Z48: 6.70 | AA48: 0.271 | AB48: 0.201 | AC48: 0.271 | AD48: =(L48+M48)*Y48 -> 0 | AE48: =(L48+M48)*Z48 -> 0 | AF48: =ROUND((L48+M48)*AA48*AB48*AC48,2) -> 0 | AG48: 1800.00 | AH48: 2890.00 | AI48: =(L48+M48)/AG48 -> 0 | AJ48: =ROUNDDOWN(AI48/0.95,0) -> 0 | AK48: =(L48+M48)/AH48 -> 0
A49: =IF(N49<>0,1,"") | C49: =IFERROR(RANK(A49,$A$12:$A$125,0)+COUNTIFS(A$12:A49,A49)-1,"") | D49: 89100317504 | E49: 中文标签 | F49: 蒸鱼豉油 | G49: SEASONED SOY SAUCE FOR SEAFOOD 1.75L*6 | H49: HADAY NƯỚC TƯƠNG HẤP CÁ 1.75L*6 | I49: 出口海天牌蒸鱼豉油1.75L*6(越南公司用)(PET瓶) | J49: 海天牌蒸鱼豉油1.75L*6 | K49: 503900 | N49: =L49+M49 -> 0 | O49: =IF(M49/N49>1/9,"大于8送1",IF(ABS(M49/N49-1/9)<0.0001,"8送1",IF(M49/N49<1/9,IF(M49/N49>1/10,"8送1和9送1之间",IF(ABS(M49/N49-1/10)<0.0001,"9送1",IF(M49/N49<1/10,IF(M49/N49>1/11,"9送1和10送1之间",IF(ABS(M49/N49-1/11)<0.0001,"10送1","小于10送1")))))))) -> #DIV/0! | P49: =K49*L49 -> 0 | Q49: =K49*M49 -> 0 | R49: =N49*K49 -> 0 | S49: 0.08 | T49: =P49*(1+$S49) -> 0 | U49: =Q49*(1+$S49) -> 0 | V49: =R49*(1+$S49) -> 0 | W49: ="海天牌"&F49 -> 海天牌蒸鱼豉油 | X49: 1.75L*6 | Y49: 13.80 | Z49: 13.00 | AA49: 0.34 | AB49: 0.224 | AC49: 0.294 | AD49: =(L49+M49)*Y49 -> 0 | AE49: =(L49+M49)*Z49 -> 0 | AF49: =ROUND((L49+M49)*AA49*AB49*AC49,2) -> 0 | AG49: 1260.00 | AH49: 2030.00 | AI49: =(L49+M49)/AG49 -> 0 | AJ49: =ROUNDDOWN(AI49/0.95,0) -> 0 | AK49: =(L49+M49)/AH49 -> 0
A50: =IF(N50<>0,1,"") | C50: =IFERROR(RANK(A50,$A$12:$A$125,0)+COUNTIFS(A$12:A50,A50)-1,"") | D50: 89100317507 | E50: 中文标签 | F50: 蒸鱼豉油 | G50: SEASONED SOY SAUCE FOR SEAFOOD 1.75L*6 | H50: HADAY NƯỚC TƯƠNG HẤP CÁ 1.75L*6 | I50: 出口海天牌蒸鱼豉油1.75L*6(越南公司用；南宁生产)(PET瓶) | J50: 小标签关系不存在，不可下单 | K50: 503900 | N50: =L50+M50 -> 0 | O50: =IF(M50/N50>1/9,"大于8送1",IF(ABS(M50/N50-1/9)<0.0001,"8送1",IF(M50/N50<1/9,IF(M50/N50>1/10,"8送1和9送1之间",IF(ABS(M50/N50-1/10)<0.0001,"9送1",IF(M50/N50<1/10,IF(M50/N50>1/11,"9送1和10送1之间",IF(ABS(M50/N50-1/11)<0.0001,"10送1","小于10送1")))))))) -> #DIV/0! | P50: =K50*L50 -> 0 | Q50: =K50*M50 -> 0 | R50: =N50*K50 -> 0 | S50: 0.08 | T50: =P50*(1+$S50) -> 0 | U50: =Q50*(1+$S50) -> 0 | V50: =R50*(1+$S50) -> 0 | W50: ="海天牌"&F50 -> 海天牌蒸鱼豉油 | X50: 1.75L*6 | Y50: 13.80 | Z50: 13.00 | AA50: 0.34 | AB50: 0.224 | AC50: 0.294 | AD50: =(L50+M50)*Y50 -> 0 | AE50: =(L50+M50)*Z50 -> 0 | AF50: =ROUND((L50+M50)*AA50*AB50*AC50,2) -> 0 | AG50: 1280.00 | AH50: 2030.00 | AI50: =(L50+M50)/AG50 -> 0 | AJ50: =ROUNDDOWN(AI50/0.95,0) -> 0 | AK50: =(L50+M50)/AH50 -> 0 | AL50: 客户小标签高度>79mm：1150 | AO50: 鲜味生抽（经典版）（精选版） | AP50: 800箱
A51: =IF(N51<>0,1,"") | B51: 海天招牌老抽王 | C51: =IFERROR(RANK(A51,$A$12:$A$125,0)+COUNTIFS(A$12:A51,A51)-1,"") | D51: 89110650005 | E51: 中文标签 | F51: 海天招牌老抽王 | G51: HADAY SIGNATURE DARK SOY SAUCE 500ML*12 | H51: HADAY HẮC XÌ DẦU HẢO HẠNG 500ML*12 | I51: 出口海天牌海天招牌老抽王500ML*12(越南公司用)(玻璃瓶) | J51: 海天牌海天招牌老抽王500ML*12 | K51: 287900 | N51: =L51+M51 -> 0 | O51: =IF(M51/N51>1/9,"大于8送1",IF(ABS(M51/N51-1/9)<0.0001,"8送1",IF(M51/N51<1/9,IF(M51/N51>1/10,"8送1和9送1之间",IF(ABS(M51/N51-1/10)<0.0001,"9送1",IF(M51/N51<1/10,IF(M51/N51>1/11,"9送1和10送1之间",IF(ABS(M51/N51-1/11)<0.0001,"10送1","小于10送1")))))))) -> #DIV/0! | P51: =K51*L51 -> 0 | Q51: =K51*M51 -> 0 | R51: =N51*K51 -> 0 | S51: 0.08 | T51: =P51*(1+$S51) -> 0 | U51: =Q51*(1+$S51) -> 0 | V51: =R51*(1+$S51) -> 0 | W51: ="海天牌"&F51 -> 海天牌海天招牌老抽王 | X51: 500ML*12 | Y51: 10.80 | Z51: 7.80 | AA51: 0.292 | AB51: 0.215 | AC51: 0.247 | AD51: =(L51+M51)*Y51 -> 0 | AE51: =(L51+M51)*Z51 -> 0 | AF51: =ROUND((L51+M51)*AA51*AB51*AC51,2) -> 0 | AG51: 1780.00 | AH51: 2590.00 | AI51: =(L51+M51)/AG51 -> 0 | AJ51: =ROUNDDOWN(AI51/0.95,0) -> 0 | AK51: =(L51+M51)/AH51 -> 0 | AN51: 蚝油 | AO51: 270g招牌蚝油 | AP51: 5000箱 | AQ51: 内销小宗产品 每月排产频次极低 | AR51: 规格受限制
A52: =IF(N52<>0,1,"") | C52: =IFERROR(RANK(A52,$A$12:$A$125,0)+COUNTIFS(A$12:A52,A52)-1,"") | D52: 89110650026 | E52: 中文标签 | F52: 海天招牌老抽王 | G52: HADAY SIGNATURE DARK SOY SAUCE 500ML*12 | H52: HADAY HẮC XÌ DẦU HẢO HẠNG 500ML*12 | I52: 出口海天牌海天招牌老抽王500ML*12(越南公司用)(PET瓶) | J52: 海天牌海天招牌老抽王500ML*12 | K52: 287900 | N52: =L52+M52 -> 0 | O52: =IF(M52/N52>1/9,"大于8送1",IF(ABS(M52/N52-1/9)<0.0001,"8送1",IF(M52/N52<1/9,IF(M52/N52>1/10,"8送1和9送1之间",IF(ABS(M52/N52-1/10)<0.0001,"9送1",IF(M52/N52<1/10,IF(M52/N52>1/11,"9送1和10送1之间",IF(ABS(M52/N52-1/11)<0.0001,"10送1","小于10送1")))))))) -> #DIV/0! | P52: =K52*L52 -> 0 | Q52: =K52*M52 -> 0 | R52: =N52*K52 -> 0 | S52: 0.08 | T52: =P52*(1+$S52) -> 0 | U52: =Q52*(1+$S52) -> 0 | V52: =R52*(1+$S52) -> 0 | W52: ="海天牌"&F52 -> 海天牌海天招牌老抽王 | X52: 500ML*12 | Y52: 8.6 | Z52: 7.80 | AA52: 0.262 | AB52: 0.199 | AC52: 0.253 | AD52: =(L52+M52)*Y52 -> 0 | AE52: =(L52+M52)*Z52 -> 0 | AF52: =ROUND((L52+M52)*AA52*AB52*AC52,2) -> 0 | AG52: 2050.00 | AH52: 3260.00 | AI52: =(L52+M52)/AG52 -> 0 | AJ52: =ROUNDDOWN(AI52/0.95,0) -> 0 | AK52: =(L52+M52)/AH52 -> 0
A53: =IF(N53<>0,1,"") | C53: =IFERROR(RANK(A53,$A$12:$A$125,0)+COUNTIFS(A$12:A53,A53)-1,"") | D53: 89110617504 | E53: 中文标签 | F53: 海天招牌老抽王 | G53: HADAY SIGNATURE DARK SOY SAUCE 1.75L*6 | H53: HADAY HẮC XÌ DẦU HẢO HẠNG 1.75L*6 | I53: 出口海天牌海天招牌老抽王1.75L*6(越南公司用)(PET瓶) | J53: 海天牌海天招牌老抽王1.75L*6 | K53: 391900 | N53: =L53+M53 -> 0 | O53: =IF(M53/N53>1/9,"大于8送1",IF(ABS(M53/N53-1/9)<0.0001,"8送1",IF(M53/N53<1/9,IF(M53/N53>1/10,"8送1和9送1之间",IF(ABS(M53/N53-1/10)<0.0001,"9送1",IF(M53/N53<1/10,IF(M53/N53>1/11,"9送1和10送1之间",IF(ABS(M53/N53-1/11)<0.0001,"10送1","小于10送1")))))))) -> #DIV/0! | P53: =K53*L53 -> 0 | Q53: =K53*M53 -> 0 | R53: =N53*K53 -> 0 | S53: 0.08 | T53: =P53*(1+$S53) -> 0 | U53: =Q53*(1+$S53) -> 0 | V53: =R53*(1+$S53) -> 0 | W53: ="海天牌"&F53 -> 海天牌海天招牌老抽王 | X53: 1.75L*6 | Y53: 14.50 | Z53: 13.70 | AA53: 0.338 | AB53: 0.226 | AC53: 0.3 | AD53: =(L53+M53)*Y53 -> 0 | AE53: =(L53+M53)*Z53 -> 0 | AF53: =ROUND((L53+M53)*AA53*AB53*AC53,2) -> 0 | AG53: 1200.00 | AH53: 1930.00 | AI53: =(L53+M53)/AG53 -> 0 | AJ53: =ROUNDDOWN(AI53/0.95,0) -> 0 | AK53: =(L53+M53)/AH53 -> 0 | AO53: 550g招牌蚝油 | AP53: 5000箱
A54: =IF(N54<>0,1,"") | B54: 鲜味生抽（经典版） | C54: =IFERROR(RANK(A54,$A$12:$A$125,0)+COUNTIFS(A$12:A54,A54)-1,"") | D54: 89102150005 | E54: 越南文标签 | F54: 鲜味生抽（经典版） | G54: DELICIOUS LIGHT SOY SAUCE (CLASSIC VERSION) 500ML*12 | H54: HADAY NƯỚC TƯƠNG CHUẨN VỊ 500ML*12 | I54: 出口海天牌鲜味生抽(经典版)500ML*12(越南版；越南公司用)(玻璃瓶) | J54: 海天牌鲜味生抽(经典版)500ML*12 | K54: 205300 | N54: =L54+M54 -> 0 | O54: =IF(M54/N54>1/9,"大于8送1",IF(ABS(M54/N54-1/9)<0.0001,"8送1",IF(M54/N54<1/9,IF(M54/N54>1/10,"8送1和9送1之间",IF(ABS(M54/N54-1/10)<0.0001,"9送1",IF(M54/N54<1/10,IF(M54/N54>1/11,"9送1和10送1之间",IF(ABS(M54/N54-1/11)<0.0001,"10送1","小于10送1")))))))) -> #DIV/0! | P54: =K54*L54 -> 0 | Q54: =K54*M54 -> 0 | R54: =N54*K54 -> 0 | S54: 0.08 | T54: =P54*(1+$S54) -> 0 | U54: =Q54*(1+$S54) -> 0 | V54: =R54*(1+$S54) -> 0 | W54: ="海天牌"&F54 -> 海天牌鲜味生抽（经典版） | X54: 500ML*12 | Y54: 10.10 | Z54: 7.00 | AA54: 0.272 | AB54: 0.206 | AC54: 0.258 | AD54: =(L54+M54)*Y54 -> 0 | AE54: =(L54+M54)*Z54 -> 0 | AF54: =ROUND((L54+M54)*AA54*AB54*AC54,2) -> 0 | AG54: 1850.00 | AH54: 2770.00 | AI54: =(L54+M54)/AG54 -> 0 | AJ54: =ROUNDDOWN(AI54/0.95,0) -> 0 | AK54: =(L54+M54)/AH54 -> 0
A55: =IF(N55<>0,1,"") | C55: =IFERROR(RANK(A55,$A$12:$A$125,0)+COUNTIFS(A$12:A55,A55)-1,"") | D55: 89102180003 | E55: 中文标签 | F55: =F54 -> 鲜味生抽（经典版） | G55: DELICIOUS LIGHT SOY SAUCE (CLASSIC VERSION) 800ML*12 | H55: HADAY NƯỚC TƯƠNG CHUẨN VỊ 800ML*12 | I55: 出口海天牌鲜味生抽(经典版)800ML*12(越南公司用)(PE瓶) | J55: 海天牌鲜味生抽(经典版)800ML*12 | K55: 253300 | N55: =L55+M55 -> 0 | O55: =IF(M55/N55>1/9,"大于8送1",IF(ABS(M55/N55-1/9)<0.0001,"8送1",IF(M55/N55<1/9,IF(M55/N55>1/10,"8送1和9送1之间",IF(ABS(M55/N55-1/10)<0.0001,"9送1",IF(M55/N55<1/10,IF(M55/N55>1/11,"9送1和10送1之间",IF(ABS(M55/N55-1/11)<0.0001,"10送1","小于10送1")))))))) -> #DIV/0! | P55: =K55*L55 -> 0 | Q55: =K55*M55 -> 0 | R55: =N55*K55 -> 0 | S55: 0.08 | T55: =P55*(1+$S55) -> 0 | U55: =Q55*(1+$S55) -> 0 | V55: =R55*(1+$S55) -> 0 | W55: ="海天牌"&F55 -> 海天牌鲜味生抽（经典版） | X55: 800ML*12 | Y55: 12.20 | Z55: 11.30 | AA55: 0.365 | AB55: 0.274 | AC55: 0.225 | AD55: =(L55+M55)*Y55 -> 0 | AE55: =(L55+M55)*Z55 -> 0 | AF55: =ROUND((L55+M55)*AA55*AB55*AC55,2) -> 0 | AG55: 1260.00 | AH55: 2300.00 | AI55: =(L55+M55)/AG55 -> 0 | AJ55: =ROUNDDOWN(AI55/0.95,0) -> 0 | AK55: =(L55+M55)/AH55 -> 0
A56: =IF(N56<>0,1,"") | C56: =IFERROR(RANK(A56,$A$12:$A$125,0)+COUNTIFS(A$12:A56,A56)-1,"") | D56: 89102110907 | E56: 中文标签 | F56: =F55 -> 鲜味生抽（经典版） | G56: DELICIOUS LIGHT SOY SAUCE (CLASSIC VERSION) 1.9L*6 | H56: HADAY NƯỚC TƯƠNG CHUẨN VỊ 1.9L*6 | I56: 出口海天牌鲜味生抽(经典版)1.9L*6(越南公司用)(PET瓶) | J56: 海天牌鲜味生抽(经典版)1.9L*6 | K56: 290600 | N56: =L56+M56 -> 0 | O56: =IF(M56/N56>1/9,"大于8送1",IF(ABS(M56/N56-1/9)<0.0001,"8送1",IF(M56/N56<1/9,IF(M56/N56>1/10,"8送1和9送1之间",IF(ABS(M56/N56-1/10)<0.0001,"9送1",IF(M56/N56<1/10,IF(M56/N56>1/11,"9送1和10送1之间",IF(ABS(M56/N56-1/11)<0.0001,"10送1","小于10送1")))))))) -> #DIV/0! | P56: =K56*L56 -> 0 | Q56: =K56*M56 -> 0 | R56: =N56*K56 -> 0 | S56: 0.08 | T56: =P56*(1+$S56) -> 0 | U56: =Q56*(1+$S56) -> 0 | V56: =R56*(1+$S56) -> 0 | W56: ="海天牌"&F56 -> 海天牌鲜味生抽（经典版） | X56: 1.9L*6 | Y56: 14.30 | Z56: 13.40 | AA56: 0.351 | AB56: 0.238 | AC56: 0.303 | AD56: =(L56+M56)*Y56 -> 0 | AE56: =(L56+M56)*Z56 -> 0 | AF56: =ROUND((L56+M56)*AA56*AB56*AC56,2) -> 0 | AG56: 1100.00 | AH56: 1960.00 | AI56: =(L56+M56)/AG56 -> 0 | AJ56: =ROUNDDOWN(AI56/0.95,0) -> 0 | AK56: =(L56+M56)/AH56 -> 0
A57: =IF(N57<>0,1,"") | B57: 海天上等蚝油（经典版） | C57: =IFERROR(RANK(A57,$A$12:$A$125,0)+COUNTIFS(A$12:A57,A57)-1,"") | D57: 89401110001 | E57: 越南文标签 | F57: 海天上等蚝油（经典版） | G57: HADAY SUPERIOR OYSTER SAUCE (CLASSIC VERSION) 100G*48 | H57: HADAY DẦU HÀO THƯỢNG HẠNG (CLASSIC VERSION) 100G*48 | I57: 出口海天牌海天上等蚝油(经典版)100g*48(越南版；越南公司用)(自立袋) | J57: 海天牌海天上等蚝油(经典版)100G*48 | K57: 280000 | N57: =L57+M57 -> 0 | O57: =IF(M57/N57>1/9,"大于8送1",IF(ABS(M57/N57-1/9)<0.0001,"8送1",IF(M57/N57<1/9,IF(M57/N57>1/10,"8送1和9送1之间",IF(ABS(M57/N57-1/10)<0.0001,"9送1",IF(M57/N57<1/10,IF(M57/N57>1/11,"9送1和10送1之间",IF(ABS(M57/N57-1/11)<0.0001,"10送1","小于10送1")))))))) -> #DIV/0! | P57: =K57*L57 -> 0 | Q57: =K57*M57 -> 0 | R57: =N57*K57 -> 0 | S57: 0.08 | T57: =P57*(1+$S57) -> 0 | U57: =Q57*(1+$S57) -> 0 | V57: =R57*(1+$S57) -> 0 | W57: ="海天牌"&F57 -> 海天牌海天上等蚝油（经典版） | X57: 100G*48 | Y57: 5.90 | Z57: 4.80 | AA57: 0.472 | AB57: 0.36 | AC57: 0.12 | AD57: =(L57+M57)*Y57 -> 0 | AE57: =(L57+M57)*Z57 -> 0 | AF57: =ROUND((L57+M57)*AA57*AB57*AC57,2) -> 0 | AG57: 1250.00 | AH57: 4750.00 | AI57: =(L57+M57)/AG57 -> 0 | AJ57: =ROUNDDOWN(AI57/0.95,0) -> 0 | AK57: =(L57+M57)/AH57 -> 0
A58: =IF(N58<>0,1,"") | C58: =IFERROR(RANK(A58,$A$12:$A$125,0)+COUNTIFS(A$12:A58,A58)-1,"") | D58: 89440126013 | E58: 越南文标签 | F58: 海天上等蚝油（经典版） | G58: HADAY SUPERIOR OYSTER SAUCE (CLASSIC VERSION) 260G*24 | H58: HADAY DẦU HÀO THƯỢNG HẠNG (CLASSIC VERSION) 260G*24 | I58: 出口海天牌海天上等蚝油(经典版)260g*24(越南版；越南公司用)(玻璃瓶) | J58: 海天牌海天上等蚝油(经典版)260G*24 | K58: 240700 | N58: =L58+M58 -> 0 | O58: =IF(M58/N58>1/9,"大于8送1",IF(ABS(M58/N58-1/9)<0.0001,"8送1",IF(M58/N58<1/9,IF(M58/N58>1/10,"8送1和9送1之间",IF(ABS(M58/N58-1/10)<0.0001,"9送1",IF(M58/N58<1/10,IF(M58/N58>1/11,"9送1和10送1之间",IF(ABS(M58/N58-1/11)<0.0001,"10送1","小于10送1")))))))) -> #DIV/0! | P58: =K58*L58 -> 0 | Q58: =K58*M58 -> 0 | R58: =N58*K58 -> 0 | S58: 0.08 | T58: =P58*(1+$S58) -> 0 | U58: =Q58*(1+$S58) -> 0 | V58: =R58*(1+$S58) -> 0 | W58: ="海天牌"&F58 -> 海天牌海天上等蚝油（经典版） | X58: 260G*24 | Y58: 10.50 | Z58: 6.24 | AA58: 0.34 | AB58: 0.227 | AC58: 0.192 | AD58: =(L58+M58)*Y58 -> 0 | AE58: =(L58+M58)*Z58 -> 0 | AF58: =ROUND((L58+M58)*AA58*AB58*AC58,2) -> 0 | AG58: 1900.00 | AH58: 2670.00 | AI58: =(L58+M58)/AG58 -> 0 | AJ58: =ROUNDDOWN(AI58/0.95,0) -> 0 | AK58: =(L58+M58)/AH58 -> 0
A59: =IF(N59<>0,1,"") | C59: =IFERROR(RANK(A59,$A$12:$A$125,0)+COUNTIFS(A$12:A59,A59)-1,"") | D59: 89440126014 | E59: 越南文标签 | F59: 海天上等蚝油（经典版） | G59: HADAY SUPERIOR OYSTER SAUCE (CLASSIC VERSION) 260G*24 | H59: HADAY DẦU HÀO THƯỢNG HẠNG (CLASSIC VERSION) 260G*24 | I59: 出口海天牌海天上等蚝油(经典版)260g*24(越南版；越南公司用；南宁生产)(玻璃瓶) | J59: 海天牌海天上等蚝油(经典版)260g*24 | K59: 240700 | N59: =L59+M59 -> 0 | O59: =IF(M59/N59>1/9,"大于8送1",IF(ABS(M59/N59-1/9)<0.0001,"8送1",IF(M59/N59<1/9,IF(M59/N59>1/10,"8送1和9送1之间",IF(ABS(M59/N59-1/10)<0.0001,"9送1",IF(M59/N59<1/10,IF(M59/N59>1/11,"9送1和10送1之间",IF(ABS(M59/N59-1/11)<0.0001,"10送1","小于10送1")))))))) -> #DIV/0! | P59: =K59*L59 -> 0 | Q59: =K59*M59 -> 0 | R59: =N59*K59 -> 0 | S59: 0.08 | T59: =P59*(1+$S59) -> 0 | U59: =Q59*(1+$S59) -> 0 | V59: =R59*(1+$S59) -> 0 | W59: ="海天牌"&F59 -> 海天牌海天上等蚝油（经典版） | X59: 260G*24 | Y59: 10.50 | Z59: 6.24 | AA59: 0.34 | AB59: 0.227 | AC59: 0.192 | AD59: =(L59+M59)*Y59 -> 0 | AE59: =(L59+M59)*Z59 -> 0 | AF59: =ROUND((L59+M59)*AA59*AB59*AC59,2) -> 0 | AG59: 1900.00 | AH59: 2670.00 | AI59: =(L59+M59)/AG59 -> 0 | AJ59: =ROUNDDOWN(AI59/0.95,0) -> 0 | AK59: =(L59+M59)/AH59 -> 0
A60: =IF(N60<>0,1,"") | C60: =IFERROR(RANK(A60,$A$12:$A$125,0)+COUNTIFS(A$12:A60,A60)-1,"") | D60: 89440126016 | E60: 中文标签 | F60: 海天上等蚝油（经典版） | G60: HADAY SUPERIOR OYSTER SAUCE (CLASSIC VERSION) 260G*24 | H60: HADAY DẦU HÀO THƯỢNG HẠNG (CLASSIC VERSION) 260G*24 | I60: 出口海天牌海天上等蚝油(经典版)260g*24(越南公司用)(玻璃瓶) | J60: 海天牌海天上等蚝油(经典版)260G*24 | K60: 240700 | N60: =L60+M60 -> 0 | O60: =IF(M60/N60>1/9,"大于8送1",IF(ABS(M60/N60-1/9)<0.0001,"8送1",IF(M60/N60<1/9,IF(M60/N60>1/10,"8送1和9送1之间",IF(ABS(M60/N60-1/10)<0.0001,"9送1",IF(M60/N60<1/10,IF(M60/N60>1/11,"9送1和10送1之间",IF(ABS(M60/N60-1/11)<0.0001,"10送1","小于10送1")))))))) -> #DIV/0! | P60: =K60*L60 -> 0 | Q60: =K60*M60 -> 0 | R60: =N60*K60 -> 0 | S60: 0.08 | T60: =P60*(1+$S60) -> 0 | U60: =Q60*(1+$S60) -> 0 | V60: =R60*(1+$S60) -> 0 | W60: ="海天牌"&F60 -> 海天牌海天上等蚝油（经典版） | X60: 260G*24 | Y60: 10.50 | Z60: 6.24 | AA60: 0.34 | AB60: 0.227 | AC60: 0.192 | AD60: =(L60+M60)*Y60 -> 0 | AE60: =(L60+M60)*Z60 -> 0 | AF60: =ROUND((L60+M60)*AA60*AB60*AC60,2) -> 0 | AG60: 1900.00 | AH60: 2670.00 | AI60: =(L60+M60)/AG60 -> 0 | AJ60: =ROUNDDOWN(AI60/0.95,0) -> 0 | AK60: =(L60+M60)/AH60 -> 0
A61: =IF(N61<>0,1,"") | C61: =IFERROR(RANK(A61,$A$12:$A$125,0)+COUNTIFS(A$12:A61,A61)-1,"") | D61: 89440126015 | E61: 中文标签 | F61: 海天上等蚝油（经典版） | G61: HADAY SUPERIOR OYSTER SAUCE (CLASSIC VERSION) 260G*24 | H61: HADAY DẦU HÀO THƯỢNG HẠNG (CLASSIC VERSION) 260G*24 | I61: 出口海天牌海天上等蚝油(经典版)260g*24(越南公司用；南宁生产)(玻璃瓶) | J61: 海天牌海天上等蚝油(经典版)260G*24 | K61: 240700 | N61: =L61+M61 -> 0 | O61: =IF(M61/N61>1/9,"大于8送1",IF(ABS(M61/N61-1/9)<0.0001,"8送1",IF(M61/N61<1/9,IF(M61/N61>1/10,"8送1和9送1之间",IF(ABS(M61/N61-1/10)<0.0001,"9送1",IF(M61/N61<1/10,IF(M61/N61>1/11,"9送1和10送1之间",IF(ABS(M61/N61-1/11)<0.0001,"10送1","小于10送1")))))))) -> #DIV/0! | P61: =K61*L61 -> 0 | Q61: =K61*M61 -> 0 | R61: =N61*K61 -> 0 | S61: 0.08 | T61: =P61*(1+$S61) -> 0 | U61: =Q61*(1+$S61) -> 0 | V61: =R61*(1+$S61) -> 0 | W61: ="海天牌"&F61 -> 海天牌海天上等蚝油（经典版） | X61: 260G*24 | Y61: 10.50 | Z61: 6.24 | AA61: 0.34 | AB61: 0.227 | AC61: 0.192 | AD61: =(L61+M61)*Y61 -> 0 | AE61: =(L61+M61)*Z61 -> 0 | AF61: =ROUND((L61+M61)*AA61*AB61*AC61,2) -> 0 | AG61: 1900.00 | AH61: 2670.00 | AI61: =(L61+M61)/AG61 -> 0 | AJ61: =ROUNDDOWN(AI61/0.95,0) -> 0 | AK61: =(L61+M61)/AH61 -> 0
A62: =IF(N62<>0,1,"") | C62: =IFERROR(RANK(A62,$A$12:$A$125,0)+COUNTIFS(A$12:A62,A62)-1,"") | D62: 89440159013 | E62: 越南文标签 | F62: 海天上等蚝油（经典版） | G62: HADAY SUPERIOR OYSTER SAUCE (CLASSIC VERSION) 590G*9 | H62: HADAY DẦU HÀO THƯỢNG HẠNG (CLASSIC VERSION) 590G*9 | I62: 出口海天牌海天上等蚝油(经典版)590g*9(越南版；越南公司用)(PET挤挤瓶) | J62: 海天牌海天上等蚝油(经典版)590G*9 | K62: 206500 | N62: =L62+M62 -> 0 | O62: =IF(M62/N62>1/9,"大于8送1",IF(ABS(M62/N62-1/9)<0.0001,"8送1",IF(M62/N62<1/9,IF(M62/N62>1/10,"8送1和9送1之间",IF(ABS(M62/N62-1/10)<0.0001,"9送1",IF(M62/N62<1/10,IF(M62/N62>1/11,"9送1和10送1之间",IF(ABS(M62/N62-1/11)<0.0001,"10送1","小于10送1")))))))) -> #DIV/0! | P62: =K62*L62 -> 0 | Q62: =K62*M62 -> 0 | R62: =N62*K62 -> 0 | S62: 0.08 | T62: =P62*(1+$S62) -> 0 | U62: =Q62*(1+$S62) -> 0 | V62: =R62*(1+$S62) -> 0 | W62: ="海天牌"&F62 -> 海天牌海天上等蚝油（经典版） | X62: 590G*9 | Y62: 6.00 | Z62: 5.31 | AA62: 0.252 | AB62: 0.18 | AC62: 0.23 | AD62: =(L62+M62)*Y62 -> 0 | AE62: =(L62+M62)*Z62 -> 0 | AF62: =ROUND((L62+M62)*AA62*AB62*AC62,2) -> 0 | AG62: 2700.00 | AH62: 4670.00 | AI62: =(L62+M62)/AG62 -> 0 | AJ62: =ROUNDDOWN(AI62/0.95,0) -> 0 | AK62: =(L62+M62)/AH62 -> 0
A63: =IF(N63<>0,1,"") | C63: =IFERROR(RANK(A63,$A$12:$A$125,0)+COUNTIFS(A$12:A63,A63)-1,"") | D63: 89401159001 | E63: 越南文标签 | F63: 海天上等蚝油（经典版） | G63: HADAY SUPERIOR OYSTER SAUCE (CLASSIC VERSION) 590G*9 | H63: HADAY DẦU HÀO THƯỢNG HẠNG (CLASSIC VERSION) 590G*9 | I63: 出口海天牌海天上等蚝油(经典版)590g*9(越南版；越南公司用；南宁生产)(PET挤挤瓶) | J63: 小标签关系不存在，不可下单 | K63: 206500 | N63: =L63+M63 -> 0 | O63: =IF(M63/N63>1/9,"大于8送1",IF(ABS(M63/N63-1/9)<0.0001,"8送1",IF(M63/N63<1/9,IF(M63/N63>1/10,"8送1和9送1之间",IF(ABS(M63/N63-1/10)<0.0001,"9送1",IF(M63/N63<1/10,IF(M63/N63>1/11,"9送1和10送1之间",IF(ABS(M63/N63-1/11)<0.0001,"10送1","小于10送1")))))))) -> #DIV/0! | P63: =K63*L63 -> 0 | Q63: =K63*M63 -> 0 | R63: =N63*K63 -> 0 | S63: 0.08 | T63: =P63*(1+$S63) -> 0 | U63: =Q63*(1+$S63) -> 0 | V63: =R63*(1+$S63) -> 0 | W63: ="海天牌"&F63 -> 海天牌海天上等蚝油（经典版） | X63: 590G*9 | Y63: 6.00 | Z63: 5.31 | AA63: 0.252 | AB63: 0.18 | AC63: 0.23 | AD63: =(L63+M63)*Y63 -> 0 | AE63: =(L63+M63)*Z63 -> 0 | AF63: =ROUND((L63+M63)*AA63*AB63*AC63,2) -> 0 | AG63: 2760.00 | AH63: 4670.00 | AI63: =(L63+M63)/AG63 -> 0 | AJ63: =ROUNDDOWN(AI63/0.95,0) -> 0 | AK63: =(L63+M63)/AH63 -> 0
A64: =IF(N64<>0,1,"") | C64: =IFERROR(RANK(A64,$A$12:$A$125,0)+COUNTIFS(A$12:A64,A64)-1,"") | D64: 89401159016 | E64: 中文标签 | F64: 海天上等蚝油（经典版） | G64: HADAY SUPERIOR OYSTER SAUCE (CLASSIC VERSION) 590G*9 | H64: HADAY DẦU HÀO THƯỢNG HẠNG (CLASSIC VERSION) 590G*9 | I64: 出口海天牌海天上等蚝油(经典版)590g*9(越南公司用)(PET挤挤瓶) | J64: 海天牌海天上等蚝油(经典版)590g*9 | K64: 206500 | N64: =L64+M64 -> 0 | O64: =IF(M64/N64>1/9,"大于8送1",IF(ABS(M64/N64-1/9)<0.0001,"8送1",IF(M64/N64<1/9,IF(M64/N64>1/10,"8送1和9送1之间",IF(ABS(M64/N64-1/10)<0.0001,"9送1",IF(M64/N64<1/10,IF(M64/N64>1/11,"9送1和10送1之间",IF(ABS(M64/N64-1/11)<0.0001,"10送1","小于10送1")))))))) -> #DIV/0! | P64: =K64*L64 -> 0 | Q64: =K64*M64 -> 0 | R64: =N64*K64 -> 0 | S64: 0.08 | T64: =P64*(1+$S64) -> 0 | U64: =Q64*(1+$S64) -> 0 | V64: =R64*(1+$S64) -> 0 | W64: ="海天牌"&F64 -> 海天牌海天上等蚝油（经典版） | X64: 590G*9 | Y64: 6.00 | Z64: 5.31 | AA64: 0.252 | AB64: 0.18 | AC64: 0.23 | AD64: =(L64+M64)*Y64 -> 0 | AE64: =(L64+M64)*Z64 -> 0 | AF64: =ROUND((L64+M64)*AA64*AB64*AC64,2) -> 0 | AG64: 2700.00 | AH64: 4670.00 | AI64: =(L64+M64)/AG64 -> 0 | AJ64: =ROUNDDOWN(AI64/0.95,0) -> 0 | AK64: =(L64+M64)/AH64 -> 0
A65: =IF(N65<>0,1,"") | C65: =IFERROR(RANK(A65,$A$12:$A$125,0)+COUNTIFS(A$12:A65,A65)-1,"") | D65: 89440170016 | E65: 越南文标签 | F65: 海天上等蚝油（经典版） | G65: HADAY SUPERIOR OYSTER SAUCE (CLASSIC VERSION) 700G*12 | H65: HADAY DẦU HÀO THƯỢNG HẠNG (CLASSIC VERSION) 700G*12 | I65: 出口海天牌海天上等蚝油(经典版)700g*12(越南版；越南公司用)(玻璃瓶) | J65: 海天牌海天上等蚝油(经典版)700G*12 | K65: 245600 | N65: =L65+M65 -> 0 | O65: =IF(M65/N65>1/9,"大于8送1",IF(ABS(M65/N65-1/9)<0.0001,"8送1",IF(M65/N65<1/9,IF(M65/N65>1/10,"8送1和9送1之间",IF(ABS(M65/N65-1/10)<0.0001,"9送1",IF(M65/N65<1/10,IF(M65/N65>1/11,"9送1和10送1之间",IF(ABS(M65/N65-1/11)<0.0001,"10送1","小于10送1")))))))) -> #DIV/0! | P65: =K65*L65 -> 0 | Q65: =K65*M65 -> 0 | R65: =N65*K65 -> 0 | S65: 0.08 | T65: =P65*(1+$S65) -> 0 | U65: =Q65*(1+$S65) -> 0 | V65: =R65*(1+$S65) -> 0 | W65: ="海天牌"&F65 -> 海天牌海天上等蚝油（经典版） | X65: 700G*12 | Y65: 12.40 | Z65: 8.40 | AA65: 0.301 | AB65: 0.226 | AC65: 0.2775 | AD65: =(L65+M65)*Y65 -> 0 | AE65: =(L65+M65)*Z65 -> 0 | AF65: =ROUND((L65+M65)*AA65*AB65*AC65,2) -> 0 | AG65: 1500.00 | AH65: 2260.00 | AI65: =(L65+M65)/AG65 -> 0 | AJ65: =ROUNDDOWN(AI65/0.95,0) -> 0 | AK65: =(L65+M65)/AH65 -> 0 | AL65: 出口大标签版：1500
A66: =IF(N66<>0,1,"") | C66: =IFERROR(RANK(A66,$A$12:$A$125,0)+COUNTIFS(A$12:A66,A66)-1,"") | D66: 89440170017 | E66: 越南文标签 | F66: 海天上等蚝油（经典版） | G66: HADAY SUPERIOR OYSTER SAUCE (CLASSIC VERSION) 700G*12 | H66: HADAY DẦU HÀO THƯỢNG HẠNG (CLASSIC VERSION) 700G*12 | I66: 出口海天牌海天上等蚝油(经典版)700g*12(越南版；越南公司用；南宁生产)(玻璃瓶) | J66: 海天牌海天上等蚝油(经典版)700g*12 | K66: 245600 | N66: =L66+M66 -> 0 | O66: =IF(M66/N66>1/9,"大于8送1",IF(ABS(M66/N66-1/9)<0.0001,"8送1",IF(M66/N66<1/9,IF(M66/N66>1/10,"8送1和9送1之间",IF(ABS(M66/N66-1/10)<0.0001,"9送1",IF(M66/N66<1/10,IF(M66/N66>1/11,"9送1和10送1之间",IF(ABS(M66/N66-1/11)<0.0001,"10送1","小于10送1")))))))) -> #DIV/0! | P66: =K66*L66 -> 0 | Q66: =K66*M66 -> 0 | R66: =N66*K66 -> 0 | S66: 0.08 | T66: =P66*(1+$S66) -> 0 | U66: =Q66*(1+$S66) -> 0 | V66: =R66*(1+$S66) -> 0 | W66: ="海天牌"&F66 -> 海天牌海天上等蚝油（经典版） | X66: 700G*12 | Y66: 12.40 | Z66: 8.40 | AA66: 0.298 | AB66: 0.224 | AC66: 0.2775 | AD66: =(L66+M66)*Y66 -> 0 | AE66: =(L66+M66)*Z66 -> 0 | AF66: =ROUND((L66+M66)*AA66*AB66*AC66,2) -> 0 | AG66: 1430.00 | AH66: 2260.00 | AI66: =(L66+M66)/AG66 -> 0 | AJ66: =ROUNDDOWN(AI66/0.95,0) -> 0 | AK66: =(L66+M66)/AH66 -> 0
A67: =IF(N67<>0,1,"") | C67: =IFERROR(RANK(A67,$A$12:$A$125,0)+COUNTIFS(A$12:A67,A67)-1,"") | D67: 89440170015 | E67: 中文标签 | F67: 海天上等蚝油（经典版） | G67: HADAY SUPERIOR OYSTER SAUCE (CLASSIC VERSION) 700G*12 | H67: HADAY DẦU HÀO THƯỢNG HẠNG (CLASSIC VERSION) 700G*12 | I67: 出口海天牌海天上等蚝油(经典版)700g*12(越南公司用)(玻璃瓶) | J67: 海天牌海天上等蚝油(经典版)700G*12 | K67: 245600 | N67: =L67+M67 -> 0 | O67: =IF(M67/N67>1/9,"大于8送1",IF(ABS(M67/N67-1/9)<0.0001,"8送1",IF(M67/N67<1/9,IF(M67/N67>1/10,"8送1和9送1之间",IF(ABS(M67/N67-1/10)<0.0001,"9送1",IF(M67/N67<1/10,IF(M67/N67>1/11,"9送1和10送1之间",IF(ABS(M67/N67-1/11)<0.0001,"10送1","小于10送1")))))))) -> #DIV/0! | P67: =K67*L67 -> 0 | Q67: =K67*M67 -> 0 | R67: =N67*K67 -> 0 | S67: 0.08 | T67: =P67*(1+$S67) -> 0 | U67: =Q67*(1+$S67) -> 0 | V67: =R67*(1+$S67) -> 0 | W67: ="海天牌"&F67 -> 海天牌海天上等蚝油（经典版） | X67: 700G*12 | Y67: 12.40 | Z67: 8.40 | AA67: 0.301 | AB67: 0.226 | AC67: 0.2775 | AD67: =(L67+M67)*Y67 -> 0 | AE67: =(L67+M67)*Z67 -> 0 | AF67: =ROUND((L67+M67)*AA67*AB67*AC67,2) -> 0 | AG67: 1500.00 | AH67: 2260.00 | AI67: =(L67+M67)/AG67 -> 0 | AJ67: =ROUNDDOWN(AI67/0.95,0) -> 0 | AK67: =(L67+M67)/AH67 -> 0
A68: =IF(N68<>0,1,"") | C68: =IFERROR(RANK(A68,$A$12:$A$125,0)+COUNTIFS(A$12:A68,A68)-1,"") | D68: 89440170018 | E68: 中文标签 | F68: 海天上等蚝油（经典版） | G68: HADAY SUPERIOR OYSTER SAUCE (CLASSIC VERSION) 700G*12 | H68: HADAY DẦU HÀO THƯỢNG HẠNG (CLASSIC VERSION) 700G*12 | I68: 出口海天牌海天上等蚝油(经典版)700g*12(越南公司用；南宁生产)(玻璃瓶) | J68: 海天牌海天上等蚝油(经典版)700G*12 | K68: 245600 | N68: =L68+M68 -> 0 | O68: =IF(M68/N68>1/9,"大于8送1",IF(ABS(M68/N68-1/9)<0.0001,"8送1",IF(M68/N68<1/9,IF(M68/N68>1/10,"8送1和9送1之间",IF(ABS(M68/N68-1/10)<0.0001,"9送1",IF(M68/N68<1/10,IF(M68/N68>1/11,"9送1和10送1之间",IF(ABS(M68/N68-1/11)<0.0001,"10送1","小于10送1")))))))) -> #DIV/0! | P68: =K68*L68 -> 0 | Q68: =K68*M68 -> 0 | R68: =N68*K68 -> 0 | S68: 0.08 | T68: =P68*(1+$S68) -> 0 | U68: =Q68*(1+$S68) -> 0 | V68: =R68*(1+$S68) -> 0 | W68: ="海天牌"&F68 -> 海天牌海天上等蚝油（经典版） | X68: 700G*12 | Y68: 12.40 | Z68: 8.40 | AA68: 0.301 | AB68: 0.226 | AC68: 0.2775 | AD68: =(L68+M68)*Y68 -> 0 | AE68: =(L68+M68)*Z68 -> 0 | AF68: =ROUND((L68+M68)*AA68*AB68*AC68,2) -> 0 | AG68: 1500.00 | AH68: 2260.00 | AI68: =(L68+M68)/AG68 -> 0 | AJ68: =ROUNDDOWN(AI68/0.95,0) -> 0 | AK68: =(L68+M68)/AH68 -> 0
A69: =IF(N69<>0,1,"") | C69: =IFERROR(RANK(A69,$A$12:$A$125,0)+COUNTIFS(A$12:A69,A69)-1,"") | D69: 89440100115 | E69: 越南文标签 | F69: 海天上等蚝油（经典版） | G69: HADAY SUPERIOR OYSTER SAUCE (CLASSIC VERSION) 1KG*9 | H69: HADAY DẦU HÀO THƯỢNG HẠNG (CLASSIC VERSION) 1KG*9 | I69: 出口海天牌海天上等蚝油(经典版)1KG*9(越南版；越南公司用)(PET挤挤瓶) | J69: 海天牌海天上等蚝油(经典版)1KG*9 | K69: 301400 | N69: =L69+M69 -> 0 | O69: =IF(M69/N69>1/9,"大于8送1",IF(ABS(M69/N69-1/9)<0.0001,"8送1",IF(M69/N69<1/9,IF(M69/N69>1/10,"8送1和9送1之间",IF(ABS(M69/N69-1/10)<0.0001,"9送1",IF(M69/N69<1/10,IF(M69/N69>1/11,"9送1和10送1之间",IF(ABS(M69/N69-1/11)<0.0001,"10送1","小于10送1")))))))) -> #DIV/0! | P69: =K69*L69 -> 0 | Q69: =K69*M69 -> 0 | R69: =N69*K69 -> 0 | S69: 0.08 | T69: =P69*(1+$S69) -> 0 | U69: =Q69*(1+$S69) -> 0 | V69: =R69*(1+$S69) -> 0 | W69: ="海天牌"&F69 -> 海天牌海天上等蚝油（经典版） | X69: 1KG*9 | Y69: 10.00 | Z69: 9.00 | AA69: 0.305 | AB69: 0.219 | AC69: 0.25 | AD69: =(L69+M69)*Y69 -> 0 | AE69: =(L69+M69)*Z69 -> 0 | AF69: =ROUND((L69+M69)*AA69*AB69*AC69,2) -> 0 | AG69: 1680.00 | AH69: 2800.00 | AI69: =(L69+M69)/AG69 -> 0 | AJ69: =ROUNDDOWN(AI69/0.95,0) -> 0 | AK69: =(L69+M69)/AH69 -> 0
A70: =IF(N70<>0,1,"") | C70: =IFERROR(RANK(A70,$A$12:$A$125,0)+COUNTIFS(A$12:A70,A70)-1,"") | D70: 89440100116 | E70: 越南文标签 | F70: 海天上等蚝油（经典版） | G70: HADAY SUPERIOR OYSTER SAUCE (CLASSIC VERSION) 1KG*9 | H70: HADAY DẦU HÀO THƯỢNG HẠNG (CLASSIC VERSION) 1KG*9 | I70: 出口海天牌海天上等蚝油(经典版)1KG*9(越南版；越南公司用；南宁生产)(PET挤挤瓶) | J70: 海天牌海天上等蚝油(经典版)1kg*9 | K70: 301400 | N70: =L70+M70 -> 0 | O70: =IF(M70/N70>1/9,"大于8送1",IF(ABS(M70/N70-1/9)<0.0001,"8送1",IF(M70/N70<1/9,IF(M70/N70>1/10,"8送1和9送1之间",IF(ABS(M70/N70-1/10)<0.0001,"9送1",IF(M70/N70<1/10,IF(M70/N70>1/11,"9送1和10送1之间",IF(ABS(M70/N70-1/11)<0.0001,"10送1","小于10送1")))))))) -> #DIV/0! | P70: =K70*L70 -> 0 | Q70: =K70*M70 -> 0 | R70: =N70*K70 -> 0 | S70: 0.08 | T70: =P70*(1+$S70) -> 0 | U70: =Q70*(1+$S70) -> 0 | V70: =R70*(1+$S70) -> 0 | W70: ="海天牌"&F70 -> 海天牌海天上等蚝油（经典版） | X70: 1KG*9 | Y70: 10.00 | Z70: 9.00 | AA70: 0.305 | AB70: 0.219 | AC70: 0.25 | AD70: =(L70+M70)*Y70 -> 0 | AE70: =(L70+M70)*Z70 -> 0 | AF70: =ROUND((L70+M70)*AA70*AB70*AC70,2) -> 0 | AG70: 1680.00 | AH70: 2800.00 | AI70: =(L70+M70)/AG70 -> 0 | AJ70: =ROUNDDOWN(AI70/0.95,0) -> 0 | AK70: =(L70+M70)/AH70 -> 0
A71: =IF(N71<>0,1,"") | C71: =IFERROR(RANK(A71,$A$12:$A$125,0)+COUNTIFS(A$12:A71,A71)-1,"") | D71: 89440122716 | E71: 越南文标签 | F71: 海天上等蚝油（经典版） | G71: HADAY SUPERIOR OYSTER SAUCE (CLASSIC VERSION) 2.27KG*4 | H71: HADAY DẦU HÀO THƯỢNG HẠNG (CLASSIC VERSION) 2.27KG*4 | I71: 出口海天牌海天上等蚝油(经典版)2.27KG*4(越南版；越南公司用)(PE瓶) | J71: 海天牌海天上等蚝油(经典版)2.27KG*4 | K71: 240000 | N71: =L71+M71 -> 0 | O71: =IF(M71/N71>1/9,"大于8送1",IF(ABS(M71/N71-1/9)<0.0001,"8送1",IF(M71/N71<1/9,IF(M71/N71>1/10,"8送1和9送1之间",IF(ABS(M71/N71-1/10)<0.0001,"9送1",IF(M71/N71<1/10,IF(M71/N71>1/11,"9送1和10送1之间",IF(ABS(M71/N71-1/11)<0.0001,"10送1","小于10送1")))))))) -> #DIV/0! | P71: =K71*L71 -> 0 | Q71: =K71*M71 -> 0 | R71: =N71*K71 -> 0 | S71: 0.08 | T71: =P71*(1+$S71) -> 0 | U71: =Q71*(1+$S71) -> 0 | V71: =R71*(1+$S71) -> 0 | W71: ="海天牌"&F71 -> 海天牌海天上等蚝油（经典版） | X71: 2.27KG*4 | Y71: 10.00 | Z71: 9.08 | AA71: 0.306 | AB71: 0.188 | AC71: 0.283 | AD71: =(L71+M71)*Y71 -> 0 | AE71: =(L71+M71)*Z71 -> 0 | AF71: =ROUND((L71+M71)*AA71*AB71*AC71,2) -> 0 | AG71: 1700.00 | AH71: 2800.00 | AI71: =(L71+M71)/AG71 -> 0 | AJ71: =ROUNDDOWN(AI71/0.95,0) -> 0 | AK71: =(L71+M71)/AH71 -> 0 | AL71: 美加版：1380
A72: =IF(N72<>0,1,"") | C72: =IFERROR(RANK(A72,$A$12:$A$125,0)+COUNTIFS(A$12:A72,A72)-1,"") | D72: 89440122717 | E72: 越南文标签 | F72: 海天上等蚝油（经典版） | G72: HADAY SUPERIOR OYSTER SAUCE (CLASSIC VERSION) 2.27KG*4 | H72: HADAY DẦU HÀO THƯỢNG HẠNG (CLASSIC VERSION) 2.27KG*4 | I72: 出口海天牌海天上等蚝油(经典版)2.27KG*4(越南版；越南公司用；南宁生产)(PE瓶) | J72: 海天牌海天上等蚝油(经典版)2.27kg*4 | K72: 240000 | N72: =L72+M72 -> 0 | O72: =IF(M72/N72>1/9,"大于8送1",IF(ABS(M72/N72-1/9)<0.0001,"8送1",IF(M72/N72<1/9,IF(M72/N72>1/10,"8送1和9送1之间",IF(ABS(M72/N72-1/10)<0.0001,"9送1",IF(M72/N72<1/10,IF(M72/N72>1/11,"9送1和10送1之间",IF(ABS(M72/N72-1/11)<0.0001,"10送1","小于10送1")))))))) -> #DIV/0! | P72: =K72*L72 -> 0 | Q72: =K72*M72 -> 0 | R72: =N72*K72 -> 0 | S72: 0.08 | T72: =P72*(1+$S72) -> 0 | U72: =Q72*(1+$S72) -> 0 | V72: =R72*(1+$S72) -> 0 | W72: ="海天牌"&F72 -> 海天牌海天上等蚝油（经典版） | X72: 2.27KG*4 | Y72: 10.00 | Z72: 9.08 | AA72: 0.306 | AB72: 0.188 | AC72: 0.283 | AD72: =(L72+M72)*Y72 -> 0 | AE72: =(L72+M72)*Z72 -> 0 | AF72: =ROUND((L72+M72)*AA72*AB72*AC72,2) -> 0 | AG72: 1700.00 | AH72: 2800.00 | AI72: =(L72+M72)/AG72 -> 0 | AJ72: =ROUNDDOWN(AI72/0.95,0) -> 0 | AK72: =(L72+M72)/AH72 -> 0
A73: =IF(N73<>0,1,"") | C73: =IFERROR(RANK(A73,$A$12:$A$125,0)+COUNTIFS(A$12:A73,A73)-1,"") | D73: 89440122715 | E73: 中文标签 | F73: 海天上等蚝油（经典版） | G73: HADAY SUPERIOR OYSTER SAUCE (CLASSIC VERSION) 2.27KG*4 | H73: HADAY DẦU HÀO THƯỢNG HẠNG (CLASSIC VERSION) 2.27KG*4 | I73: 出口海天牌海天上等蚝油(经典版)2.27KG*4(越南公司用)(PE瓶) | J73: 海天牌海天上等蚝油(经典版)2.27KG*4 | K73: 240000 | N73: =L73+M73 -> 0 | O73: =IF(M73/N73>1/9,"大于8送1",IF(ABS(M73/N73-1/9)<0.0001,"8送1",IF(M73/N73<1/9,IF(M73/N73>1/10,"8送1和9送1之间",IF(ABS(M73/N73-1/10)<0.0001,"9送1",IF(M73/N73<1/10,IF(M73/N73>1/11,"9送1和10送1之间",IF(ABS(M73/N73-1/11)<0.0001,"10送1","小于10送1")))))))) -> #DIV/0! | P73: =K73*L73 -> 0 | Q73: =K73*M73 -> 0 | R73: =N73*K73 -> 0 | S73: 0.08 | T73: =P73*(1+$S73) -> 0 | U73: =Q73*(1+$S73) -> 0 | V73: =R73*(1+$S73) -> 0 | W73: ="海天牌"&F73 -> 海天牌海天上等蚝油（经典版） | X73: 2.27KG*4 | Y73: 10.00 | Z73: 9.08 | AA73: 0.306 | AB73: 0.188 | AC73: 0.283 | AD73: =(L73+M73)*Y73 -> 0 | AE73: =(L73+M73)*Z73 -> 0 | AF73: =ROUND((L73+M73)*AA73*AB73*AC73,2) -> 0 | AG73: 1700.00 | AH73: 2800.00 | AI73: =(L73+M73)/AG73 -> 0 | AJ73: =ROUNDDOWN(AI73/0.95,0) -> 0 | AK73: =(L73+M73)/AH73 -> 0
A74: =IF(N74<>0,1,"") | C74: =IFERROR(RANK(A74,$A$12:$A$125,0)+COUNTIFS(A$12:A74,A74)-1,"") | D74: 89440122718 | E74: 中文标签 | F74: 海天上等蚝油（经典版） | G74: HADAY SUPERIOR OYSTER SAUCE (CLASSIC VERSION) 2.27KG*4 | H74: HADAY DẦU HÀO THƯỢNG HẠNG (CLASSIC VERSION) 2.27KG*4 | I74: 出口海天牌海天上等蚝油(经典版)2.27KG*4(越南公司用；南宁生产)(PE瓶) | J74: 海天牌海天上等蚝油(经典版)2.27kg*4 | K74: 240000 | N74: =L74+M74 -> 0 | O74: =IF(M74/N74>1/9,"大于8送1",IF(ABS(M74/N74-1/9)<0.0001,"8送1",IF(M74/N74<1/9,IF(M74/N74>1/10,"8送1和9送1之间",IF(ABS(M74/N74-1/10)<0.0001,"9送1",IF(M74/N74<1/10,IF(M74/N74>1/11,"9送1和10送1之间",IF(ABS(M74/N74-1/11)<0.0001,"10送1","小于10送1")))))))) -> #DIV/0! | P74: =K74*L74 -> 0 | Q74: =K74*M74 -> 0 | R74: =N74*K74 -> 0 | S74: 0.08 | T74: =P74*(1+$S74) -> 0 | U74: =Q74*(1+$S74) -> 0 | V74: =R74*(1+$S74) -> 0 | W74: ="海天牌"&F74 -> 海天牌海天上等蚝油（经典版） | X74: 2.27KG*4 | Y74: 10.00 | Z74: 9.08 | AA74: 0.306 | AB74: 0.188 | AC74: 0.283 | AD74: =(L74+M74)*Y74 -> 0 | AE74: =(L74+M74)*Z74 -> 0 | AF74: =ROUND((L74+M74)*AA74*AB74*AC74,2) -> 0 | AG74: 1700.00 | AH74: 2800.00 | AI74: =(L74+M74)/AG74 -> 0 | AJ74: =ROUNDDOWN(AI74/0.95,0) -> 0 | AK74: =(L74+M74)/AH74 -> 0
A75: =IF(N75<>0,1,"") | C75: =IFERROR(RANK(A75,$A$12:$A$125,0)+COUNTIFS(A$12:A75,A75)-1,"") | D75: 89440100614 | E75: 越南文标签 | F75: 海天上等蚝油（经典版） | G75: HADAY SUPERIOR OYSTER SAUCE (CLASSIC VERSION) 6KG*2 | H75: HADAY DẦU HÀO THƯỢNG HẠNG (CLASSIC VERSION) 6KG*2 | I75: 出口海天牌海天上等蚝油(经典版)6KG*2(越南版；越南公司用)(PE瓶) | J75: 海天牌海天上等蚝油(经典版)6KG*2 | K75: 251200 | N75: =L75+M75 -> 0 | O75: =IF(M75/N75>1/9,"大于8送1",IF(ABS(M75/N75-1/9)<0.0001,"8送1",IF(M75/N75<1/9,IF(M75/N75>1/10,"8送1和9送1之间",IF(ABS(M75/N75-1/10)<0.0001,"9送1",IF(M75/N75<1/10,IF(M75/N75>1/11,"9送1和10送1之间",IF(ABS(M75/N75-1/11)<0.0001,"10送1","小于10送1")))))))) -> #DIV/0! | P75: =K75*L75 -> 0 | Q75: =K75*M75 -> 0 | R75: =N75*K75 -> 0 | S75: 0.08 | T75: =P75*(1+$S75) -> 0 | U75: =Q75*(1+$S75) -> 0 | V75: =R75*(1+$S75) -> 0 | W75: ="海天牌"&F75 -> 海天牌海天上等蚝油（经典版） | X75: 6KG*2 | Y75: 12.90 | Z75: 12.00 | AA75: 0.366 | AB75: 0.187 | AC75: 0.282 | AD75: =(L75+M75)*Y75 -> 0 | AE75: =(L75+M75)*Z75 -> 0 | AF75: =ROUND((L75+M75)*AA75*AB75*AC75,2) -> 0 | AG75: 1440.00 | AH75: 2170.00 | AI75: =(L75+M75)/AG75 -> 0 | AJ75: =ROUNDDOWN(AI75/0.95,0) -> 0 | AK75: =(L75+M75)/AH75 -> 0 | AL75: 美加版：1440
A76: =IF(N76<>0,1,"") | C76: =IFERROR(RANK(A76,$A$12:$A$125,0)+COUNTIFS(A$12:A76,A76)-1,"") | D76: 89440100615 | E76: 越南文标签 | F76: 海天上等蚝油（经典版） | G76: HADAY SUPERIOR OYSTER SAUCE (CLASSIC VERSION) 6KG*2 | H76: HADAY DẦU HÀO THƯỢNG HẠNG (CLASSIC VERSION) 6KG*2 | I76: 出口海天牌海天上等蚝油(经典版)6KG*2(越南版；越南公司用；南宁生产)(PE瓶) | J76: 海天牌海天上等蚝油(经典版)6KG*2 | K76: 251200 | N76: =L76+M76 -> 0 | O76: =IF(M76/N76>1/9,"大于8送1",IF(ABS(M76/N76-1/9)<0.0001,"8送1",IF(M76/N76<1/9,IF(M76/N76>1/10,"8送1和9送1之间",IF(ABS(M76/N76-1/10)<0.0001,"9送1",IF(M76/N76<1/10,IF(M76/N76>1/11,"9送1和10送1之间",IF(ABS(M76/N76-1/11)<0.0001,"10送1","小于10送1")))))))) -> #DIV/0! | P76: =K76*L76 -> 0 | Q76: =K76*M76 -> 0 | R76: =N76*K76 -> 0 | S76: 0.08 | T76: =P76*(1+$S76) -> 0 | U76: =Q76*(1+$S76) -> 0 | V76: =R76*(1+$S76) -> 0 | W76: ="海天牌"&F76 -> 海天牌海天上等蚝油（经典版） | X76: 6KG*2 | Y76: 12.90 | Z76: 12.00 | AA76: 0.366 | AB76: 0.187 | AC76: 0.282 | AD76: =(L76+M76)*Y76 -> 0 | AE76: =(L76+M76)*Z76 -> 0 | AF76: =ROUND((L76+M76)*AA76*AB76*AC76,2) -> 0 | AG76: 1440.00 | AH76: 2170.00 | AI76: =(L76+M76)/AG76 -> 0 | AJ76: =ROUNDDOWN(AI76/0.95,0) -> 0 | AK76: =(L76+M76)/AH76 -> 0
A77: =IF(N77<>0,1,"") | C77: =IFERROR(RANK(A77,$A$12:$A$125,0)+COUNTIFS(A$12:A77,A77)-1,"") | D77: 89440100617 | E77: 中文标签 | F77: 海天上等蚝油（经典版） | G77: HADAY SUPERIOR OYSTER SAUCE (CLASSIC VERSION) 6KG*2 | H77: HADAY DẦU HÀO THƯỢNG HẠNG (CLASSIC VERSION) 6KG*2 | I77: 出口海天牌海天上等蚝油(经典版)6KG*2(越南公司用)(PE瓶) | J77: 海天牌海天上等蚝油(经典版)6KG*2 | K77: 251200 | N77: =L77+M77 -> 0 | O77: =IF(M77/N77>1/9,"大于8送1",IF(ABS(M77/N77-1/9)<0.0001,"8送1",IF(M77/N77<1/9,IF(M77/N77>1/10,"8送1和9送1之间",IF(ABS(M77/N77-1/10)<0.0001,"9送1",IF(M77/N77<1/10,IF(M77/N77>1/11,"9送1和10送1之间",IF(ABS(M77/N77-1/11)<0.0001,"10送1","小于10送1")))))))) -> #DIV/0! | P77: =K77*L77 -> 0 | Q77: =K77*M77 -> 0 | R77: =N77*K77 -> 0 | S77: 0.08 | T77: =P77*(1+$S77) -> 0 | U77: =Q77*(1+$S77) -> 0 | V77: =R77*(1+$S77) -> 0 | W77: ="海天牌"&F77 -> 海天牌海天上等蚝油（经典版） | X77: 6KG*2 | Y77: 12.90 | Z77: 12.00 | AA77: 0.366 | AB77: 0.187 | AC77: 0.282 | AD77: =(L77+M77)*Y77 -> 0 | AE77: =(L77+M77)*Z77 -> 0 | AF77: =ROUND((L77+M77)*AA77*AB77*AC77,2) -> 0 | AG77: 1440.00 | AH77: 2170.00 | AI77: =(L77+M77)/AG77 -> 0 | AJ77: =ROUNDDOWN(AI77/0.95,0) -> 0 | AK77: =(L77+M77)/AH77 -> 0
A78: =IF(N78<>0,1,"") | C78: =IFERROR(RANK(A78,$A$12:$A$125,0)+COUNTIFS(A$12:A78,A78)-1,"") | D78: 89440100616 | E78: 中文标签 | F78: 海天上等蚝油（经典版） | G78: HADAY SUPERIOR OYSTER SAUCE (CLASSIC VERSION) 6KG*2 | H78: HADAY DẦU HÀO THƯỢNG HẠNG (CLASSIC VERSION) 6KG*2 | I78: 出口海天牌海天上等蚝油(经典版)6KG*2(越南公司用；南宁生产)(PE瓶) | J78: 海天牌海天上等蚝油(经典版)6KG*2 | K78: 251200 | N78: =L78+M78 -> 0 | O78: =IF(M78/N78>1/9,"大于8送1",IF(ABS(M78/N78-1/9)<0.0001,"8送1",IF(M78/N78<1/9,IF(M78/N78>1/10,"8送1和9送1之间",IF(ABS(M78/N78-1/10)<0.0001,"9送1",IF(M78/N78<1/10,IF(M78/N78>1/11,"9送1和10送1之间",IF(ABS(M78/N78-1/11)<0.0001,"10送1","小于10送1")))))))) -> #DIV/0! | P78: =K78*L78 -> 0 | Q78: =K78*M78 -> 0 | R78: =N78*K78 -> 0 | S78: 0.08 | T78: =P78*(1+$S78) -> 0 | U78: =Q78*(1+$S78) -> 0 | V78: =R78*(1+$S78) -> 0 | W78: ="海天牌"&F78 -> 海天牌海天上等蚝油（经典版） | X78: 6KG*2 | Y78: 12.90 | Z78: 12.00 | AA78: 0.366 | AB78: 0.187 | AC78: 0.282 | AD78: =(L78+M78)*Y78 -> 0 | AE78: =(L78+M78)*Z78 -> 0 | AF78: =ROUND((L78+M78)*AA78*AB78*AC78,2) -> 0 | AG78: 1440.00 | AH78: 2170.00 | AI78: =(L78+M78)/AG78 -> 0 | AJ78: =ROUNDDOWN(AI78/0.95,0) -> 0 | AK78: =(L78+M78)/AH78 -> 0
A79: =IF(N79<>0,1,"") | B79: 海天金字装蚝油（经典版） | C79: =IFERROR(RANK(A79,$A$12:$A$125,0)+COUNTIFS(A$12:A79,A79)-1,"") | D79: 89440551507 | E79: 越南文标签 | F79: 海天金字装蚝油（经典版） | G79: HADAY GOLDEN SIGNATURE OYSTER SAUCE (CLASSIC VERSION) 515G*12 | H79: HADAY DẦU HÀO CHUẨN VỊ (CLASSIC VERSION) 515G*12 | I79: 出口海天牌海天金字装蚝油(经典版)515g*12(越南版；越南公司用)(玻璃瓶) | J79: 海天牌海天金字装蚝油(经典版)515G*12 | K79: 181400 | N79: =L79+M79 -> 0 | O79: =IF(M79/N79>1/9,"大于8送1",IF(ABS(M79/N79-1/9)<0.0001,"8送1",IF(M79/N79<1/9,IF(M79/N79>1/10,"8送1和9送1之间",IF(ABS(M79/N79-1/10)<0.0001,"9送1",IF(M79/N79<1/10,IF(M79/N79>1/11,"9送1和10送1之间",IF(ABS(M79/N79-1/11)<0.0001,"10送1","小于10送1")))))))) -> #DIV/0! | P79: =K79*L79 -> 0 | Q79: =K79*M79 -> 0 | R79: =N79*K79 -> 0 | S79: 0.08 | T79: =P79*(1+$S79) -> 0 | U79: =Q79*(1+$S79) -> 0 | V79: =R79*(1+$S79) -> 0 | W79: ="海天牌"&F79 -> 海天牌海天金字装蚝油（经典版） | X79: 515G*12 | Y79: 9.50 | Z79: 6.18 | AA79: 0.275 | AB79: 0.204 | AC79: 0.252 | AD79: =(L79+M79)*Y79 -> 0 | AE79: =(L79+M79)*Z79 -> 0 | AF79: =ROUND((L79+M79)*AA79*AB79*AC79,2) -> 0 | AG79: 2000.00 | AH79: 2950.00 | AI79: =(L79+M79)/AG79 -> 0 | AJ79: =ROUNDDOWN(AI79/0.95,0) -> 0 | AK79: =(L79+M79)/AH79 -> 0 | AL79: 非越南版：1780
A80: =IF(N80<>0,1,"") | C80: =IFERROR(RANK(A80,$A$12:$A$125,0)+COUNTIFS(A$12:A80,A80)-1,"") | D80: 89440551508 | E80: 越南文标签 | F80: 海天金字装蚝油（经典版） | G80: HADAY GOLDEN SIGNATURE OYSTER SAUCE (CLASSIC VERSION) 515G*12 | H80: HADAY DẦU HÀO CHUẨN VỊ (CLASSIC VERSION) 515G*12 | I80: 出口海天牌海天金字装蚝油(经典版)515g*12(越南版；越南公司用；南宁生产)(玻璃瓶) | J80: 海天牌海天金字装蚝油(经典版)515G*12 | K80: 181400 | N80: =L80+M80 -> 0 | O80: =IF(M80/N80>1/9,"大于8送1",IF(ABS(M80/N80-1/9)<0.0001,"8送1",IF(M80/N80<1/9,IF(M80/N80>1/10,"8送1和9送1之间",IF(ABS(M80/N80-1/10)<0.0001,"9送1",IF(M80/N80<1/10,IF(M80/N80>1/11,"9送1和10送1之间",IF(ABS(M80/N80-1/11)<0.0001,"10送1","小于10送1")))))))) -> #DIV/0! | P80: =K80*L80 -> 0 | Q80: =K80*M80 -> 0 | R80: =N80*K80 -> 0 | S80: 0.08 | T80: =P80*(1+$S80) -> 0 | U80: =Q80*(1+$S80) -> 0 | V80: =R80*(1+$S80) -> 0 | W80: ="海天牌"&F80 -> 海天牌海天金字装蚝油（经典版） | X80: 515G*12 | Y80: 9.50 | Z80: 6.18 | AA80: 0.275 | AB80: 0.204 | AC80: 0.252 | AD80: =(L80+M80)*Y80 -> 0 | AE80: =(L80+M80)*Z80 -> 0 | AF80: =ROUND((L80+M80)*AA80*AB80*AC80,2) -> 0 | AG80: 2000.00 | AH80: 2950.00 | AI80: =(L80+M80)/AG80 -> 0 | AJ80: =ROUNDDOWN(AI80/0.95,0) -> 0 | AK80: =(L80+M80)/AH80 -> 0
A81: =IF(N81<>0,1,"") | C81: =IFERROR(RANK(A81,$A$12:$A$125,0)+COUNTIFS(A$12:A81,A81)-1,"") | D81: 89440551509 | E81: 中文标签 | F81: 海天金字装蚝油（经典版） | G81: HADAY GOLDEN SIGNATURE OYSTER SAUCE (CLASSIC VERSION) 515G*12 | H81: HADAY DẦU HÀO CHUẨN VỊ (CLASSIC VERSION) 515G*12 | I81: 出口海天牌海天金字装蚝油(经典版)515g*12(越南公司用)(玻璃瓶) | J81: 海天牌海天金字装蚝油(经典版)515G*12 | K81: 181400 | N81: =L81+M81 -> 0 | O81: =IF(M81/N81>1/9,"大于8送1",IF(ABS(M81/N81-1/9)<0.0001,"8送1",IF(M81/N81<1/9,IF(M81/N81>1/10,"8送1和9送1之间",IF(ABS(M81/N81-1/10)<0.0001,"9送1",IF(M81/N81<1/10,IF(M81/N81>1/11,"9送1和10送1之间",IF(ABS(M81/N81-1/11)<0.0001,"10送1","小于10送1")))))))) -> #DIV/0! | P81: =K81*L81 -> 0 | Q81: =K81*M81 -> 0 | R81: =N81*K81 -> 0 | S81: 0.08 | T81: =P81*(1+$S81) -> 0 | U81: =Q81*(1+$S81) -> 0 | V81: =R81*(1+$S81) -> 0 | W81: ="海天牌"&F81 -> 海天牌海天金字装蚝油（经典版） | X81: 515G*12 | Y81: 9.50 | Z81: 6.18 | AA81: 0.275 | AB81: 0.204 | AC81: 0.252 | AD81: =(L81+M81)*Y81 -> 0 | AE81: =(L81+M81)*Z81 -> 0 | AF81: =ROUND((L81+M81)*AA81*AB81*AC81,2) -> 0 | AG81: 2000.00 | AH81: 2950.00 | AI81: =(L81+M81)/AG81 -> 0 | AJ81: =ROUNDDOWN(AI81/0.95,0) -> 0 | AK81: =(L81+M81)/AH81 -> 0
A82: =IF(N82<>0,1,"") | C82: =IFERROR(RANK(A82,$A$12:$A$125,0)+COUNTIFS(A$12:A82,A82)-1,"") | D82: 89440568007 | E82: 越南文标签 | F82: =F79 -> 海天金字装蚝油（经典版） | G82: HADAY GOLDEN SIGNATURE OYSTER SAUCE (CLASSIC VERSION) 680G*12 | H82: HADAY DẦU HÀO CHUẨN VỊ (CLASSIC VERSION) 680G*12 | I82: 出口海天牌海天金字装蚝油(经典版)680g*12(越南版；越南公司用)(玻璃瓶) | J82: 海天牌海天金字装蚝油(经典版)680G*12 | K82: 214900 | N82: =L82+M82 -> 0 | O82: =IF(M82/N82>1/9,"大于8送1",IF(ABS(M82/N82-1/9)<0.0001,"8送1",IF(M82/N82<1/9,IF(M82/N82>1/10,"8送1和9送1之间",IF(ABS(M82/N82-1/10)<0.0001,"9送1",IF(M82/N82<1/10,IF(M82/N82>1/11,"9送1和10送1之间",IF(ABS(M82/N82-1/11)<0.0001,"10送1","小于10送1")))))))) -> #DIV/0! | P82: =K82*L82 -> 0 | Q82: =K82*M82 -> 0 | R82: =N82*K82 -> 0 | S82: 0.08 | T82: =P82*(1+$S82) -> 0 | U82: =Q82*(1+$S82) -> 0 | V82: =R82*(1+$S82) -> 0 | W82: ="海天牌"&F82 -> 海天牌海天金字装蚝油（经典版） | X82: 680G*12 | Y82: 12.10 | Z82: 8.16 | AA82: 0.298 | AB82: 0.224 | AC82: 0.2775 | AD82: =(L82+M82)*Y82 -> 0 | AE82: =(L82+M82)*Z82 -> 0 | AF82: =ROUND((L82+M82)*AA82*AB82*AC82,2) -> 0 | AG82: 1430.00 | AH82: 2310.00 | AI82: =(L82+M82)/AG82 -> 0 | AJ82: =ROUNDDOWN(AI82/0.95,0) -> 0 | AK82: =(L82+M82)/AH82 -> 0 | AL82: 非越南版：1280
A83: =IF(N83<>0,1,"") | C83: =IFERROR(RANK(A83,$A$12:$A$125,0)+COUNTIFS(A$12:A83,A83)-1,"") | D83: 89440568008 | E83: 越南文标签 | F83: =F82 -> 海天金字装蚝油（经典版） | G83: HADAY GOLDEN SIGNATURE OYSTER SAUCE (CLASSIC VERSION) 680G*12 | H83: HADAY DẦU HÀO CHUẨN VỊ (CLASSIC VERSION) 680G*12 | I83: 出口海天牌海天金字装蚝油(经典版)680g*12(越南版；越南公司用；南宁生产)(玻璃瓶) | J83: 海天牌海天金字装蚝油(经典版)680G*12 | K83: 214900 | N83: =L83+M83 -> 0 | O83: =IF(M83/N83>1/9,"大于8送1",IF(ABS(M83/N83-1/9)<0.0001,"8送1",IF(M83/N83<1/9,IF(M83/N83>1/10,"8送1和9送1之间",IF(ABS(M83/N83-1/10)<0.0001,"9送1",IF(M83/N83<1/10,IF(M83/N83>1/11,"9送1和10送1之间",IF(ABS(M83/N83-1/11)<0.0001,"10送1","小于10送1")))))))) -> #DIV/0! | P83: =K83*L83 -> 0 | Q83: =K83*M83 -> 0 | R83: =N83*K83 -> 0 | S83: 0.08 | T83: =P83*(1+$S83) -> 0 | U83: =Q83*(1+$S83) -> 0 | V83: =R83*(1+$S83) -> 0 | W83: ="海天牌"&F83 -> 海天牌海天金字装蚝油（经典版） | X83: 680G*12 | Y83: 12.10 | Z83: 8.16 | AA83: 0.298 | AB83: 0.224 | AC83: 0.2775 | AD83: =(L83+M83)*Y83 -> 0 | AE83: =(L83+M83)*Z83 -> 0 | AF83: =ROUND((L83+M83)*AA83*AB83*AC83,2) -> 0 | AG83: 1430.00 | AH83: 2310.00 | AI83: =(L83+M83)/AG83 -> 0 | AJ83: =ROUNDDOWN(AI83/0.95,0) -> 0 | AK83: =(L83+M83)/AH83 -> 0
A84: =IF(N84<>0,1,"") | C84: =IFERROR(RANK(A84,$A$12:$A$125,0)+COUNTIFS(A$12:A84,A84)-1,"") | D84: 89440568009 | E84: 中文标签 | F84: =F82 -> 海天金字装蚝油（经典版） | G84: HADAY GOLDEN SIGNATURE OYSTER SAUCE (CLASSIC VERSION) 680G*12 | H84: HADAY DẦU HÀO CHUẨN VỊ (CLASSIC VERSION) 680G*12 | I84: 出口海天牌海天金字装蚝油(经典版)680g*12(越南公司用)(玻璃瓶) | J84: 海天牌海天金字装蚝油(经典版)680G*12 | K84: 214900 | N84: =L84+M84 -> 0 | O84: =IF(M84/N84>1/9,"大于8送1",IF(ABS(M84/N84-1/9)<0.0001,"8送1",IF(M84/N84<1/9,IF(M84/N84>1/10,"8送1和9送1之间",IF(ABS(M84/N84-1/10)<0.0001,"9送1",IF(M84/N84<1/10,IF(M84/N84>1/11,"9送1和10送1之间",IF(ABS(M84/N84-1/11)<0.0001,"10送1","小于10送1")))))))) -> #DIV/0! | P84: =K84*L84 -> 0 | Q84: =K84*M84 -> 0 | R84: =N84*K84 -> 0 | S84: 0.08 | T84: =P84*(1+$S84) -> 0 | U84: =Q84*(1+$S84) -> 0 | V84: =R84*(1+$S84) -> 0 | W84: ="海天牌"&F84 -> 海天牌海天金字装蚝油（经典版） | X84: 680G*12 | Y84: 12.10 | Z84: 8.16 | AA84: 0.298 | AB84: 0.224 | AC84: 0.2775 | AD84: =(L84+M84)*Y84 -> 0 | AE84: =(L84+M84)*Z84 -> 0 | AF84: =ROUND((L84+M84)*AA84*AB84*AC84,2) -> 0 | AG84: 1430.00 | AH84: 2310.00 | AI84: =(L84+M84)/AG84 -> 0 | AJ84: =ROUNDDOWN(AI84/0.95,0) -> 0 | AK84: =(L84+M84)/AH84 -> 0
A85: =IF(N85<>0,1,"") | C85: =IFERROR(RANK(A85,$A$12:$A$125,0)+COUNTIFS(A$12:A85,A85)-1,"") | D85: 89440522506 | E85: 越南文标签 | F85: =F82 -> 海天金字装蚝油（经典版） | G85: HADAY GOLDEN SIGNATURE OYSTER SAUCE (CLASSIC VERSION) 2.25KG*4 | H85: HADAY DẦU HÀO CHUẨN VỊ (CLASSIC VERSION) 2.25KG*4 | I85: 出口海天牌海天金字装蚝油(经典版)2.25KG*4(越南版；越南公司用)(PE瓶) | J85: 海天牌海天金字装蚝油(经典版)2.25KG*4 | K85: 178600 | N85: =L85+M85 -> 0 | O85: =IF(M85/N85>1/9,"大于8送1",IF(ABS(M85/N85-1/9)<0.0001,"8送1",IF(M85/N85<1/9,IF(M85/N85>1/10,"8送1和9送1之间",IF(ABS(M85/N85-1/10)<0.0001,"9送1",IF(M85/N85<1/10,IF(M85/N85>1/11,"9送1和10送1之间",IF(ABS(M85/N85-1/11)<0.0001,"10送1","小于10送1")))))))) -> #DIV/0! | P85: =K85*L85 -> 0 | Q85: =K85*M85 -> 0 | R85: =N85*K85 -> 0 | S85: 0.08 | T85: =P85*(1+$S85) -> 0 | U85: =Q85*(1+$S85) -> 0 | V85: =R85*(1+$S85) -> 0 | W85: ="海天牌"&F85 -> 海天牌海天金字装蚝油（经典版） | X85: 2.25KG*4 | Y85: 9.90 | Z85: 9.00 | AA85: 0.306 | AB85: 0.188 | AC85: 0.283 | AD85: =(L85+M85)*Y85 -> 0 | AE85: =(L85+M85)*Z85 -> 0 | AF85: =ROUND((L85+M85)*AA85*AB85*AC85,2) -> 0 | AG85: 1700.00 | AH85: 2830.00 | AI85: =(L85+M85)/AG85 -> 0 | AJ85: =ROUNDDOWN(AI85/0.95,0) -> 0 | AK85: =(L85+M85)/AH85 -> 0
A86: =IF(N86<>0,1,"") | C86: =IFERROR(RANK(A86,$A$12:$A$125,0)+COUNTIFS(A$12:A86,A86)-1,"") | D86: 89440522507 | E86: 越南文标签 | F86: =F84 -> 海天金字装蚝油（经典版） | G86: HADAY GOLDEN SIGNATURE OYSTER SAUCE (CLASSIC VERSION) 2.25KG*4 | H86: HADAY DẦU HÀO CHUẨN VỊ (CLASSIC VERSION) 2.25KG*4 | I86: 出口海天牌海天金字装蚝油(经典版)2.25KG*4(越南版；越南公司用；南宁生产)(PE瓶) | J86: 海天牌海天金字装蚝油(经典版)2.25KG*4 | K86: 178600 | N86: =L86+M86 -> 0 | O86: =IF(M86/N86>1/9,"大于8送1",IF(ABS(M86/N86-1/9)<0.0001,"8送1",IF(M86/N86<1/9,IF(M86/N86>1/10,"8送1和9送1之间",IF(ABS(M86/N86-1/10)<0.0001,"9送1",IF(M86/N86<1/10,IF(M86/N86>1/11,"9送1和10送1之间",IF(ABS(M86/N86-1/11)<0.0001,"10送1","小于10送1")))))))) -> #DIV/0! | P86: =K86*L86 -> 0 | Q86: =K86*M86 -> 0 | R86: =N86*K86 -> 0 | S86: 0.08 | T86: =P86*(1+$S86) -> 0 | U86: =Q86*(1+$S86) -> 0 | V86: =R86*(1+$S86) -> 0 | W86: ="海天牌"&F86 -> 海天牌海天金字装蚝油（经典版） | X86: 2.25KG*4 | Y86: 9.90 | Z86: 9.00 | AA86: 0.306 | AB86: 0.188 | AC86: 0.283 | AD86: =(L86+M86)*Y86 -> 0 | AE86: =(L86+M86)*Z86 -> 0 | AF86: =ROUND((L86+M86)*AA86*AB86*AC86,2) -> 0 | AG86: 1700.00 | AH86: 2830.00 | AI86: =(L86+M86)/AG86 -> 0 | AJ86: =ROUNDDOWN(AI86/0.95,0) -> 0 | AK86: =(L86+M86)/AH86 -> 0
A87: =IF(N87<>0,1,"") | C87: =IFERROR(RANK(A87,$A$12:$A$125,0)+COUNTIFS(A$12:A87,A87)-1,"") | D87: 89440522508 | E87: 中文标签 | F87: =F85 -> 海天金字装蚝油（经典版） | G87: HADAY GOLDEN SIGNATURE OYSTER SAUCE (CLASSIC VERSION) 2.25KG*4 | H87: HADAY DẦU HÀO CHUẨN VỊ (CLASSIC VERSION) 2.25KG*4 | I87: 出口海天牌海天金字装蚝油(经典版)2.25KG*4(越南公司用)(PE瓶) | J87: 海天牌海天金字装蚝油(经典版)2.25KG*4 | K87: 178600 | N87: =L87+M87 -> 0 | O87: =IF(M87/N87>1/9,"大于8送1",IF(ABS(M87/N87-1/9)<0.0001,"8送1",IF(M87/N87<1/9,IF(M87/N87>1/10,"8送1和9送1之间",IF(ABS(M87/N87-1/10)<0.0001,"9送1",IF(M87/N87<1/10,IF(M87/N87>1/11,"9送1和10送1之间",IF(ABS(M87/N87-1/11)<0.0001,"10送1","小于10送1")))))))) -> #DIV/0! | P87: =K87*L87 -> 0 | Q87: =K87*M87 -> 0 | R87: =N87*K87 -> 0 | S87: 0.08 | T87: =P87*(1+$S87) -> 0 | U87: =Q87*(1+$S87) -> 0 | V87: =R87*(1+$S87) -> 0 | W87: ="海天牌"&F87 -> 海天牌海天金字装蚝油（经典版） | X87: 2.25KG*4 | Y87: 9.90 | Z87: 9.00 | AA87: 0.306 | AB87: 0.188 | AC87: 0.283 | AD87: =(L87+M87)*Y87 -> 0 | AE87: =(L87+M87)*Z87 -> 0 | AF87: =ROUND((L87+M87)*AA87*AB87*AC87,2) -> 0 | AG87: 1700.00 | AH87: 2830.00 | AI87: =(L87+M87)/AG87 -> 0 | AJ87: =ROUNDDOWN(AI87/0.95,0) -> 0 | AK87: =(L87+M87)/AH87 -> 0
A88: =IF(N88<>0,1,"") | C88: =IFERROR(RANK(A88,$A$12:$A$125,0)+COUNTIFS(A$12:A88,A88)-1,"") | D88: 89401322501 | E88: 中文标签 | F88: =F87 -> 海天金字装蚝油（经典版） | G88: HADAY GOLDEN SIGNATURE OYSTER SAUCE (CLASSIC VERSION) 2.25KG*4 | H88: HADAY DẦU HÀO CHUẨN VỊ (CLASSIC VERSION) 2.25KG*4 | I88: 出口海天牌海天金字装蚝油(经典版)2.25KG*4(越南公司用；南宁生产)(PE瓶) | J88: 海天牌海天金字装蚝油(经典版)2.25kg*4 | K88: 178600 | N88: =L88+M88 -> 0 | O88: =IF(M88/N88>1/9,"大于8送1",IF(ABS(M88/N88-1/9)<0.0001,"8送1",IF(M88/N88<1/9,IF(M88/N88>1/10,"8送1和9送1之间",IF(ABS(M88/N88-1/10)<0.0001,"9送1",IF(M88/N88<1/10,IF(M88/N88>1/11,"9送1和10送1之间",IF(ABS(M88/N88-1/11)<0.0001,"10送1","小于10送1")))))))) -> #DIV/0! | P88: =K88*L88 -> 0 | Q88: =K88*M88 -> 0 | R88: =N88*K88 -> 0 | S88: 0.08 | T88: =P88*(1+$S88) -> 0 | U88: =Q88*(1+$S88) -> 0 | V88: =R88*(1+$S88) -> 0 | W88: ="海天牌"&F88 -> 海天牌海天金字装蚝油（经典版） | X88: 2.25KG*4 | Y88: 9.90 | Z88: 9.00 | AA88: 0.306 | AB88: 0.188 | AC88: 0.283 | AD88: =(L88+M88)*Y88 -> 0 | AE88: =(L88+M88)*Z88 -> 0 | AF88: =ROUND((L88+M88)*AA88*AB88*AC88,2) -> 0 | AG88: 1700.00 | AH88: 2830.00 | AI88: =(L88+M88)/AG88 -> 0 | AJ88: =ROUNDDOWN(AI88/0.95,0) -> 0 | AK88: =(L88+M88)/AH88 -> 0
A89: =IF(N89<>0,1,"") | C89: =IFERROR(RANK(A89,$A$12:$A$125,0)+COUNTIFS(A$12:A89,A89)-1,"") | D89: 89440500606 | E89: 越南文标签 | F89: =F87 -> 海天金字装蚝油（经典版） | G89: HADAY GOLDEN SIGNATURE OYSTER SAUCE (CLASSIC VERSION) 6KG*2 | H89: HADAY DẦU HÀO CHUẨN VỊ (CLASSIC VERSION) 6KG*2 | I89: 出口海天牌海天金字装蚝油(经典版)6KG*2(越南版；越南公司用)(PE瓶) | J89: 海天牌海天金字装蚝油(经典版)6KG*2 | K89: 212100 | N89: =L89+M89 -> 0 | O89: =IF(M89/N89>1/9,"大于8送1",IF(ABS(M89/N89-1/9)<0.0001,"8送1",IF(M89/N89<1/9,IF(M89/N89>1/10,"8送1和9送1之间",IF(ABS(M89/N89-1/10)<0.0001,"9送1",IF(M89/N89<1/10,IF(M89/N89>1/11,"9送1和10送1之间",IF(ABS(M89/N89-1/11)<0.0001,"10送1","小于10送1")))))))) -> #DIV/0! | P89: =K89*L89 -> 0 | Q89: =K89*M89 -> 0 | R89: =N89*K89 -> 0 | S89: 0.08 | T89: =P89*(1+$S89) -> 0 | U89: =Q89*(1+$S89) -> 0 | V89: =R89*(1+$S89) -> 0 | W89: ="海天牌"&F89 -> 海天牌海天金字装蚝油（经典版） | X89: 6KG*2 | Y89: 12.90 | Z89: 12.00 | AA89: 0.366 | AB89: 0.187 | AC89: 0.282 | AD89: =(L89+M89)*Y89 -> 0 | AE89: =(L89+M89)*Z89 -> 0 | AF89: =ROUND((L89+M89)*AA89*AB89*AC89,2) -> 0 | AG89: 1440.00 | AH89: 2170.00 | AI89: =(L89+M89)/AG89 -> 0 | AJ89: =ROUNDDOWN(AI89/0.95,0) -> 0 | AK89: =(L89+M89)/AH89 -> 0
A90: =IF(N90<>0,1,"") | C90: =IFERROR(RANK(A90,$A$12:$A$125,0)+COUNTIFS(A$12:A90,A90)-1,"") | D90: 89440500607 | E90: 越南文标签 | F90: =F88 -> 海天金字装蚝油（经典版） | G90: HADAY GOLDEN SIGNATURE OYSTER SAUCE (CLASSIC VERSION) 6KG*2 | H90: HADAY DẦU HÀO CHUẨN VỊ (CLASSIC VERSION) 6KG*2 | I90: 出口海天牌海天金字装蚝油(经典版)6KG*2(越南版；越南公司用；南宁生产)(PE瓶) | J90: 海天牌海天金字装蚝油(经典版)6KG*2 | K90: 212100 | N90: =L90+M90 -> 0 | O90: =IF(M90/N90>1/9,"大于8送1",IF(ABS(M90/N90-1/9)<0.0001,"8送1",IF(M90/N90<1/9,IF(M90/N90>1/10,"8送1和9送1之间",IF(ABS(M90/N90-1/10)<0.0001,"9送1",IF(M90/N90<1/10,IF(M90/N90>1/11,"9送1和10送1之间",IF(ABS(M90/N90-1/11)<0.0001,"10送1","小于10送1")))))))) -> #DIV/0! | P90: =K90*L90 -> 0 | Q90: =K90*M90 -> 0 | R90: =N90*K90 -> 0 | S90: 0.08 | T90: =P90*(1+$S90) -> 0 | U90: =Q90*(1+$S90) -> 0 | V90: =R90*(1+$S90) -> 0 | W90: ="海天牌"&F90 -> 海天牌海天金字装蚝油（经典版） | X90: 6KG*2 | Y90: 12.90 | Z90: 12.00 | AA90: 0.366 | AB90: 0.187 | AC90: 0.282 | AD90: =(L90+M90)*Y90 -> 0 | AE90: =(L90+M90)*Z90 -> 0 | AF90: =ROUND((L90+M90)*AA90*AB90*AC90,2) -> 0 | AG90: 1440.00 | AH90: 2170.00 | AI90: =(L90+M90)/AG90 -> 0 | AJ90: =ROUNDDOWN(AI90/0.95,0) -> 0 | AK90: =(L90+M90)/AH90 -> 0
A91: =IF(N91<>0,1,"") | C91: =IFERROR(RANK(A91,$A$12:$A$125,0)+COUNTIFS(A$12:A91,A91)-1,"") | D91: 89401300601 | E91: 中文标签 | F91: =F88 -> 海天金字装蚝油（经典版） | G91: HADAY GOLDEN SIGNATURE OYSTER SAUCE (CLASSIC VERSION) 6KG*2 | H91: HADAY DẦU HÀO CHUẨN VỊ (CLASSIC VERSION) 6KG*2 | I91: 出口海天牌海天金字装蚝油(经典版)6KG*2(越南公司用；南宁生产)(PE瓶) | J91: 海天牌海天金字装蚝油(经典版)6KG*2 | K91: 212100 | N91: =L91+M91 -> 0 | O91: =IF(M91/N91>1/9,"大于8送1",IF(ABS(M91/N91-1/9)<0.0001,"8送1",IF(M91/N91<1/9,IF(M91/N91>1/10,"8送1和9送1之间",IF(ABS(M91/N91-1/10)<0.0001,"9送1",IF(M91/N91<1/10,IF(M91/N91>1/11,"9送1和10送1之间",IF(ABS(M91/N91-1/11)<0.0001,"10送1","小于10送1")))))))) -> #DIV/0! | P91: =K91*L91 -> 0 | Q91: =K91*M91 -> 0 | R91: =N91*K91 -> 0 | S91: 0.08 | T91: =P91*(1+$S91) -> 0 | U91: =Q91*(1+$S91) -> 0 | V91: =R91*(1+$S91) -> 0 | W91: ="海天牌"&F91 -> 海天牌海天金字装蚝油（经典版） | X91: 6KG*2 | Y91: 12.90 | Z91: 12.00 | AA91: 0.366 | AB91: 0.187 | AC91: 0.282 | AD91: =(L91+M91)*Y91 -> 0 | AE91: =(L91+M91)*Z91 -> 0 | AF91: =ROUND((L91+M91)*AA91*AB91*AC91,2) -> 0 | AG91: 1440.00 | AH91: 2170.00 | AI91: =(L91+M91)/AG91 -> 0 | AJ91: =ROUNDDOWN(AI91/0.95,0) -> 0 | AK91: =(L91+M91)/AH91 -> 0
A92: =IF(N92<>0,1,"") | C92: =IFERROR(RANK(A92,$A$12:$A$125,0)+COUNTIFS(A$12:A92,A92)-1,"") | D92: 89440500608 | E92: 中文标签 | F92: =F89 -> 海天金字装蚝油（经典版） | G92: HADAY GOLDEN SIGNATURE OYSTER SAUCE (CLASSIC VERSION) 6KG*2 | H92: HADAY DẦU HÀO CHUẨN VỊ (CLASSIC VERSION) 6KG*2 | I92: 出口海天牌海天金字装蚝油(经典版)6KG*2(越南公司用)(PE瓶) | J92: 海天牌海天金字装蚝油(经典版)6KG*2 | K92: 212100 | N92: =L92+M92 -> 0 | O92: =IF(M92/N92>1/9,"大于8送1",IF(ABS(M92/N92-1/9)<0.0001,"8送1",IF(M92/N92<1/9,IF(M92/N92>1/10,"8送1和9送1之间",IF(ABS(M92/N92-1/10)<0.0001,"9送1",IF(M92/N92<1/10,IF(M92/N92>1/11,"9送1和10送1之间",IF(ABS(M92/N92-1/11)<0.0001,"10送1","小于10送1")))))))) -> #DIV/0! | P92: =K92*L92 -> 0 | Q92: =K92*M92 -> 0 | R92: =N92*K92 -> 0 | S92: 0.08 | T92: =P92*(1+$S92) -> 0 | U92: =Q92*(1+$S92) -> 0 | V92: =R92*(1+$S92) -> 0 | W92: ="海天牌"&F92 -> 海天牌海天金字装蚝油（经典版） | X92: 6KG*2 | Y92: 12.90 | Z92: 12.00 | AA92: 0.366 | AB92: 0.187 | AC92: 0.282 | AD92: =(L92+M92)*Y92 -> 0 | AE92: =(L92+M92)*Z92 -> 0 | AF92: =ROUND((L92+M92)*AA92*AB92*AC92,2) -> 0 | AG92: 1440.00 | AH92: 2170.00 | AI92: =(L92+M92)/AG92 -> 0 | AJ92: =ROUNDDOWN(AI92/0.95,0) -> 0 | AK92: =(L92+M92)/AH92 -> 0
A93: =IF(N93<>0,1,"") | B93: 海天香菇素食蚝油 | C93: =IFERROR(RANK(A93,$A$12:$A$125,0)+COUNTIFS(A$12:A93,A93)-1,"") | D93: 89403863505 | E93: 越南文标签 | F93: 海天香菇素食蚝油 | G93: SHIITAKE MUSHROOM VEGETARIAN OYSTER FLAVOURED SAUCE 635G*9 | H93: DẦU HÀO CHAY NẤM HƯƠNG 635G*9 | I93: 出口海天牌香菇素食蚝油635g*9(越南版；越南公司用)(PET挤挤瓶) | J93: 出口海天牌香菇素食蚝油635g*9 | K93: 250000 | N93: =L93+M93 -> 0 | O93: =IF(M93/N93>1/9,"大于8送1",IF(ABS(M93/N93-1/9)<0.0001,"8送1",IF(M93/N93<1/9,IF(M93/N93>1/10,"8送1和9送1之间",IF(ABS(M93/N93-1/10)<0.0001,"9送1",IF(M93/N93<1/10,IF(M93/N93>1/11,"9送1和10送1之间",IF(ABS(M93/N93-1/11)<0.0001,"10送1","小于10送1")))))))) -> #DIV/0! | P93: =K93*L93 -> 0 | Q93: =K93*M93 -> 0 | R93: =N93*K93 -> 0 | S93: 0.08 | T93: =P93*(1+$S93) -> 0 | U93: =Q93*(1+$S93) -> 0 | V93: =R93*(1+$S93) -> 0 | W93: ="海天牌"&F93 -> 海天牌海天香菇素食蚝油 | X93: 635g*9 | Y93: 6.4 | Z93: 5.72 | AA93: 0.252 | AB93: 0.18 | AC93: 0.23 | AD93: =(L93+M93)*Y93 -> 0 | AE93: =(L93+M93)*Z93 -> 0 | AF93: =ROUND((L93+M93)*AA93*AB93*AC93,2) -> 0 | AG93: 2700.00 | AH93: 4380.00 | AI93: =(L93+M93)/AG93 -> 0 | AJ93: =ROUNDDOWN(AI93/0.95,0) -> 0 | AK93: =(L93+M93)/AH93 -> 0
A94: =IF(N94<>0,1,"") | B94: 叉烧酱 | C94: =IFERROR(RANK(A94,$A$12:$A$125,0)+COUNTIFS(A$12:A94,A94)-1,"") | D94: 89501928001 | E94: 中文标签 | F94: 海天叉烧酱 | G94: HADAY CHAR SIU SAUCE 280G*15 | H94: HADAY XỐT ƯỚP XÁ XÍU 280G*15 | I94: 出口海天牌叉烧酱280g*15(越南版；越南公司用)(玻璃瓶) | J94: 海天牌叉烧酱280G*15 | K94: 308000 | N94: =L94+M94 -> 0 | O94: =IF(M94/N94>1/9,"大于8送1",IF(ABS(M94/N94-1/9)<0.0001,"8送1",IF(M94/N94<1/9,IF(M94/N94>1/10,"8送1和9送1之间",IF(ABS(M94/N94-1/10)<0.0001,"9送1",IF(M94/N94<1/10,IF(M94/N94>1/11,"9送1和10送1之间",IF(ABS(M94/N94-1/11)<0.0001,"10送1","小于10送1")))))))) -> #DIV/0! | P94: =K94*L94 -> 0 | Q94: =K94*M94 -> 0 | R94: =N94*K94 -> 0 | S94: 0.08 | T94: =P94*(1+$S94) -> 0 | U94: =Q94*(1+$S94) -> 0 | V94: =R94*(1+$S94) -> 0 | W94: ="海天牌"&F94 -> 海天牌海天叉烧酱 | X94: 280G*15 | Y94: 6.80 | Z94: 4.20 | AA94: 0.37 | AB94: 0.223 | AC94: 0.122 | AD94: =(L94+M94)*Y94 -> 0 | AE94: =(L94+M94)*Z94 -> 0 | AF94: =ROUND((L94+M94)*AA94*AB94*AC94,2) -> 0 | AG94: 2700.00 | AH94: 4000.00 | AI94: =(L94+M94)/AG94 -> 0 | AJ94: =ROUNDDOWN(AI94/0.95,0) -> 0 | AK94: =(L94+M94)/AH94 -> 0
A95: =IF(N95<>0,1,"") | C95: =IFERROR(RANK(A95,$A$12:$A$125,0)+COUNTIFS(A$12:A95,A95)-1,"") | D95: 89501970501 | E95: 中文标签 | F95: 海天叉烧酱 | G95: HADAY CHAR SIU SAUCE 7.5KG*2 | H95: HADAY XỐT ƯỚP XÁ XÍU 7.5KG*2 | I95: 出口海天牌叉烧酱7.5KG*2(越南版；越南公司用)(PE瓶) | J95: 海天牌叉烧酱7.5KG*2 | K95: 563500 | N95: =L95+M95 -> 0 | O95: =IF(M95/N95>1/9,"大于8送1",IF(ABS(M95/N95-1/9)<0.0001,"8送1",IF(M95/N95<1/9,IF(M95/N95>1/10,"8送1和9送1之间",IF(ABS(M95/N95-1/10)<0.0001,"9送1",IF(M95/N95<1/10,IF(M95/N95>1/11,"9送1和10送1之间",IF(ABS(M95/N95-1/11)<0.0001,"10送1","小于10送1")))))))) -> #DIV/0! | P95: =K95*L95 -> 0 | Q95: =K95*M95 -> 0 | R95: =N95*K95 -> 0 | S95: 0.08 | T95: =P95*(1+$S95) -> 0 | U95: =Q95*(1+$S95) -> 0 | V95: =R95*(1+$S95) -> 0 | W95: ="海天牌"&F95 -> 海天牌海天叉烧酱 | X95: 7.5KG*2 | Y95: 16.00 | Z95: 15.00 | AA95: 0.369 | AB95: 0.191 | AC95: 0.292 | AD95: =(L95+M95)*Y95 -> 0 | AE95: =(L95+M95)*Z95 -> 0 | AF95: =ROUND((L95+M95)*AA95*AB95*AC95,2) -> 0 | AG95: 1260.00 | AH95: 1750.00 | AI95: =(L95+M95)/AG95 -> 0 | AJ95: =ROUNDDOWN(AI95/0.95,0) -> 0 | AK95: =(L95+M95)/AH95 -> 0
A96: =IF(N96<>0,1,"") | B96: 柱候酱 | C96: =IFERROR(RANK(A96,$A$12:$A$125,0)+COUNTIFS(A$12:A96,A96)-1,"") | D96: 89500325503 | E96: 中文标签 | F96: 海天柱候酱 | G96: CHU HOU PASTE 255G*15 | H96: TƯƠNG TRỤ HẦU 255G*15 | I96: 出口海天牌柱侯酱255g*15(越南公司用)(玻璃瓶) | J96: 海天牌柱候酱255G*15 | K96: 0 | N96: =L96+M96 -> 0 | O96: =IF(M96/N96>1/9,"大于8送1",IF(ABS(M96/N96-1/9)<0.0001,"8送1",IF(M96/N96<1/9,IF(M96/N96>1/10,"8送1和9送1之间",IF(ABS(M96/N96-1/10)<0.0001,"9送1",IF(M96/N96<1/10,IF(M96/N96>1/11,"9送1和10送1之间",IF(ABS(M96/N96-1/11)<0.0001,"10送1","小于10送1")))))))) -> #DIV/0! | P96: =K96*L96 -> 0 | Q96: =K96*M96 -> 0 | R96: =N96*K96 -> 0 | S96: 0.08 | T96: =P96*(1+$S96) -> 0 | U96: =Q96*(1+$S96) -> 0 | V96: =R96*(1+$S96) -> 0 | W96: ="海天牌"&F96 -> 海天牌海天柱候酱 | X96: 255G*15 | Y96: 6.40 | Z96: 3.83 | AA96: 0.37 | AB96: 0.223 | AC96: 0.122 | AD96: =(L96+M96)*Y96 -> 0 | AE96: =(L96+M96)*Z96 -> 0 | AF96: =ROUND((L96+M96)*AA96*AB96*AC96,2) -> 0 | AG96: 2700.00 | AH96: 4380.00 | AI96: =(L96+M96)/AG96 -> 0 | AJ96: =ROUNDDOWN(AI96/0.95,0) -> 0 | AK96: =(L96+M96)/AH96 -> 0
A97: =IF(N97<>0,1,"") | C97: =IFERROR(RANK(A97,$A$12:$A$125,0)+COUNTIFS(A$12:A97,A97)-1,"") | D97: 89500360503 | E97: 中文标签 | F97: 海天柱候酱 | G97: CHU HOU PASTE 6.5KG*2 | H97: TƯƠNG TRỤ HẦU 6.5KG*2 | I97: 出口海天牌柱侯酱6.5KG*2(越南公司用)(PE瓶) | J97: 海天牌柱候酱6.5KG*2 | K97: 487000 | N97: =L97+M97 -> 0 | O97: =IF(M97/N97>1/9,"大于8送1",IF(ABS(M97/N97-1/9)<0.0001,"8送1",IF(M97/N97<1/9,IF(M97/N97>1/10,"8送1和9送1之间",IF(ABS(M97/N97-1/10)<0.0001,"9送1",IF(M97/N97<1/10,IF(M97/N97>1/11,"9送1和10送1之间",IF(ABS(M97/N97-1/11)<0.0001,"10送1","小于10送1")))))))) -> #DIV/0! | P97: =K97*L97 -> 0 | Q97: =K97*M97 -> 0 | R97: =N97*K97 -> 0 | S97: 0.08 | T97: =P97*(1+$S97) -> 0 | U97: =Q97*(1+$S97) -> 0 | V97: =R97*(1+$S97) -> 0 | W97: ="海天牌"&F97 -> 海天牌海天柱候酱 | X97: 6.5KG*2 | Y97: 14.00 | Z97: 13.00 | AA97: 0.369 | AB97: 0.191 | AC97: 0.292 | AD97: =(L97+M97)*Y97 -> 0 | AE97: =(L97+M97)*Z97 -> 0 | AF97: =ROUND((L97+M97)*AA97*AB97*AC97,2) -> 0 | AG97: 1260.00 | AH97: 2000.00 | AI97: =(L97+M97)/AG97 -> 0 | AJ97: =ROUNDDOWN(AI97/0.95,0) -> 0 | AK97: =(L97+M97)/AH97 -> 0
A98: =IF(N98<>0,1,"") | B98: 烤肉酱 | C98: =IFERROR(RANK(A98,$A$12:$A$125,0)+COUNTIFS(A$12:A98,A98)-1,"") | D98: 89501123001 | E98: 中文标签 | F98: 烤肉酱 | G98: HADAY GRILLED SAUCE 230G*15 | H98: HADAY NƯỚC XỐT THỊT NƯỚNG 230G*15 | I98: 出口海天牌烤肉酱230g*15(越南公司用)(玻璃瓶) | J98: 海天牌烤肉酱230g*15 | K98: 180000 | N98: =L98+M98 -> 0 | O98: =IF(M98/N98>1/9,"大于8送1",IF(ABS(M98/N98-1/9)<0.0001,"8送1",IF(M98/N98<1/9,IF(M98/N98>1/10,"8送1和9送1之间",IF(ABS(M98/N98-1/10)<0.0001,"9送1",IF(M98/N98<1/10,IF(M98/N98>1/11,"9送1和10送1之间",IF(ABS(M98/N98-1/11)<0.0001,"10送1","小于10送1")))))))) -> #DIV/0! | P98: =K98*L98 -> 0 | Q98: =K98*M98 -> 0 | R98: =N98*K98 -> 0 | S98: 0.08 | T98: =P98*(1+$S98) -> 0 | U98: =Q98*(1+$S98) -> 0 | V98: =R98*(1+$S98) -> 0 | W98: ="海天牌"&F98 -> 海天牌烤肉酱 | X98: 230G*15 | Y98: 6.00 | Z98: 3.45 | AA98: 0.367 | AB98: 0.224 | AC98: 0.109 | AD98: =(L98+M98)*Y98 -> 0 | AE98: =(L98+M98)*Z98 -> 0 | AF98: =ROUND((L98+M98)*AA98*AB98*AC98,2) -> 0 | AG98: 3000.00 | AH98: 4670.00 | AI98: =(L98+M98)/AG98 -> 0 | AJ98: =ROUNDDOWN(AI98/0.95,0) -> 0 | AK98: =(L98+M98)/AH98 -> 0
A99: =IF(N99<>0,1,"") | C99: =IFERROR(RANK(A99,$A$12:$A$125,0)+COUNTIFS(A$12:A99,A99)-1,"") | D99: 89501134001 | E99: 中文标签 | F99: =F98 -> 烤肉酱 | G99: HADAY GRILLED SAUCE 340G*15 | H99: HADAY NƯỚC XỐT THỊT NƯỚNG 340G*15 | I99: 出口海天牌烤肉酱340g*15(越南公司用)(玻璃瓶) | J99: 海天牌烤肉酱340g*15 | K99: 210000 | N99: =L99+M99 -> 0 | O99: =IF(M99/N99>1/9,"大于8送1",IF(ABS(M99/N99-1/9)<0.0001,"8送1",IF(M99/N99<1/9,IF(M99/N99>1/10,"8送1和9送1之间",IF(ABS(M99/N99-1/10)<0.0001,"9送1",IF(M99/N99<1/10,IF(M99/N99>1/11,"9送1和10送1之间",IF(ABS(M99/N99-1/11)<0.0001,"10送1","小于10送1")))))))) -> #DIV/0! | P99: =K99*L99 -> 0 | Q99: =K99*M99 -> 0 | R99: =N99*K99 -> 0 | S99: 0.08 | T99: =P99*(1+$S99) -> 0 | U99: =Q99*(1+$S99) -> 0 | V99: =R99*(1+$S99) -> 0 | W99: ="海天牌"&F99 -> 海天牌烤肉酱 | X99: 340G*15 | Y99: 8.50 | Z99: 5.10 | AA99: 0.367 | AB99: 0.224 | AC99: 0.149 | AD99: =(L99+M99)*Y99 -> 0 | AE99: =(L99+M99)*Z99 -> 0 | AF99: =ROUND((L99+M99)*AA99*AB99*AC99,2) -> 0 | AG99: 2150.00 | AH99: 3290.00 | AI99: =(L99+M99)/AG99 -> 0 | AJ99: =ROUNDDOWN(AI99/0.95,0) -> 0 | AK99: =(L99+M99)/AH99 -> 0
A100: =IF(N100<>0,1,"") | C100: =IFERROR(RANK(A100,$A$12:$A$125,0)+COUNTIFS(A$12:A100,A100)-1,"") | D100: 89501180001 | E100: 中文标签 | F100: =F99 -> 烤肉酱 | G100: HADAY GRILLED SAUCE 800G*6 | H100: HADAY NƯỚC XỐT THỊT NƯỚNG 800G*6 | I100: 出口海天牌烤肉酱800g*6(越南公司用)(玻璃瓶) | J100: 海天牌烤肉酱800g*6 | K100: 190000 | N100: =L100+M100 -> 0 | O100: =IF(M100/N100>1/9,"大于8送1",IF(ABS(M100/N100-1/9)<0.0001,"8送1",IF(M100/N100<1/9,IF(M100/N100>1/10,"8送1和9送1之间",IF(ABS(M100/N100-1/10)<0.0001,"9送1",IF(M100/N100<1/10,IF(M100/N100>1/11,"9送1和10送1之间",IF(ABS(M100/N100-1/11)<0.0001,"10送1","小于10送1")))))))) -> #DIV/0! | P100: =K100*L100 -> 0 | Q100: =K100*M100 -> 0 | R100: =N100*K100 -> 0 | S100: 0.08 | T100: =P100*(1+$S100) -> 0 | U100: =Q100*(1+$S100) -> 0 | V100: =R100*(1+$S100) -> 0 | W100: ="海天牌"&F100 -> 海天牌烤肉酱 | X100: 800G*6 | Y100: 7.20 | Z100: 4.80 | AA100: 0.3 | AB100: 0.205 | AC100: 0.18 | AD100: =(L100+M100)*Y100 -> 0 | AE100: =(L100+M100)*Z100 -> 0 | AF100: =ROUND((L100+M100)*AA100*AB100*AC100,2) -> 0 | AG100: 2370.00 | AH100: 3890.00 | AI100: =(L100+M100)/AG100 -> 0 | AJ100: =ROUNDDOWN(AI100/0.95,0) -> 0 | AK100: =(L100+M100)/AH100 -> 0
...

Sheet 客户地址信息汇总
A1: client_id | B1: client_name_ch | C1: id | D1: kh_id | E1: continent | F1: country | G1: province | H1: city | I1: destination | J1: company | K1: address | L1: phone | M1: email | N1: notice | O1: default_address | P1: create_by | Q1: create_time | R1: update_by | S1: update_time | T1: check_company | U1: check_company_address | V1: delivery_address_type | W1: destination_final | X1: trade_terms | Y1: deliver_warehouse | Z1: RDC仓
A2: 2141020020 | B2: 越南VP进出口贸易有限公司 | C2: 27 | D2: 337 | H2: Thanh Pho Ho Chi Minh | I2: CAT LAI PORT,HO CHI MINH-越南 | K2: 252/18P Phan Anh, Phường Phú Thạnh, Thành phố Hồ Chí Minh | L2: 0903003877 | N2: Anh Bân | O2: 1 | P2: admin | Q2: 2025-07-22 11:00:00 | R2: zhangh31 | S2: 2026-05-13 13:41:04 | V2: 4 | W2: CAT LAI PORT,HO CHI MINH-越南 | X2: CIF | Y2: =IF(Z2="北部","1",IF(Z2="南部","2","")) -> 2 | Z2: 南部
A3: 2141030020 | B3: 越南谅山龙霞一成员有限公司 | C3: 31 | D3: 343 | F3: Viet Nam | H3: Yen Vien | I3: YEN VIEN-越南 | K3: tổ 16 phường nùng chí cao tp cao bằng | L3: 0941960009 | N3: Ninh Văn Bình（高平） | O3: 0 | P3: admin | Q3: 2025-07-22 11:00:00 | R3: zhangh31 | S3: 2026-03-23 10:47:47 | V3: 4 | W3: YEN VIEN-越南 | X3: CIF | Y3: =IF(Z3="北部","1",IF(Z3="南部","2","")) -> 1 | Z3: 北部
A4: 2141030020 | B4: 越南谅山龙霞一成员有限公司 | C4: 32 | D4: 343 | F4: Viet Nam | H4: Yen Vien | I4: YEN VIEN-越南 | K4: phố cò . Sông công . Thái nguyên | L4: 0373133660 | N4: /（太原） | O4: 0 | P4: admin | Q4: 2025-07-22 11:00:00 | R4: zhangh31 | S4: 2026-03-23 10:47:47 | V4: 4 | W4: YEN VIEN-越南 | X4: CIF | Y4: =IF(Z4="北部","1",IF(Z4="南部","2","")) -> 1 | Z4: 北部
A5: 2141070020 | B5: 越南通达发一成员贸易服务有限公司 | C5: 166 | D5: 1712389292203786242 | H5: Thanh Pho Ho Chi Minh | I5: CAT LAI PORT,HO CHI MINH-越南 | K5: Cụm công nghiệp bảy mẫu Phường Tân Đông Hiệp, Thành phố Hồ Chí Minh | L5: 0379774123 | N5: Chị Kim | O5: 1 | P5: admin | Q5: 2025-07-22 11:00:00 | R5: zhangh31 | S5: 2026-05-13 13:45:15 | V5: 4 | W5: CAT LAI PORT,HO CHI MINH-越南 | X5: CIF | Y5: =IF(Z5="北部","1",IF(Z5="南部","2","")) -> 2 | Z5: 南部
A6: 2141020110 | B6: 越南黄天发贸易有限公司 | C6: 172 | D6: 1722956703705415681 | H6: Thanh Pho Ho Chi Minh | I6: CAT LAI PORT,HO CHI MINH-越南 | K6: 97/12 kinh dương vương p12 q6 | L6: 090 9853318 | N6: duy | O6: 0 | P6: admin | Q6: 2025-07-22 11:00:00 | R6: zhangh31 | S6: 2026-05-13 13:43:34 | V6: 4 | W6: CAT LAI PORT,HO CHI MINH-越南 | X6: CIF | Y6: =IF(Z6="北部","1",IF(Z6="南部","2","")) -> 2 | Z6: 南部
A7: 2141010070 | B7: 越南食品进出口服务贸易有限公司 | C7: 213 | D7: 1802266337481670657 | H7: Chi Ma | I7: YEN VIEN-越南 | K7: 1138 nguyễn khoái, Phường Hoàng Mai, Thành phố Hà Nội Việt Nam | L7: 0984968999 | N7: Anh Thành Tuấn Phương | O7: 1 | P7: admin | Q7: 2025-07-22 11:00:00 | R7: admin | S7: 2026-04-03 16:18:20 | V7: 4 | W7: YEN VIEN-越南 | X7: CIF | Y7: =IF(Z7="北部","1",IF(Z7="南部","2","")) -> 1 | Z7: 北部
A8: 2141020130 | B8: 越南智越发贸易服务及生产有限公司（工业） | C8: 221 | D8: 1814694555153154049 | H8: Thanh Pho Ho Chi Minh | I8: CAT LAI PORT,HO CHI MINH-越南 | K8: 178 Đường Long Thuận, Phường Long Phước, Thành phố Hồ Chí Minh | L8: 0977905020 | N8: Mr. Tân | O8: 1 | P8: admin | Q8: 2025-07-22 11:00:00 | R8: admin | S8: 2026-04-03 16:20:43 | V8: 4 | W8: CAT LAI PORT,HO CHI MINH-越南 | X8: CIF | Y8: =IF(Z8="北部","1",IF(Z8="南部","2","")) -> 1 | Z8: 北部
A9: 2141010080 | B9: 越南全德贸易投资有限公司 | C9: 223 | D9: 1815036820530741250 | H9: Friendship Pass | I9: YEN VIEN-越南 | K9: D06-NV4 ô 033, khu D, KĐT Gleximco - Lê Trọng Tấn, Xã An Khánh, Thành phố Hà Nội Việt Nam | L9: 0967260022 | N9: ĐỖ VĂN LƯƠNG | O9: 1 | P9: admin | Q9: 2025-07-22 11:00:00 | R9: admin | S9: 2026-04-03 16:22:26 | V9: 4 | W9: YEN VIEN-越南 | X9: CIF | Y9: =IF(Z9="北部","1",IF(Z9="南部","2","")) -> 1 | Z9: 北部
A10: 2141010090 | B10: 越南食品进出口服务贸易有限公司（工业） | C10: 233 | D10: 1827906661763596289 | H10: Thanh Pho Ho Chi Minh | I10: YEN VIEN-越南 | K10: Khu khả lễ, Phường Võ Cường, Tỉnh Bắc Ninh Việt Nam | L10: 0984968999 | N10: Anh Thành Tuấn Phương | O10: 1 | P10: admin | Q10: 2025-07-22 11:00:00 | R10: admin | S10: 2026-04-03 16:23:36 | V10: 4 | W10: YEN VIEN-越南 | X10: CIF | Y10: =IF(Z10="北部","1",IF(Z10="南部","2","")) -> 1 | Z10: 北部
A11: 2141020150 | B11: 越南诺萨食品股份公司（工业） | C11: 234 | D11: 1829111819826708481 | H11: Thanh Pho Ho Chi Minh | I11: CAT LAI PORT,HO CHI MINH-越南 | K11: Lô D3/1-4 đường VL7, KCN Vĩnh Lộc 2, Xã Mỹ Yên, Tỉnh Tây Ninh | O11: 1 | P11: admin | Q11: 2025-07-22 11:00:00 | R11: admin | S11: 2026-04-03 16:34:48 | V11: 4 | W11: CAT LAI PORT,HO CHI MINH-越南 | X11: CIF | Y11: =IF(Z11="北部","1",IF(Z11="南部","2","")) -> 1 | Z11: 北部
A12: 2141020140 | B12: 越南芳云进出口有限公司 | C12: 235 | D12: 1827911185878302721 | H12: Thanh Pho Ho Chi Minh | I12: CAT LAI PORT,HO CHI MINH-越南 | K12: 168 Quang Trung, Phường Bảy Hiền, Thành phố Hồ Chí Minh | L12: 0905586622 | N12: Bùi Thị Thu Hằng | O12: 1 | P12: admin | Q12: 2025-07-22 11:00:00 | R12: zhangh31 | S12: 2026-05-13 13:44:19 | V12: 4 | W12: CAT LAI PORT,HO CHI MINH-越南 | X12: CIF | Y12: =IF(Z12="北部","1",IF(Z12="南部","2","")) -> 2 | Z12: 南部
A13: 2141020160 | B13: 越南诺萨食品股份公司（OEM） | C13: 237 | D13: 1831555971633987585 | H13: Thanh Pho Ho Chi Minh | I13: CAT LAI PORT,HO CHI MINH-越南 | K13: Lô D3/1-4 đường VL7, KCN Vĩnh Lộc 2, Xã Mỹ Yên, Tỉnh Tây Ninh | O13: 1 | P13: admin | Q13: 2025-07-22 11:00:00 | R13: admin | S13: 2026-04-03 16:25:15 | V13: 4 | W13: CAT LAI PORT,HO CHI MINH-越南 | X13: CIF | Y13: =IF(Z13="北部","1",IF(Z13="南部","2","")) -> 1 | Z13: 北部
A14: 2141010100 | B14: 越南安库生产贸易和服务有限公司（工业） | C14: 247 | D14: 1848643578368966657 | H14: Thanh Pho Ho Chi Minh | I14: HAIPHONG-越南 | K14: Số 374A đường Hùng Vương, Phường Hồng Bàng, Thành phố Hải Phòng | L14: 0869813026 | O14: 1 | P14: admin | Q14: 2025-07-22 11:00:00 | R14: admin | S14: 2026-04-03 16:35:46 | V14: 4 | W14: HAIPHONG-越南 | X14: CIF | Y14: =IF(Z14="北部","1",IF(Z14="南部","2","")) -> 1 | Z14: 北部
A15: 2141110020 | B15: 越南惠嘉进出口有限公司 | C15: 267 | D15: 1869970867165675521 | H15: Yen Vien | I15: YEN VIEN-越南 | K15: Khu 7 xã Hy Cương -Tỉnh Phú Thọ | L15: 0972017465 | N15: Hoàng Anh（富寿） | O15: 1 | P15: admin | Q15: 2025-07-22 11:00:00 | R15: admin | S15: 2026-04-03 16:47:56 | V15: 4 | W15: YEN VIEN-越南 | X15: CIF | Y15: =IF(Z15="北部","1",IF(Z15="南部","2","")) -> 1 | Z15: 北部
A16: 2141030060 | B16: 越南荷青综合贸易有限公司 | C16: 285 | D16: 1891749549555138562 | H16: Yen Vien | I16: YEN VIEN-越南 | K16: Số 164, đường Hoàng Văn Thụ, khu Lò Rèn, Xã Đồng Đăng, Lạng Sơn | L16: 0352139888 | O16: 1 | P16: admin | Q16: 2025-07-22 11:00:00 | R16: admin | S16: 2026-04-03 16:42:00 | V16: 4 | W16: YEN VIEN-越南 | X16: CIF | Y16: =IF(Z16="北部","1",IF(Z16="南部","2","")) -> 1 | Z16: 北部
A17: 2141120010 | B17: 越南KEKI股份有限公司（工业） | C17: 298 | D17: 1899120340106035201 | H17: Thanh Pho Ho Chi Minh | I17: HAIPHONG-越南 | K17: Thửa đất số 1488, tờ bản đồ số 09, Xã Thanh Miện, Thành phố Hải Phòng | O17: 1 | P17: admin | Q17: 2025-07-22 11:00:00 | R17: admin | S17: 2026-04-03 16:37:54 | V17: 4 | W17: HAIPHONG-越南 | X17: CIF | Y17: =IF(Z17="北部","1",IF(Z17="南部","2","")) -> 1 | Z17: 北部
A18: 2141120020 | B18: 越南海阳安军一成员责任有限公司 | C18: 326 | D18: 1914275489241710593 | F18: Viet Nam | H18: Yen Vien | I18: YEN VIEN-越南 | K18: Số nhà 13/75 Bùi Thị Xuân, Phường Lê Thanh Nghị, TP Hải Phòng Việt Nam | O18: 1 | P18: admin | Q18: 2025-07-22 11:00:00 | R18: zhangh31 | S18: 2026-04-02 08:13:30 | V18: 4 | W18: YEN VIEN-越南 | X18: CIF | Y18: =IF(Z18="北部","1",IF(Z18="南部","2","")) -> 1 | Z18: 北部
A19: 2141130010 | B19: 越南流行水族有限公司 | C19: 360 | D19: 1937147493145722882 | F19: Viet Nam | H19: Yen Vien | I19: YEN VIEN-越南 | K19: Số nhà 17, tổ dân phố số 3, phường Mỹ Độ, thành phố Bắc Giang, tỉnh Bắc Giang | L19: 0326296668 | N19: CÔNG TY TNHH POP AQUA | O19: 1 | P19: admin | Q19: 2025-07-22 11:00:00 | R19: dongqq | S19: 2026-05-19 18:14:55 | V19: 4 | W19: YEN VIEN-越南 | X19: CIF | Y19: =IF(Z19="北部","1",IF(Z19="南部","2","")) -> 1 | Z19: 北部
A20: 2141020190 | B20: 越南亚洲化学股份有限公司（工业） | C20: 365 | D20: 1937178454658990081 | H20: Thanh Pho Ho Chi Minh | I20: CAT LAI PORT,HO CHI MINH-越南 | K20: Lô K4B khu công nghiệp Lê Minh Xuân, Đường Số 4, Xã Bình Lợi, Thành phố Hồ Chí Minh | L20: 0938939817 | N20: Anh Nhân - Thủ kho | O20: 1 | P20: admin | Q20: 2025-07-22 11:00:00 | R20: admin | S20: 2026-04-03 16:39:50 | V20: 4 | W20: CAT LAI PORT,HO CHI MINH-越南 | X20: CIF | Y20: =IF(Z20="北部","1",IF(Z20="南部","2","")) -> 1 | Z20: 北部
A21: 2141010120 | B21: 越南美越食品供应有限公司 | C21: 629 | D21: 1947215916886212610 | H21: Thanh Pho Ho Chi Minh | I21: CAT LAI PORT,HO CHI MINH-越南 | K21: No. 168, Ha Huy Tap Street, Tan Hung Ward, Ho Chi Minh City, Vietnam. | L21: +84 0931452183 | N21: THOMAS LUO | O21: 1 | P21: luoqf | Q21: 2025-07-21 17:00:57 | R21: zhangh31 | S21: 2026-05-13 13:40:41 | V21: 4 | W21: CAT LAI PORT,HO CHI MINH-越南 | X21: CIF | Y21: =IF(Z21="北部","1",IF(Z21="南部","2","")) -> 2 | Z21: 南部
A22: 2141010130 | B22: 越南山水发商贸服务股份公司 | C22: 676 | D22: 1958192450996355074 | H22: Yen Vien | I22: YEN VIEN-越南 | K22: Ngách 87 ngõ 56 phố thạch cầu phường Long biên hà nội. | L22: 0912961292 | N22: chị Thuý | O22: 1 | P22: luoqf | Q22: 2025-08-20 23:56:26 | R22: admin | S22: 2026-04-03 16:47:14 | V22: 3 | W22: YEN VIEN-越南 | X22: CIF | Y22: =IF(Z22="北部","1",IF(Z22="南部","2","")) -> 1 | Z22: 北部
A23: 2141140010 | B23: 越南​​秋香贸易经营有限责任公司​ | C23: 677 | D23: 1958371479359668225 | H23: Yen Vien | I23: YEN VIEN-越南 | K23: 116 phan đình phùng, phường trần hưng đạo, Nam Định | L23: +84 91 3344477 | N23: chị Hương | O23: 1 | P23: luoqf | Q23: 2025-08-21 11:48:46 | R23: zhangh31 | S23: 2026-05-28 15:11:10 | V23: 3 | W23: YEN VIEN-越南 | X23: CIF | Y23: =IF(Z23="北部","1",IF(Z23="南部","2","")) -> 1 | Z23: 北部
A24: 2141150010 | B24: 越南味丹股份有限公司(OEM) | C24: 746 | D24: 1982694991293399041 | F24: Viet Nam | H24: Thanh Pho Ho Chi Minh | I24: CAT LAI PORT,HO CHI MINH-越南 | K24: 26C Quốc lộ 91B, KV Bình Chánh, Phường Long Tuyền, Thành phố Cần Thơ | L24: 0789833800 | N24: MR NAM | O24: 1 | P24: luoqf | Q24: 2025-10-27 15:54:12 | R24: zhangh31 | S24: 2026-03-25 14:30:56 | V24: 4 | W24: CAT LAI PORT,HO CHI MINH-越南 | X24: CIF | Y24: =IF(Z24="北部","1",IF(Z24="南部","2","")) -> 1 | Z24: 北部
A25: 2141170010 | B25: 越南宝芳林有限责任公司 | C25: 785 | D25: 1997607182266089473 | H25: Yen Vien | I25: YEN VIEN-越南 | K25: Số 6 ngõ 56 đường Kim Quan Thượng, Việt Hưng, Long Biên, Hà Nội | L25: 0903231681/0966295689 | N25: Huynh/Tú Anh（龙边） | O25: 1 | P25: luoqf | Q25: 2025-12-07 18:11:55 | R25: admin | S25: 2026-04-03 16:48:43 | V25: 3 | W25: YEN VIEN-越南 | X25: CIF | Y25: =IF(Z25="北部","1",IF(Z25="南部","2","")) -> 1 | Z25: 北部
A26: 2141160010 | B26: 越南泰东兴有限公司 | C26: 786 | D26: 1997665787883372546 | H26: Da Nang | I26: DA NANG-越南 | K26: 172-178 Bùi Tấn Diên, phường Hòa Khánh, thành phố Đà Nẵng, Việt Nam | L26: 0932159830 | N26: Dinh Ngoc Dinh | O26: 1 | P26: luoqf | Q26: 2025-12-07 22:39:12 | R26: admin | S26: 2026-04-03 16:43:52 | V26: 3 | W26: DA NANG-越南 | X26: CIF | Y26: =IF(Z26="北部","1",IF(Z26="南部","2","")) -> 1 | Z26: 北部
A27: 2141020200 | B27: 越南国宴云厨房有限公司（工业） | C27: 787 | D27: 1997716887458103297 | F27: Viet Nam | H27: Thanh Pho Ho Chi Minh | I27: CAT LAI PORT,HO CHI MINH-越南 | K27: 3SB1-12 Duong so 20, Khu pho My Vien, Khu do thi Phu My Hung, Phuong Tan My, Thanh pho Ho Chi Minh, Vietnam | L27: 0888058989 | N27: LY TRUONG HUY | O27: 1 | P27: luoqf | Q27: 2025-12-08 11:10:17 | R27: luohj4 | S27: 2025-12-22 09:00:28 | V27: 3 | W27: CAT LAI PORT,HO CHI MINH-越南 | X27: CIF | Y27: =IF(Z27="北部","1",IF(Z27="南部","2","")) -> 1 | Z27: 北部
A28: 2141020240 | B28: 越南陈日儿有限公司 | C28: 850 | D28: 2011693875696844802 | H28: Thanh Pho Ho Chi Minh | I28: CAT LAI PORT,HO CHI MINH-越南 | K28: Rosa Vạn Đạt Lô2/1 KCN Tân Bình đường Cn1 phường Tây Thạnh quận Tân Phú | L28: 0708518166 | N28: Ánh Tuyết | O28: 1 | P28: zhujj3 | Q28: 2026-01-15 14:56:10 | R28: zhangh31 | S28: 2026-05-13 13:44:40 | V28: 4 | W28: CAT LAI PORT,HO CHI MINH-越南 | X28: CIF | Y28: =IF(Z28="北部","1",IF(Z28="南部","2","")) -> 2 | Z28: 南部
A29: 2141180010 | B29: 越南-安平发添加剂公司（食品工业） | C29: 940 | D29: 2037451724620120066 | F29: Viet Nam | H29: Haiphong | I29: HAIPHONG-越南 | K29: Số 72 đường Hồng Tiến, Bồ đề, Long Biên, Hà Nội | L29: 0972237290 | N29: HONG | O29: 1 | P29: pengy6 | Q29: 2026-03-17 11:04:10 | R29: admin | S29: 2026-04-28 16:53:04 | V29: 4 | W29: HAIPHONG-越南 | X29: CIF | Y29: =IF(Z29="北部","1",IF(Z29="南部","2","")) -> 1 | Z29: 北部
A30: 2141020110 | B30: 越南黄天发贸易有限公司 | C30: 950 | D30: 1722956703705415681 | H30: Thanh Pho Ho Chi Minh | I30: CAT LAI PORT,HO CHI MINH-越南 | K30: 387 Phan Văn Trị,Phường Bình Lợi Trung, Thành phố Hồ Chí Minh | L30: 0937778293 | N30: Hoàng | O30: 1 | P30: zhangh31 | Q30: 2026-03-20 21:16:33 | R30: zhangh31 | S30: 2026-05-13 13:43:38 | V30: 4 | W30: CAT LAI PORT,HO CHI MINH-越南 | X30: CIF | Y30: =IF(Z30="北部","1",IF(Z30="南部","2","")) -> 2 | Z30: 南部
A31: 2141030020 | B31: 越南谅山龙霞一成员有限公司 | C31: 951 | D31: 343 | F31: Viet Nam | H31: Yen Vien | I31: YEN VIEN-越南 | K31: Số 132 đường Trần Phú, Phường Kỳ Lừa, Lạng Sơn | L31: 0942854827 | N31: Anh Long（谅山） | O31: 0 | P31: zhangh31 | Q31: 2026-03-20 21:24:22 | R31: zhangh31 | S31: 2026-03-23 10:47:47 | V31: 4 | W31: YEN VIEN-越南 | X31: CIF | Y31: =IF(Z31="北部","1",IF(Z31="南部","2","")) -> 1 | Z31: 北部
A32: 2141030020 | B32: 越南谅山龙霞一成员有限公司 | C32: 952 | D32: 343 | F32: Viet Nam | H32: Yen Vien | I32: YEN VIEN-越南 | K32: Số 9 đường trần đăng tuyển phường vũ ninh tỉnh bắc ninh | L32: 0985195083 | N32: Người Nhận（北宁） | O32: 0 | P32: zhangh31 | Q32: 2026-03-20 21:26:03 | R32: zhangh31 | S32: 2026-03-23 10:47:47 | V32: 4 | W32: YEN VIEN-越南 | X32: CIF | Y32: =IF(Z32="北部","1",IF(Z32="南部","2","")) -> 1 | Z32: 北部
A33: 2141030020 | B33: 越南谅山龙霞一成员有限公司 | C33: 953 | D33: 343 | H33: Yen Vien | I33: YEN VIEN-越南 | K33: 178 Lê Hồng Phong , Cốc Lếu, Lào Cai | L33: 0378003378- 0398101085 | N33: Sdt thủ kho（芒街） | O33: 0 | P33: zhangh31 | Q33: 2026-03-20 21:29:51 | R33: zhangh31 | S33: 2026-03-30 09:13:38 | V33: 4 | W33: YEN VIEN-越南 | X33: CIF | Y33: =IF(Z33="北部","1",IF(Z33="南部","2","")) -> 1 | Z33: 北部
A34: 2141030020 | B34: 越南谅山龙霞一成员有限公司 | C34: 954 | D34: 343 | F34: Viet Nam | H34: Yen Vien | I34: YEN VIEN-越南 | K34: Cầu gỗ quảng thành tỉnh quảng ninh | L34: 0762487280 | N34: Phạm chí tuấn（广宁） | O34: 0 | P34: zhangh31 | Q34: 2026-03-20 21:30:26 | R34: zhangh31 | S34: 2026-03-23 10:47:47 | V34: 4 | W34: YEN VIEN-越南 | X34: CIF | Y34: =IF(Z34="北部","1",IF(Z34="南部","2","")) -> 1 | Z34: 北部
A35: 2141020030 | B35: 越南味丹股份有限公司 | C35: 965 | D35: 340 | H35: Thanh Pho Ho Chi Minh | I35: CAT LAI PORT,HO CHI MINH-越南 | K35: QL 51, ấp 2, xã Phước Thái, Xã Phước Thái, Đồng Nai | L35: 0963122795 | N35: Chị Huyền | O35: 0 | P35: zhangh31 | Q35: 2026-03-25 14:17:23 | R35: zhangh31 | S35: 2026-05-09 12:06:23 | V35: 4 | W35: CAT LAI PORT,HO CHI MINH-越南 | X35: CIF | Y35: =IF(Z35="北部","1",IF(Z35="南部","2","")) -> 2 | Z35: 南部
A36: 2141020030 | B36: 越南味丹股份有限公司 | C36: 966 | D36: 340 | H36: Thanh Pho Ho Chi Minh | I36: CAT LAI PORT,HO CHI MINH-越南 | K36: QL 51, ấp 2, xã Phước Thái, Xã Phước Thái, Đồng Nai | L36: 0917846481 | N36: Chị Phương | O36: 0 | P36: zhangh31 | Q36: 2026-03-25 14:18:12 | R36: zhangh31 | S36: 2026-05-09 13:19:14 | V36: 4 | W36: CAT LAI PORT,HO CHI MINH-越南 | X36: CIF | Y36: =IF(Z36="北部","1",IF(Z36="南部","2","")) -> 2 | Z36: 南部
A37: 2141020030 | B37: 越南味丹股份有限公司 | C37: 967 | D37: 340 | H37: Thanh Pho Ho Chi Minh | I37: CAT LAI PORT,HO CHI MINH-越南 | K37: Lô D1, Đường D2, Khu công nghiệp Cát Lái - cụm 2, giai đoạn II, phường Cát Lái, TPHCM, Việt Nam | L37: 0917846481 | N37: Phương | O37: 0 | P37: zhangh31 | Q37: 2026-03-25 14:18:51 | R37: zhangh31 | S37: 2026-05-09 13:19:18 | V37: 4 | W37: CAT LAI PORT,HO CHI MINH-越南 | X37: CIF | Y37: =IF(Z37="北部","1",IF(Z37="南部","2","")) -> 2 | Z37: 南部
A38: 2141020030 | B38: 越南味丹股份有限公司 | C38: 968 | D38: 340 | H38: Yen Vien | I38: YEN VIEN-越南 | K38: khu Công nghiệp Quang Minh 2,thôn Phù Trì,Xã Quang Minh,Thành phố Hà Nội. | L38: 0975699585 | N38: Ms Hường | O38: 0 | P38: zhangh31 | Q38: 2026-03-25 14:19:19 | R38: zhangh31 | S38: 2026-05-13 13:42:45 | V38: 4 | W38: YEN VIEN-越南 | X38: CIF | Y38: =IF(Z38="北部","1",IF(Z38="南部","2","")) -> 1 | Z38: 北部
A39: 2141020030 | B39: 越南味丹股份有限公司 | C39: 969 | D39: 340 | H39: Da Nang | I39: DA NANG-越南 | K39: QL 130 Phạm Đình Hổ, Phường Hòa Khánh, Thành phố Đà Nẵng | L39: 0982156159 | N39: Anh Dinh | O39: 0 | P39: zhangh31 | Q39: 2026-03-25 14:19:49 | R39: zhangh31 | S39: 2026-05-13 13:42:48 | V39: 4 | W39: DA NANG-越南 | X39: CIF | Y39: =IF(Z39="北部","1",IF(Z39="南部","2","")) -> 1 | Z39: 北部
A40: 2141150010 | B40: 越南味丹股份有限公司(OEM) | C40: 970 | D40: 1982694991293399041 | F40: Viet Nam | H40: Thanh Pho Ho Chi Minh | I40: CAT LAI PORT,HO CHI MINH-越南 | K40: QL 51, ấp 2, xã Phước Thái, Xã Phước Thái, Đồng Nai | L40: 0917846481 | N40: Chị Phương | O40: 0 | P40: zhangh31 | Q40: 2026-03-25 14:30:36 | R40: zhangh31 | S40: 2026-03-25 14:30:56 | V40: 4 | W40: CAT LAI PORT,HO CHI MINH-越南 | X40: CIF | Y40: =IF(Z40="北部","1",IF(Z40="南部","2","")) -> 1 | Z40: 北部
A41: 2141030020 | B41: 越南谅山龙霞一成员有限公司 | C41: 975 | D41: 343 | I41: YEN VIEN-越南 | K41: Ngã 5 ninh dương , cảng quang phát 1 , phường mc 2 | L41: 0932603888 | N41: /（老街） | O41: 0 | P41: zhangh31 | Q41: 2026-03-30 09:14:25 | R41: zhangh31 | S41: 2026-03-30 09:14:25 | V41: 4 | W41: YEN VIEN-越南 | X41: CIF | Y41: =IF(Z41="北部","1",IF(Z41="南部","2","")) -> 1 | Z41: 北部
A42: 2141120020 | B42: 越南海阳安军一成员责任有限公司 | C42: 981 | D42: 1914275489241710593 | F42: Viet Nam | H42: Yen Vien | I42: YEN VIEN-越南 | K42: KM52 đường An Định (QL5A),Việt Hòa, Hải Dương | L42: 0903160889 | O42: 0 | P42: zhangh31 | Q42: 2026-04-02 08:13:24 | R42: zhangh31 | S42: 2026-04-02 08:13:30 | V42: 4 | W42: YEN VIEN-越南 | X42: CIF | Y42: =IF(Z42="北部","1",IF(Z42="南部","2","")) -> 1 | Z42: 北部
A43: 2141100030 | B43: 越南邻客贸易有限公司 | C43: 982 | D43: 1869942599901331458 | H43: Thanh Pho Ho Chi Minh | I43: CAT LAI PORT,HO CHI MINH-越南 | K43: Số 49, Đường Truông Bồng Bông, Phường Chánh Hiệp, Thành phố Hồ Chí Minh | L43: 0899021119 | O43: 1 | P43: zhangh31 | Q43: 2026-04-02 08:30:59 | R43: zhangh31 | S43: 2026-05-13 13:45:59 | V43: 4 | W43: CAT LAI PORT,HO CHI MINH-越南 | X43: CIF | Y43: =IF(Z43="北部","1",IF(Z43="南部","2","")) -> 2 | Z43: 南部
A44: 2141170010 | B44: 越南宝芳林有限责任公司 | C44: 985 | D44: 1997607182266089473 | I44: YEN VIEN-越南 | K44: NO13-LK13-04, Khu đất dịch vụ LK8, LK9, LK10, LK15, LK21, LK23, LK24, LK26, C6, TH17 đường Nguyễn Thanh Bình, Phường Hà Đông, TP Hà Nội, Việt Na | L44: 0765526888 | N44: TRẦN THỊ NGỌC ANH | O44: 0 | P44: admin | Q44: 2026-04-03 16:50:36 | R44: admin | S44: 2026-04-03 16:50:36 | V44: 4 | W44: YEN VIEN-越南 | X44: CIF | Y44: =IF(Z44="北部","1",IF(Z44="南部","2","")) -> 1 | Z44: 北部
A45: 2141170010 | B45: 越南宝芳林有限责任公司 | C45: 986 | D45: 1997607182266089473 | I45: YEN VIEN-越南 | K45: Khu thượng mại xã yên mỹ tỉnh hưng yên | L45: 0977771435 | N45: Ngọc（兴安） | O45: 0 | P45: admin | Q45: 2026-04-03 16:51:16 | R45: admin | S45: 2026-04-03 16:51:16 | V45: 4 | W45: YEN VIEN-越南 | X45: CIF | Y45: =IF(Z45="北部","1",IF(Z45="南部","2","")) -> 1 | Z45: 北部
A46: 2141050030 | B46: 越南平明果蔬有限公司（工业） | C46: 987 | D46: 1793939999033528320 | I46: HAIPHONG-越南 | K46: Tờ bản đồ số 15, Thôn Hạ, Xã An Hưng, Huyện An Dương, Thành phố Hải Phòng, Việt Nam | L46: 0904288089 | N46: Anh Trung | O46: 0 | P46: admin | Q46: 2026-04-03 16:52:52 | R46: admin | S46: 2026-04-03 16:52:52 | V46: 4 | W46: HAIPHONG-越南 | X46: CIF | Y46: =IF(Z46="北部","1",IF(Z46="南部","2","")) -> 1 | Z46: 北部
A47: 2141110020 | B47: 越南惠嘉进出口有限公司 | C47: 988 | D47: 1869970867165675521 | I47: YEN VIEN-越南 | K47: 77 Nguyễn Tất Thành, Phường Vĩnh Phúc, Tỉnh Phú Thọ | L47: 0365634443 | O47: 0 | P47: admin | Q47: 2026-04-03 16:54:04 | R47: admin | S47: 2026-04-03 16:54:04 | V47: 4 | W47: YEN VIEN-越南 | X47: CIF | Y47: =IF(Z47="北部","1",IF(Z47="南部","2","")) -> 1 | Z47: 北部
A48: 2141030060 | B48: 越南荷青综合贸易有限公司 | C48: 989 | D48: 1891749549555138562 | I48: YEN VIEN-越南 | K48: Trung tâm thương mại Đồng Đăng, Số 75, đường Hoàng Văn Thụ, Xã Đồng Đăng, Tỉnh Lạng Sơn | L48: 0969049348 | O48: 0 | P48: admin | Q48: 2026-04-03 16:54:53 | R48: admin | S48: 2026-04-03 16:54:53 | V48: 4 | W48: YEN VIEN-越南 | X48: CIF | Y48: =IF(Z48="北部","1",IF(Z48="南部","2","")) -> 1 | Z48: 北部
A49: 2141180010 | B49: 越南-安平发添加剂公司（食品工业） | C49: 1015 | D49: 2037451724620120066 | F49: Viet Nam | H49: Haiphong | I49: HAIPHONG-越南 | K49: Số 344 đường Hà Huy Tập, Xã Phù Đổng, Thành phố Hà Nội, Việt Nam | L49: 0919 999 893 | N49: HONG | O49: 0 | P49: pengy6 | Q49: 2026-04-23 14:33:32 | R49: admin | S49: 2026-04-28 16:53:04 | V49: 4 | W49: HAIPHONG-越南 | X49: CIF | Y49: =IF(Z49="北部","1",IF(Z49="南部","2","")) -> 1 | Z49: 北部
A50: 2141020030 | B50: 越南味丹股份有限公司 | C50: 1045 | D50: 340 | H50: Da Nang | I50: DA NANG-越南 | K50: Lô E, đường số 7,KCN Hoà Khánh, Phường Liên Chiểu, Thành phố Đà Nẵng, Việt Nam | L50: 0918136016 | N50: Mr Tâm | O50: 0 | P50: zhangh31 | Q50: 2026-05-06 09:42:11 | R50: zhangh31 | S50: 2026-05-13 13:42:52 | V50: 4 | W50: DA NANG-越南 | X50: CIF | Y50: =IF(Z50="北部","1",IF(Z50="南部","2","")) -> 1 | Z50: 北部
A51: 2141220010 | B51: 越南TIKTIOK海天越南店铺（电商） | C51: 1055 | D51: 2052947753788325890 | F51: Viet Nam | H51: Thanh Pho Ho Chi Minh | I51: CAT LAI PORT,HO CHI MINH-越南 | K51: Lô Đất LK, Đường số 2 và đường số 10, KCN Xuyên á, xã Mỹ Hạnh Bắc, huyện Đức Hòa, tỉnh Long An | L51: +840375495453 | N51: TRIEU THI NGOC ANH赵氏玉英 | O51: 1 | P51: luoqf | Q51: 2026-05-09 15:48:31 | R51: cails | S51: 2026-05-13 17:23:22 | V51: 3 | W51: CAT LAI PORT,HO CHI MINH-越南 | X51: CIF | Y51: =IF(Z51="北部","1",IF(Z51="南部","2","")) -> 2 | Z51: 南部
A52: 2141220030 | B52: 越南SHOPEE海天越南店铺（电商） | C52: 1056 | D52: 2053146902827712514 | F52: Viet Nam | H52: Thanh Pho Ho Chi Minh | I52: CAT LAI PORT,HO CHI MINH-越南 | K52: Lô Đất LK, Đường số 2 và đường số 10, KCN Xuyên á, xã Mỹ Hạnh Bắc, huyện Đức Hòa, tỉnh Long An | L52: +840375495453 | N52: TRIEU THI NGOC ANH赵氏玉英 | O52: 1 | P52: luoqf | Q52: 2026-05-10 00:53:36 | R52: cails | S52: 2026-05-15 08:17:56 | V52: 3 | W52: CAT LAI PORT,HO CHI MINH-越南 | X52: CIF | Y52: =IF(Z52="北部","1",IF(Z52="南部","2","")) -> 2 | Z52: 南部
A53: 2141220020 | B53: 越南LAZADA海天越南店铺（电商） | C53: 1057 | D53: 2053486211929817089 | F53: Viet Nam | H53: Thanh Pho Ho Chi Minh | I53: CAT LAI PORT,HO CHI MINH-越南 | K53: Lô Đất LK, Đường số 2 và đường số 10, KCN Xuyên á, xã Mỹ Hạnh Bắc, huyện Đức Hòa, tỉnh Long An Liên hệ: 0976467736 | L53: +840375495453 | N53: TRIEU THI NGOC ANH赵氏玉英 | O53: 1 | P53: luoqf | Q53: 2026-05-11 01:51:56 | R53: luoqf | S53: 2026-05-21 16:16:28 | V53: 3 | W53: CAT LAI PORT,HO CHI MINH-越南 | X53: CIF | Y53: =IF(Z53="北部","1",IF(Z53="南部","2","")) -> 2 | Z53: 南部
A54: 2141040020 | B54: 越南明缘进出口有限公司 | C54: 1060 | D54: 2053701606212939778 | H54: Yen Vien | I54: YEN VIEN-越南 | K54: Kho lưu bằng, kcn bắc duyên hải, tp lào cai tỉnh lào cai | L54: 0868251224 | N54: ĐẢO ĐỨC MINH | O54: 1 | P54: suny12 | Q54: 2026-05-11 17:12:10 | R54: zhangh31 | S54: 2026-05-27 17:45:42 | V54: 4 | W54: YEN VIEN-越南 | X54: CIF | Y54: =IF(Z54="北部","1",IF(Z54="南部","2","")) -> 1 | Z54: 北部
A55: 2141290010 | B55: 越南鸿发MC进出口有限公司 | C55: 1063 | D55: 2053761307470508033 | F55: Viet Nam | H55: Yen Vien | I55: YEN VIEN-越南 | K55: Ngã 5 ninh dương , cảng quang phát 1 , phường mc 2 | L55: 0913237269 | N55: NGUYỄN XUÂN HOÀN | O55: 1 | P55: suny12 | Q55: 2026-05-12 09:27:42 | R55: cails | S55: 2026-05-18 22:27:14 | V55: 4 | W55: YEN VIEN-越南 | X55: CIF | Y55: =IF(Z55="北部","1",IF(Z55="南部","2","")) -> 1 | Z55: 北部
A56: 2141190020 | B56: 越南卷芝贸易服务有限公司 | C56: 1069 | D56: 2054131309499428866 | F56: Viet Nam | H56: Yen Vien | I56: YEN VIEN-越南 | K56: Số 9 Trần Đăng Tuyển ,Vũ Ninh , Bắc Ninh | L56: 0387882186 | N56: VŨ XUÂN QUYẾN | O56: 1 | P56: suny12 | Q56: 2026-05-14 19:20:32 | R56: suny12 | S56: 2026-05-20 11:53:57 | V56: 4 | W56: YEN VIEN-越南 | X56: CIF | Y56: =IF(Z56="北部","1",IF(Z56="南部","2","")) -> 1 | Z56: 北部
A57: 2141190010 | B57: 越南福禄BG进出口有限公司 | C57: 1074 | D57: 2055239694974234625 | H57: Yen Vien | I57: YEN VIEN-越南 | K57: Tổ 3 phường đa mai tỉnh bắc ninh | L57: 0983915597 | N57: LƯƠNG VĂN PHÚC | O57: 1 | P57: suny12 | Q57: 2026-05-15 19:03:19 | R57: zhangh31 | S57: 2026-05-27 15:01:13 | V57: 4 | W57: YEN VIEN-越南 | X57: CIF | Y57: =IF(Z57="北部","1",IF(Z57="南部","2","")) -> 1 | Z57: 北部
A58: 2141020190 | B58: 越南亚洲化学股份有限公司（工业） | C58: 1084 | D58: 1937178454658990081 | I58: HAIPHONG-越南 | K58: Tờ bản đồ số 15, Tổ Dân Phố Hạ, Phường Hồng An, Thành phố Hải Phòng, Việt Nam | L58: 0922 882 022 | N58: Chị Thủy | O58: 0 | P58: zhangh31 | Q58: 2026-05-20 18:15:32 | R58: zhangh31 | S58: 2026-05-20 18:15:32 | V58: 4 | W58: HAIPHONG-越南 | X58: CIF | Y58: =IF(Z58="北部","1",IF(Z58="南部","2","")) -> 1 | Z58: 北部
A59: 2141020190 | B59: 越南亚洲化学股份有限公司（工业） | C59: 1085 | D59: 1937178454658990081 | I59: HAIPHONG-越南 | K59: Số 7, đường 9, KCN VietNam – Singapore (VSIP), Phù Chẩn, Từ Sơn, Bắc Ninh | L59: 0922 882 022 | N59: Chị Thủy | O59: 0 | P59: zhangh31 | Q59: 2026-05-20 18:16:15 | R59: zhangh31 | S59: 2026-05-20 18:16:15 | V59: 4 | W59: HAIPHONG-越南 | X59: CIF | Y59: =IF(Z59="北部","1",IF(Z59="南部","2","")) -> 1 | Z59: 北部

Sheet 客户地址筛选
A1: 客户名称 | B1: 客户编码 | C1: 客户仓库地址 | D1: 仓库联系人电话 | E1: 仓库联系人
A2: ='产品订单（暂不含工业物料，待更新物料编码及装运信息）'!K1 -> 越南黄天发贸易有限公司 | B2: ='产品订单（暂不含工业物料，待更新物料编码及装运信息）'!P1 -> 2141020110 | C2: {=_xlfn._xlws.FILTER(客户地址信息汇总!K:K,客户地址信息汇总!A:A=B2,"未找到地址")} -> 97/12 kinh dương vương p12 q6 | D2: =VLOOKUP(C2,客户地址信息汇总!K:N,2,FALSE()) -> 090 9853318 | E2: =VLOOKUP(C2,客户地址信息汇总!K:N,4,FALSE()) -> duy
C3: 387 Phan Văn Trị,Phường Bình Lợi Trung, Thành phố Hồ Chí Minh | D3: =VLOOKUP(C3,客户地址信息汇总!K:N,2,FALSE()) -> 0937778293 | E3: =VLOOKUP(C3,客户地址信息汇总!K:N,4,FALSE()) -> Hoàng
D4: =VLOOKUP(C4,客户地址信息汇总!K:N,2,FALSE()) -> #N/A | E4: =VLOOKUP(C4,客户地址信息汇总!K:N,4,FALSE()) -> #N/A
D5: =VLOOKUP(C5,客户地址信息汇总!K:N,2,FALSE()) -> #N/A | E5: =VLOOKUP(C5,客户地址信息汇总!K:N,4,FALSE()) -> #N/A
D6: =VLOOKUP(C6,客户地址信息汇总!K:N,2,FALSE()) -> #N/A | E6: =VLOOKUP(C6,客户地址信息汇总!K:N,4,FALSE()) -> #N/A
D7: =VLOOKUP(C7,客户地址信息汇总!K:N,2,FALSE()) -> #N/A | E7: =VLOOKUP(C7,客户地址信息汇总!K:N,4,FALSE()) -> #N/A
D8: =VLOOKUP(C8,客户地址信息汇总!K:N,2,FALSE()) -> #N/A | E8: =VLOOKUP(C8,客户地址信息汇总!K:N,4,FALSE()) -> #N/A

Sheet 成交确认书
B1: 成交确认书
B2: XÁC NHẬN GIAO DỊCH
F4: ="编号："&'产品订单（暂不含工业物料，待更新物料编码及装运信息）'!G2 -> 编号：20261001001
F5: ="Số: "&'产品订单（暂不含工业物料，待更新物料编码及装运信息）'!G2 -> Số: 20261001001 | P5: 休假日 | Q5: 补上班日
F6: ="日期："&K7 -> 日期：2026年10月1日 | J6: 合同签订日期 | K6: =TEXT('产品订单（暂不含工业物料，待更新物料编码及装运信息）'!G3,""" Ngày ""d"" Tháng ""M"" Năm ""yyyy") -> Ngày 1 Tháng 10 Năm 2026 | P6: Plaintext | Q6: Plaintext
F7: ="Ngày: "&K6 -> Ngày: Ngày 1 Tháng 10 Năm 2026 | J7: 合同签订日期 | K7: =TEXT('产品订单（暂不含工业物料，待更新物料编码及装运信息）'!G3,"yyyy年m月d日") -> 2026年10月1日
F8: ="签约地："&K8 -> 签约地：胡志明市，越南 | K8: 胡志明市，越南 | P8: 46026 | Q8: 46023
F9: ="Nơi ký: "&K9 -> Nơi ký: Thành phố Hồ Chí Minh, Việt Nam. | K9: Thành phố Hồ Chí Minh, Việt Nam. | P9: 46067 | Q9: 46024
P10: 46025 | Q10: 46081
B11: 甲方（“卖方”）：海天越南有限公司 | J11: 预计30日后的交付日期 | K11: =TEXT(IF(COUNTIF($Q$8:$Q$18,K7+30)>0,K7+30,WORKDAY(K7+30-1,1,$P$8:$P$70)),"yyyy年m月d日") -> 2026年11月2日 | P11: 46068 | Q11: 46151
B12: Bên A ("Bên Bán"): CÔNG TY TNHH HADAY VIỆT NAM | K12: =TEXT(K11,""" Ngày ""d"" Tháng ""M"" Năm ""yyyy") -> Ngày 2 Tháng 11 Năm 2026 | P12: 46069 | Q12: 46285
B13: 税号：0318185296 | P13: 46070 | Q13: 46305
B14: Mã số thuế: 0318185296 | P14: 46071 | Q14: 46432
B15: 地址：越南胡志明市新兴坊何辉集路168号 | P15: 46072 | Q15: 46502
B16: Địa chỉ: Số 168, Đường Hà Huy Tập, Phường Tân Hưng, Thành phố Hồ Chí Minh, Việt Nam | P16: 46073 | Q16: 46515
B17: 代表人：裴迎宾 | P17: 46074 | Q17: 46656
B18: Người đại diện: PEI,YINGBIN | P18: 46075 | Q18: 46669
B19: 职务：总经理 | P19: 46076
B20: Chức vụ: TỔNG GIÁM ĐỐC | P20: 46116
B21: 电话：+84-2854166016 | P21: 46117
B22: Điện thoại: +84-2854166016 | P22: 46118
P23: 46143
B24: ="乙方（“买方”）："&'产品订单（暂不含工业物料，待更新物料编码及装运信息）'!K1 -> 乙方（“买方”）：越南黄天发贸易有限公司 | P24: 46144
B25: ="Bên A ("&"Bên Bán"&"): "&'产品订单（暂不含工业物料，待更新物料编码及装运信息）'!K2 -> Bên A (Bên Bán): CÔNG TY TNHH THƯƠNG MẠI HOÀNG THIÊN PHÁT | P25: 46145
B26: ="税号："&'产品订单（暂不含工业物料，待更新物料编码及装运信息）'!P2 -> 税号：0316353410 | P26: 46146
B27: ="Mã số thuế: "&'产品订单（暂不含工业物料，待更新物料编码及装运信息）'!P2 -> Mã số thuế: 0316353410 | P27: 46147
B28: ="地址："&'产品订单（暂不含工业物料，待更新物料编码及装运信息）'!S5 -> 地址：越南胡志明市平盛郡潘文治路387号 | P28: 46192
B29: ="Địa chỉ: "&'产品订单（暂不含工业物料，待更新物料编码及装运信息）'!K3 -> Địa chỉ: 387 Phan Văn Trị, Phường Bình Lợi Trung, TP Hồ Chí Minh, Việt Nam. | P29: 46193
B30: ="代表人："&'产品订单（暂不含工业物料，待更新物料编码及装运信息）'!P4 -> 代表人：陈明黄 | P30: 46194
B31: ="Người đại diện: "&'产品订单（暂不含工业物料，待更新物料编码及装运信息）'!P3 -> Người đại diện: TRAN MINH HOANG | P31: 46290
B32: ="职务："&'产品订单（暂不含工业物料，待更新物料编码及装运信息）'!P6 -> 职务：总经理 | P32: 46291
B33: ="Chức vụ: "&'产品订单（暂不含工业物料，待更新物料编码及装运信息）'!P5 -> Chức vụ: TỔNG GIÁM ĐỐC | P33: 46292
B34: ="电话："&'产品订单（暂不含工业物料，待更新物料编码及装运信息）'!K4 -> 电话：0939368123 | P34: 46296
B35: ="Điện thoại: "&'产品订单（暂不含工业物料，待更新物料编码及装运信息）'!K4 -> Điện thoại: 0939368123 | P35: 46297
P36: 46298
P37: 46299
B38: 按照以下约定，买方同意采购、卖方同意销售以下产品： | P38: 46300
B39: Theo các thỏa thuận sau đây, Bên Mua đồng ý mua và Bên Bán đồng ý bán các sản phẩm dưới đây: | P39: 46301
B40: 1. 商品信息 (Thông tin Sản phẩm): | P40: 46302
B41: 序号 | C41: 品名及规格 | D41: 单位 | E41: 数量 | F41: 单价（未税） | G41: 金额（未税） | J41: 此表的数据会自动生成，无需编辑 | P41: 46388
A42: 1 | B42: (STT) | C42: (Tên hàng & Quy cách) | D42: (Đơn vị) | E42: (Số lượng) | F42: (Đơn giá - Chưa thuế) | G42: (Thành tiền - Chưa thuế) | J42: 自行删除空白行后另存PDF发送给客户即可 | P42: 46389
A43: 1 | B43: =A42 -> 1 | C43: =IFERROR(VLOOKUP(A42,'产品订单（暂不含工业物料，待更新物料编码及装运信息）'!$C$10:$H$127,6,0),"") -> HADAY XỐT NẤM HƯƠNG 300G*15 | D43: =IF(E43<>"","Thùng","") -> Thùng | E43: =IFERROR(VLOOKUP(J43,'产品订单（暂不含工业物料，待更新物料编码及装运信息）'!$D$10:$N$127,11,FALSE),"") -> 18 | F43: =IFERROR(VLOOKUP(C43,'产品订单（暂不含工业物料，待更新物料编码及装运信息）'!$H$10:$N$127,4,FALSE),"") -> 476800 | G43: =IFERROR(IF(E43*F43>0,E43*F43,""),"") -> 8582400 | J43: =IFERROR(VLOOKUP(A42,'产品订单（暂不含工业物料，待更新物料编码及装运信息）'!$C$10:$D$127,2,0),"") -> 89502130001 | P43: 46390
A44: 2 | B44: =A43 -> 1 | C44: =IFERROR(VLOOKUP(A42,'产品订单（暂不含工业物料，待更新物料编码及装运信息）'!$C$10:$J$127,8,0),"") -> 海天牌香菇酱300g*15 | D44: =IF(E43<>"","箱","") -> 箱 | J44: =IFERROR(VLOOKUP(A43,'产品订单（暂不含工业物料，待更新物料编码及装运信息）'!$C$10:$D$127,2,0),"") -> 89502130001 | P44: 46423
A45: 2 | B45: =A44 -> 2 | C45: =IFERROR(VLOOKUP(A44,'产品订单（暂不含工业物料，待更新物料编码及装运信息）'!$C$10:$H$127,6,0),"") -> HADAY DẦU MÈ 250ML*12 | D45: =IF(E45<>"","Thùng","") -> Thùng | E45: =IFERROR(VLOOKUP(J45,'产品订单（暂不含工业物料，待更新物料编码及装运信息）'!$D$10:$N$127,11,FALSE),"") -> 14 | F45: =IFERROR(VLOOKUP(C45,'产品订单（暂不含工业物料，待更新物料编码及装运信息）'!$H$10:$N$127,4,FALSE),"") -> 546500 | G45: =IFERROR(IF(E45*F45>0,E45*F45,""),"") -> 7651000 | J45: =IFERROR(VLOOKUP(A44,'产品订单（暂不含工业物料，待更新物料编码及装运信息）'!$C$10:$D$127,2,0),"") -> 89730225001 | P45: 46424
A46: 3 | B46: =A45 -> 2 | C46: =IFERROR(VLOOKUP(A44,'产品订单（暂不含工业物料，待更新物料编码及装运信息）'!$C$10:$J$127,8,0),"") -> 海天牌芝麻香油250ML*12 | D46: =IF(E45<>"","箱","") -> 箱 | J46: =IFERROR(VLOOKUP(A45,'产品订单（暂不含工业物料，待更新物料编码及装运信息）'!$C$10:$D$127,2,0),"") -> 89730225001 | P46: 46425
A47: 3 | B47: =A46 -> 3 | C47: =IFERROR(VLOOKUP(A46,'产品订单（暂不含工业物料，待更新物料编码及装运信息）'!$C$10:$H$127,6,0),"") -> HADAY GIẤM GẠO 800ML*12 | D47: =IF(E47<>"","Thùng","") -> Thùng | E47: =IFERROR(VLOOKUP(J47,'产品订单（暂不含工业物料，待更新物料编码及装运信息）'!$D$10:$N$127,11,FALSE),"") -> 28 | F47: =IFERROR(VLOOKUP(C47,'产品订单（暂不含工业物料，待更新物料编码及装运信息）'!$H$10:$N$127,4,FALSE),"") -> 136000 | G47: =IFERROR(IF(E47*F47>0,E47*F47,""),"") -> 3808000 | J47: =IFERROR(VLOOKUP(A46,'产品订单（暂不含工业物料，待更新物料编码及装运信息）'!$C$10:$D$127,2,0),"") -> 89201580001 | P47: 46426
